Workbook
Name Ak: #REF!
Name NOB: #REF!
Name Source: #REF!
Name SRCE: #REF!
Name Style: #REF!
Name TOS: #REF!
Name Type: #REF!
Name VLOOKUP: #REF!

Sheet Weekwise summary
A2: Collection Executive | B2: Week 1 | C2: Week 2 | D2: Week 3 | E2: Week 4 | F2: Week 5 | G2: Grand Total
A3: Dues
A4: Monish | B4: 7155724.4 | C4: 5763300 | D4: 0 | E4: 0 | F4: 0 | G4: =SUM(B4:F4) -> 12919024
A5: Melvyn | B5: 3459118.8 | C5: 7468102.6 | D5: 0 | E5: 0 | F5: 0 | G5: =SUM(B5:F5) -> 10927221
A6: Walid | B6: 7881000.9 | C6: 8410159.6 | D6: 0 | E6: 0 | F6: 0 | G6: =SUM(B6:F6) -> 16291161
A7: Anna | B7: 1325391.9 | C7: 1606659.9 | D7: 0 | E7: 0 | F7: 0 | G7: =SUM(B7:F7) -> 2932051.8
A8: UAQ Sub Total | B8: =SUM(B4:B7) -> 19821236 | C8: =SUM(C4:C7) -> 23248222 | D8: =SUM(D4:D7) -> 0 | E8: =SUM(E4:E7) -> 0 | F8: =SUM(F4:F7) -> 0 | G8: =SUM(B8:F8) -> 43069458
A9: Ruhul | B9: 498000 | C9: 1335821 | D9: 0 | E9: 0 | F9: 0 | G9: =SUM(B9:F9) -> 1833821
A10: Ali | B10: 3009971 | C10: 3907729 | D10: 0 | E10: 0 | F10: 0 | G10: =SUM(B10:F10) -> 6917700
A11: Anirudh | B11: 4491953.5 | C11: 5334775.2 | D11: 0 | E11: 0 | F11: 0 | G11: =SUM(B11:F11) -> 9826728.7
A12: Aqsa | B12: 5572975 | C12: 6186990.1 | D12: 0 | E12: 0 | F12: 0 | G12: =SUM(B12:F12) -> 11759965
A13: Karan | B13: 2647104 | C13: 4343823 | D13: 0 | E13: 0 | F13: 0 | G13: =SUM(B13:F13) -> 6990927
A14: Rajiv | B14: 4660561 | C14: 6841253 | D14: 0 | E14: 0 | F14: 0 | G14: =SUM(B14:F14) -> 11501814
A15: Vinod | B15: 431500 | C15: 1625439.4 | D15: 0 | E15: 0 | F15: 0 | G15: =SUM(B15:F15) -> 2056939.4
A16: Sarmad | B16: 5883054.9 | C16: 8708469.5 | D16: 0 | E16: 0 | F16: 0 | G16: =SUM(B16:F16) -> 14591524
A17: Zeba | B17: 4831508.7 | C17: 5672744.5 | D17: 0 | E17: 0 | F17: 0 | G17: =SUM(B17:F17) -> 10504253
A18: Oksana | B18: 4259004 | C18: 6132007 | D18: 0 | E18: 0 | F18: 0 | G18: =SUM(B18:F18) -> 10391011
A19: Omar | B19: 2739365.4 | C19: 7010906.2 | D19: 0 | E19: 0 | F19: 0 | G19: =SUM(B19:F19) -> 9750271.5
A20: Sid | B20: 4101645 | C20: 4682952.4 | D20: 0 | E20: 0 | F20: 0 | G20: =SUM(B20:F20) -> 8784597.4
... A30: Abdellatif | B30: 3923405.7 | C30: 5716735.7 | D30: 0 | E30: 0 | F30: 0 | G30: =SUM(B30:F30) -> 9640141.4
A31: SOBHA Sub Total | B31: =SUM(B9:B30) -> 69786823 | C31: =SUM(C9:C30) -> 1.0447751e+08 | D31: =SUM(D9:D30) -> 0 | E31: =SUM(E9:E30) -> 0 | F31: =SUM(F9:F30) -> 0 | G31: =SUM(B31:F31) -> 1.7426434e+08
A32: Total Dues | B32: =SUM(B31,B8) -> 89608059 | C32: =SUM(C31,C8) -> 1.2772573e+08 | D32: =SUM(D31,D8) -> 0 | E32: =SUM(E31,E8) -> 0 | F32: =SUM(F31,F8) -> 0 | G32: =SUM(B32:F32) -> 2.1733379e+08
A33: Advances
A34: Abdulla | B34: 1527000 | C34: 3000682 | D34: 0 | E34: 0 | F34: 0 | G34: =SUM(B34:F34) -> 4527682
A35: Ateev | B35: 4361320 | C35: 7551735 | D35: 0 | E35: 0 | F35: 0 | G35: =SUM(B35:F35) -> 11913055
A36: Ayari | B36: 3577590 | C36: 2781023 | D36: 0 | E36: 0 | F36: 0 | G36: =SUM(B36:F36) -> 6358613
A37: Nischitha | B37: 0 | C37: 0 | D37: 0 | E37: 0 | F37: 0 | G37: =SUM(B37:F37) -> 0
A38: Sherif | B38: 1778643 | C38: 3396199 | D38: 0 | E38: 0 | F38: 0 | G38: =SUM(B38:F38) -> 5174842
A39: Wael | B39: 2246551 | C39: 4503635 | D39: 0 | E39: 0 | F39: 0 | G39: =SUM(B39:F39) -> 6750186
A40: Yogesh | B40: 1236697 | C40: 1914006 | D40: 0 | E40: 0 | F40: 0 | G40: =SUM(B40:F40) -> 3150703
A41: Krizia | B41: 1814275 | C41: 2765789.6 | D41: 0 | E41: 0 | F41: 0 | G41: =SUM(B41:F41) -> 4580064.6
A42: Vijay | B42: 1700796 | C42: 2601344 | D42: 0 | E42: 0 | F42: 0 | G42: =SUM(B42:F42) -> 4302140
A43: Jaidev | B43: 1520232 | C43: 3888415.5 | D43: 0 | E43: 0 | F43: 0 | G43: =SUM(B43:F43) -> 5408647.5
A44: Basma | B44: 4555749 | C44: 6188354 | D44: 0 | E44: 0 | F44: 0 | G44: =SUM(B44:F44) -> 10744103
A45: Noha | B45: 3651990 | C45: 1561248.6 | D45: 0 | E45: 0 | F45: 0 | G45: =SUM(B45:F45) -> 5213238.6
A46: Total Advances | B46: =SUM(B34:B45) -> 27970843 | C46: =SUM(C34:C45) -> 40152432 | D46: =SUM(D34:D45) -> 0 | E46: =SUM(E34:E45) -> 0 | F46: =SUM(F34:F45) -> 0 | G46: =SUM(B46:F46) -> 68123275
A47: Grand Total | B47: =SUM(B32,B46) -> 1.175789e+08 | C47: =SUM(C32,C46) -> 1.6787817e+08 | D47: =SUM(D32,D46) -> 0 | E47: =SUM(E32,E46) -> 0 | F47: =SUM(F32,F46) -> 0 | G47: =SUM(B47:F47) -> 2.8545707e+08

Sheet Datewise Summary
A1: 46142
A2: Collection Executive | B2: =A1+1 -> 46143 | C2: =B2+1 -> 46144 | D2: =C2+1 -> 46145 | E2: =D2+1 -> 46146 | F2: =E2+1 -> 46147 | G2: =F2+1 -> 46148 | H2: =G2+1 -> 46149 | I2: =H2+1 -> 46150 | J2: =I2+1 -> 46151 | ... AF2: =AE2+1 -> 46173 | AG2: Grand Total
A3: Dues
A4: Monish | B4: 4098413.4 | C4: 0 | D4: 0 | E4: 3057311 | F4: 1572743 | G4: 1730345.1 | H4: 2460211.9 | I4: 0 | J4: 0 | K4: 0 | L4: 0 | M4: 0 | N4: 0 | O4: 0 | P4: 0 | Q4: 0 | R4: 0 | S4: 0 | T4: 0 | U4: 0 | V4: 0 | W4: 0 | X4: 0 | Y4: 0 | Z4: 0 | AA4: 0 | AB4: 0 | AC4: 0 | AD4: 0 | AE4: 0 | AF4: 0 | AG4: =SUM(B4:AF4) -> 12919024
A5: Walid | B5: 2879518.4 | C5: 0 | D5: 0 | E5: 5001482.6 | F5: 3818560.8 | G5: 2591192.1 | H5: 2000406.8 | I5: 0 | J5: 0 | K5: 0 | L5: 0 | M5: 0 | N5: 0 | O5: 0 | P5: 0 | Q5: 0 | R5: 0 | S5: 0 | T5: 0 | U5: 0 | V5: 0 | W5: 0 | X5: 0 | Y5: 0 | Z5: 0 | AA5: 0 | AB5: 0 | AC5: 0 | AD5: 0 | AE5: 0 | AF5: 0 | AG5: =SUM(B5:AF5) -> 16291161
A6: Melvyn | B6: 1145061.6 | C6: 0 | D6: 0 | E6: 2314057.3 | F6: 2340843 | G6: 2509495.1 | H6: 2617764.5 | I6: 0 | J6: 0 | K6: 0 | L6: 0 | M6: 0 | N6: 0 | O6: 0 | P6: 0 | Q6: 0 | R6: 0 | S6: 0 | T6: 0 | U6: 0 | V6: 0 | W6: 0 | X6: 0 | Y6: 0 | Z6: 0 | AA6: 0 | AB6: 0 | AC6: 0 | AD6: 0 | AE6: 0 | AF6: 0 | AG6: =SUM(B6:AF6) -> 10927221
A7: Anna | B7: 0 | C7: 0 | D7: 0 | E7: 1325391.9 | F7: 587649 | G7: 598975.15 | H7: 420035.73 | I7: 0 | J7: 0 | K7: 0 | L7: 0 | M7: 0 | N7: 0 | O7: 0 | P7: 0 | Q7: 0 | R7: 0 | S7: 0 | T7: 0 | U7: 0 | V7: 0 | W7: 0 | X7: 0 | Y7: 0 | Z7: 0 | AA7: 0 | AB7: 0 | AC7: 0 | AD7: 0 | AE7: 0 | AF7: 0 | AG7: =SUM(B7:AF7) -> 2932051.8
A8: UAQ Sub Total | B8: =SUM(B4:B7) -> 8122993.3 | C8: =SUM(C4:C7) -> 0 | D8: =SUM(D4:D7) -> 0 | E8: =SUM(E4:E7) -> 11698243 | F8: =SUM(F4:F7) -> 8319795.8 | G8: =SUM(G4:G7) -> 7430007.4 | H8: =SUM(H4:H7) -> 7498418.9 | I8: =SUM(I4:I7) -> 0 | ... AF8: =SUM(AF4:AF7) -> 0 | AG8: =SUM(B8:AF8) -> 43069458
A9: Ruhul | B9: 200000 | C9: 0 | D9: 0 | E9: 298000 | F9: 291447 | G9: 519864 | H9: 524510 | I9: 0 | J9: 0 | K9: 0 | L9: 0 | M9: 0 | N9: 0 | O9: 0 | P9: 0 | Q9: 0 | R9: 0 | S9: 0 | T9: 0 | U9: 0 | V9: 0 | W9: 0 | X9: 0 | Y9: 0 | Z9: 0 | AA9: 0 | AB9: 0 | AC9: 0 | AD9: 0 | AE9: 0 | AF9: 0 | AG9: =SUM(B9:AF9) -> 1833821
A10: Ali | B10: 1476660 | C10: 0 | D10: 0 | E10: 1533311 | F10: 1549723 | G10: 1575286 | H10: 782720 | I10: 0 | J10: 0 | K10: 0 | L10: 0 | M10: 0 | N10: 0 | O10: 0 | P10: 0 | Q10: 0 | R10: 0 | S10: 0 | T10: 0 | U10: 0 | V10: 0 | W10: 0 | X10: 0 | Y10: 0 | Z10: 0 | AA10: 0 | AB10: 0 | AC10: 0 | AD10: 0 | AE10: 0 | AF10: 0 | AG10: =SUM(B10:AF10) -> 6917700
A11: Anirudh | B11: 2487142.3 | C11: 0 | D11: 0 | E11: 2004811.2 | F11: 1716589.1 | G11: 1800817 | H11: 1817369.1 | I11: 0 | J11: 0 | K11: 0 | L11: 0 | M11: 0 | N11: 0 | O11: 0 | P11: 0 | Q11: 0 | R11: 0 | S11: 0 | T11: 0 | U11: 0 | V11: 0 | W11: 0 | X11: 0 | Y11: 0 | Z11: 0 | AA11: 0 | AB11: 0 | AC11: 0 | AD11: 0 | AE11: 0 | AF11: 0 | AG11: =SUM(B11:AF11) -> 9826728.7
A12: Aqsa | B12: 1471944 | C12: 0 | D12: 0 | E12: 4101031 | F12: 2272475.6 | G12: 1935737.5 | H12: 1978777 | I12: 0 | J12: 0 | K12: 0 | L12: 0 | M12: 0 | N12: 0 | O12: 0 | P12: 0 | Q12: 0 | R12: 0 | S12: 0 | T12: 0 | U12: 0 | V12: 0 | W12: 0 | X12: 0 | Y12: 0 | Z12: 0 | AA12: 0 | AB12: 0 | AC12: 0 | AD12: 0 | AE12: 0 | AF12: 0 | AG12: =SUM(B12:AF12) -> 11759965
A13: Karan | B13: 1426030 | C13: 0 | D13: 0 | E13: 1221074 | F13: 1621551 | G13: 1410721 | H13: 1311551 | I13: 0 | J13: 0 | K13: 0 | L13: 0 | M13: 0 | N13: 0 | O13: 0 | P13: 0 | Q13: 0 | R13: 0 | S13: 0 | T13: 0 | U13: 0 | V13: 0 | W13: 0 | X13: 0 | Y13: 0 | Z13: 0 | AA13: 0 | AB13: 0 | AC13: 0 | AD13: 0 | AE13: 0 | AF13: 0 | AG13: =SUM(B13:AF13) -> 6990927
A14: Rajiv | B14: 2541514 | C14: 0 | D14: 0 | E14: 2119047 | F14: 2211363 | G14: 2350313 | H14: 2279577 | I14: 0 | J14: 0 | K14: 0 | L14: 0 | M14: 0 | N14: 0 | O14: 0 | P14: 0 | Q14: 0 | R14: 0 | S14: 0 | T14: 0 | U14: 0 | V14: 0 | W14: 0 | X14: 0 | Y14: 0 | Z14: 0 | AA14: 0 | AB14: 0 | AC14: 0 | AD14: 0 | AE14: 0 | AF14: 0 | AG14: =SUM(B14:AF14) -> 11501814
A15: Vinod | B15: 202000 | C15: 0 | D15: 0 | E15: 229500 | F15: 1092125.9 | G15: 333313.5 | H15: 200000 | I15: 0 | J15: 0 | K15: 0 | L15: 0 | M15: 0 | N15: 0 | O15: 0 | P15: 0 | Q15: 0 | R15: 0 | S15: 0 | T15: 0 | U15: 0 | V15: 0 | W15: 0 | X15: 0 | Y15: 0 | Z15: 0 | AA15: 0 | AB15: 0 | AC15: 0 | AD15: 0 | AE15: 0 | AF15: 0 | AG15: =SUM(B15:AF15) -> 2056939.4
A16: Sarmad | B16: 2737489 | C16: 0 | D16: 0 | E16: 3145565.9 | F16: 3117450.5 | G16: 3092921 | H16: 2498098 | I16: 0 | J16: 0 | K16: 0 | L16: 0 | M16: 0 | N16: 0 | O16: 0 | P16: 0 | Q16: 0 | R16: 0 | S16: 0 | T16: 0 | U16: 0 | V16: 0 | W16: 0 | X16: 0 | Y16: 0 | Z16: 0 | AA16: 0 | AB16: 0 | AC16: 0 | AD16: 0 | AE16: 0 | AF16: 0 | AG16: =SUM(B16:AF16) -> 14591524
A17: Zeba | B17: 2555920.7 | C17: 0 | D17: 0 | E17: 2275588 | F17: 2008035.5 | G17: 2506470 | H17: 1158239 | I17: 0 | J17: 0 | K17: 0 | L17: 0 | M17: 0 | N17: 0 | O17: 0 | P17: 0 | Q17: 0 | R17: 0 | S17: 0 | T17: 0 | U17: 0 | V17: 0 | W17: 0 | X17: 0 | Y17: 0 | Z17: 0 | AA17: 0 | AB17: 0 | AC17: 0 | AD17: 0 | AE17: 0 | AF17: 0 | AG17: =SUM(B17:AF17) -> 10504253
A18: Oksana | B18: 2128529 | C18: 0 | D18: 0 | E18: 2130475 | F18: 2049878 | G18: 2022619 | H18: 2059510 | I18: 0 | J18: 0 | K18: 0 | L18: 0 | M18: 0 | N18: 0 | O18: 0 | P18: 0 | Q18: 0 | R18: 0 | S18: 0 | T18: 0 | U18: 0 | V18: 0 | W18: 0 | X18: 0 | Y18: 0 | Z18: 0 | AA18: 0 | AB18: 0 | AC18: 0 | AD18: 0 | AE18: 0 | AF18: 0 | AG18: =SUM(B18:AF18) -> 10391011
A19: Omar | B19: 669971 | C19: 0 | D19: 0 | E19: 2069394.4 | F19: 2116543.1 | G19: 2722870.3 | H19: 2171492.8 | I19: 0 | J19: 0 | K19: 0 | L19: 0 | M19: 0 | N19: 0 | O19: 0 | P19: 0 | Q19: 0 | R19: 0 | S19: 0 | T19: 0 | U19: 0 | V19: 0 | W19: 0 | X19: 0 | Y19: 0 | Z19: 0 | AA19: 0 | AB19: 0 | AC19: 0 | AD19: 0 | AE19: 0 | AF19: 0 | AG19: =SUM(B19:AF19) -> 9750271.5
A20: Yusuf | B20: 329528.08 | C20: 0 | D20: 0 | E20: 2004150.4 | F20: 1929236.1 | G20: 1590901.2 | H20: 1486579 | I20: 0 | J20: 0 | K20: 0 | L20: 0 | M20: 0 | N20: 0 | O20: 0 | P20: 0 | Q20: 0 | R20: 0 | S20: 0 | T20: 0 | U20: 0 | V20: 0 | W20: 0 | X20: 0 | Y20: 0 | Z20: 0 | AA20: 0 | AB20: 0 | AC20: 0 | AD20: 0 | AE20: 0 | AF20: 0 | AG20: =SUM(B20:AF20) -> 7340394.8
... A30: Moustafa | B30: 1584660 | C30: 0 | D30: 0 | E30: 1142000 | F30: 1014000 | G30: 1029590 | H30: 1101602 | I30: 0 | J30: 0 | K30: 0 | L30: 0 | M30: 0 | N30: 0 | O30: 0 | P30: 0 | Q30: 0 | R30: 0 | S30: 0 | T30: 0 | U30: 0 | V30: 0 | W30: 0 | X30: 0 | Y30: 0 | Z30: 0 | AA30: 0 | AB30: 0 | AC30: 0 | AD30: 0 | AE30: 0 | AF30: 0 | AG30: =SUM(B30:AF30) -> 5871852
A31: SOBHA Sub Total | B31: =SUM(B9:B30) -> 32261966 | C31: =SUM(C9:C30) -> 0 | D31: =SUM(D9:D30) -> 0 | E31: =SUM(E9:E30) -> 37524857 | F31: =SUM(F9:F30) -> 35199787 | G31: =SUM(G9:G30) -> 34839227 | H31: =SUM(H9:H30) -> 34438498 | I31: =SUM(I9:I30) -> 0 | ... AF31: =SUM(AF9:AF30) -> 0 | AG31: =SUM(B31:AF31) -> 1.7426434e+08
A32: Total Dues | B32: =SUM(B31,B8) -> 40384959 | C32: =SUM(C31,C8) -> 0 | D32: =SUM(D31,D8) -> 0 | E32: =SUM(E31,E8) -> 49223100 | F32: =SUM(F31,F8) -> 43519583 | G32: =SUM(G31,G8) -> 42269235 | H32: =SUM(H31,H8) -> 41936917 | I32: =SUM(I31,I8) -> 0 | ... AF32: =SUM(AF31,AF8) -> 0 | AG32: =SUM(B32:AF32) -> 2.1733379e+08
A33: Advances
A34: Abdulla | B34: 527000 | C34: 0 | D34: 0 | E34: 1000000 | F34: 1000629 | G34: 1000053 | H34: 1000000 | I34: 0 | J34: 0 | K34: 0 | L34: 0 | M34: 0 | N34: 0 | O34: 0 | P34: 0 | Q34: 0 | R34: 0 | S34: 0 | T34: 0 | U34: 0 | V34: 0 | W34: 0 | X34: 0 | Y34: 0 | Z34: 0 | AA34: 0 | AB34: 0 | AC34: 0 | AD34: 0 | AE34: 0 | AF34: 0 | AG34: =SUM(B34:AF34) -> 4527682
A35: Ateev | B35: 1903600 | C35: 0 | D35: 0 | E35: 2457720 | F35: 2603374 | G35: 2436483 | H35: 2511878 | I35: 0 | J35: 0 | K35: 0 | L35: 0 | M35: 0 | N35: 0 | O35: 0 | P35: 0 | Q35: 0 | R35: 0 | S35: 0 | T35: 0 | U35: 0 | V35: 0 | W35: 0 | X35: 0 | Y35: 0 | Z35: 0 | AA35: 0 | AB35: 0 | AC35: 0 | AD35: 0 | AE35: 0 | AF35: 0 | AG35: =SUM(B35:AF35) -> 11913055
A36: Ayari | B36: 2577558 | C36: 0 | D36: 0 | E36: 1000032 | F36: 1035731 | G36: 745292 | H36: 1000000 | I36: 0 | J36: 0 | K36: 0 | L36: 0 | M36: 0 | N36: 0 | O36: 0 | P36: 0 | Q36: 0 | R36: 0 | S36: 0 | T36: 0 | U36: 0 | V36: 0 | W36: 0 | X36: 0 | Y36: 0 | Z36: 0 | AA36: 0 | AB36: 0 | AC36: 0 | AD36: 0 | AE36: 0 | AF36: 0 | AG36: =SUM(B36:AF36) -> 6358613
A37: Nischitha | B37: 0 | C37: 0 | D37: 0 | E37: 0 | F37: 0 | G37: 0 | H37: 0 | I37: 0 | J37: 0 | K37: 0 | L37: 0 | M37: 0 | N37: 0 | O37: 0 | P37: 0 | Q37: 0 | R37: 0 | S37: 0 | T37: 0 | U37: 0 | V37: 0 | W37: 0 | X37: 0 | Y37: 0 | Z37: 0 | AA37: 0 | AB37: 0 | AC37: 0 | AD37: 0 | AE37: 0 | AF37: 0 | AG37: =SUM(B37:AF37) -> 0
A38: Basma | B38: 2008082 | C38: 0 | D38: 0 | E38: 2547667 | F38: 2011915 | G38: 2176439 | H38: 2000000 | I38: 0 | J38: 0 | K38: 0 | L38: 0 | M38: 0 | N38: 0 | O38: 0 | P38: 0 | Q38: 0 | R38: 0 | S38: 0 | T38: 0 | U38: 0 | V38: 0 | W38: 0 | X38: 0 | Y38: 0 | Z38: 0 | AA38: 0 | AB38: 0 | AC38: 0 | AD38: 0 | AE38: 0 | AF38: 0 | AG38: =SUM(B38:AF38) -> 10744103
A39: Sherif | B39: 1000589 | C39: 0 | D39: 0 | E39: 778054 | F39: 1000175 | G39: 1000000 | H39: 1396024 | I39: 0 | J39: 0 | K39: 0 | L39: 0 | M39: 0 | N39: 0 | O39: 0 | P39: 0 | Q39: 0 | R39: 0 | S39: 0 | T39: 0 | U39: 0 | V39: 0 | W39: 0 | X39: 0 | Y39: 0 | Z39: 0 | AA39: 0 | AB39: 0 | AC39: 0 | AD39: 0 | AE39: 0 | AF39: 0 | AG39: =SUM(B39:AF39) -> 5174842
A40: Wael | B40: 1036362 | C40: 0 | D40: 0 | E40: 1210189 | F40: 2001934 | G40: 1501564.6 | H40: 1000136.4 | I40: 0 | J40: 0 | K40: 0 | L40: 0 | M40: 0 | N40: 0 | O40: 0 | P40: 0 | Q40: 0 | R40: 0 | S40: 0 | T40: 0 | U40: 0 | V40: 0 | W40: 0 | X40: 0 | Y40: 0 | Z40: 0 | AA40: 0 | AB40: 0 | AC40: 0 | AD40: 0 | AE40: 0 | AF40: 0 | AG40: =SUM(B40:AF40) -> 6750186
A41: Yogesh | B41: 436577 | C41: 0 | D41: 0 | E41: 800120 | F41: 613976 | G41: 616706 | H41: 683324 | I41: 0 | J41: 0 | K41: 0 | L41: 0 | M41: 0 | N41: 0 | O41: 0 | P41: 0 | Q41: 0 | R41: 0 | S41: 0 | T41: 0 | U41: 0 | V41: 0 | W41: 0 | X41: 0 | Y41: 0 | Z41: 0 | AA41: 0 | AB41: 0 | AC41: 0 | AD41: 0 | AE41: 0 | AF41: 0 | AG41: =SUM(B41:AF41) -> 3150703
A42: Krizia | B42: 1113130 | C42: 0 | D42: 0 | E42: 701145 | F42: 509301 | G42: 509071.56 | H42: 1747417 | I42: 0 | J42: 0 | K42: 0 | L42: 0 | M42: 0 | N42: 0 | O42: 0 | P42: 0 | Q42: 0 | R42: 0 | S42: 0 | T42: 0 | U42: 0 | V42: 0 | W42: 0 | X42: 0 | Y42: 0 | Z42: 0 | AA42: 0 | AB42: 0 | AC42: 0 | AD42: 0 | AE42: 0 | AF42: 0 | AG42: =SUM(B42:AF42) -> 4580064.6
A43: Vijay | B43: 1000698 | C43: 0 | D43: 0 | E43: 700098 | F43: 601000 | G43: 1000215 | H43: 1000129 | I43: 0 | J43: 0 | K43: 0 | L43: 0 | M43: 0 | N43: 0 | O43: 0 | P43: 0 | Q43: 0 | R43: 0 | S43: 0 | T43: 0 | U43: 0 | V43: 0 | W43: 0 | X43: 0 | Y43: 0 | Z43: 0 | AA43: 0 | AB43: 0 | AC43: 0 | AD43: 0 | AE43: 0 | AF43: 0 | AG43: =SUM(B43:AF43) -> 4302140
A44: Jaidev | B44: 519046 | C44: 0 | D44: 0 | E44: 1001186 | F44: 1039578.5 | G44: 1004599 | H44: 1844238 | I44: 0 | J44: 0 | K44: 0 | L44: 0 | M44: 0 | N44: 0 | O44: 0 | P44: 0 | Q44: 0 | R44: 0 | S44: 0 | T44: 0 | U44: 0 | V44: 0 | W44: 0 | X44: 0 | Y44: 0 | Z44: 0 | AA44: 0 | AB44: 0 | AC44: 0 | AD44: 0 | AE44: 0 | AF44: 0 | AG44: =SUM(B44:AF44) -> 5408647.5
A45: Noha | B45: 1430954 | C45: 0 | D45: 0 | E45: 2221036 | F45: 551059.61 | G45: 358881 | H45: 651308 | I45: 0 | J45: 0 | K45: 0 | L45: 0 | M45: 0 | N45: 0 | O45: 0 | P45: 0 | Q45: 0 | R45: 0 | S45: 0 | T45: 0 | U45: 0 | V45: 0 | W45: 0 | X45: 0 | Y45: 0 | Z45: 0 | AA45: 0 | AB45: 0 | AC45: 0 | AD45: 0 | AE45: 0 | AF45: 0 | AG45: =SUM(B45:AF45) -> 5213238.6
A46: Total Advances | B46: =SUM(B34:B45) -> 13553596 | C46: =SUM(C34:C45) -> 0 | D46: =SUM(D34:D45) -> 0 | E46: =SUM(E34:E45) -> 14417247 | F46: =SUM(F34:F45) -> 12968673 | G46: =SUM(G34:G45) -> 12349304 | H46: =SUM(H34:H45) -> 14834454 | I46: =SUM(I34:I45) -> 0 | ... AF46: =SUM(AF34:AF45) -> 0 | AG46: =SUM(B46:AF46) -> 68123275
A47: Grand Total | B47: =SUM(B32,B46) -> 53938555 | C47: =SUM(C32,C46) -> 0 | D47: =SUM(D32,D46) -> 0 | E47: =SUM(E32,E46) -> 63640347 | F47: =SUM(F32,F46) -> 56488256 | G47: =SUM(G32,G46) -> 54618539 | H47: =SUM(H32,H46) -> 56771371 | I47: =SUM(I32,I46) -> 0 | ... AF47: =SUM(AF32,AF46) -> 0 | AG47: =SUM(B47:AF47) -> 2.8545707e+08

Sheet PR Report - SOBHA 
A2: Sobha | B2: As per Tracker | H2: PR
A3: Collection Executive | B3: Daily Target 07/05 | C3: Collected 07-05-26 | D3: Target (01/05 - 07/05) | E3: Achieved (01/05 - 07/05) | F3: Monthly Target | G3: Total Achieved % | H3: PR Approved | I3: PR Not Approved
A4: Dues
A5: Ali | B5: 2176503.6 | C5: 782720 | D5: 10882518 | E5: 6917700 | F5: 37000562 | G5: =IFERROR(E5/D5,0) -> 0.63567089 | H5: 6097448.4 | I5: =_xlfn.XLOOKUP(A5,$A$48:$A$70,$B$48:$B$70) -> 5003503.6
A6: Anirudh | B6: 2840497.8 | C6: 1817369.1 | D6: 14202489 | E6: 9826728.7 | F6: 48288463 | G6: =IFERROR(E6/D6,0) -> 0.69190187 | H6: 12626119 | I6: =_xlfn.XLOOKUP(A6,$A$48:$A$70,$B$48:$B$70) -> 4572457
A7: Ruhul | B7: 2774274.2 | C7: 524510 | D7: 13871371 | E7: 1833821 | F7: 47162662 | G7: =IFERROR(E7/D7,0) -> 0.13220185 | H7: 5649097.7 | I7: =_xlfn.XLOOKUP(A7,$A$48:$A$70,$B$48:$B$70) -> 4238208.5
A8: Karan | B8: 2554015.1 | C8: 1311551 | D8: 12770076 | E8: 6990927 | F8: 43418257 | G8: =IFERROR(E8/D8,0) -> 0.54744602 | H8: 1317193.7 | I8: =_xlfn.XLOOKUP(A8,$A$48:$A$70,$B$48:$B$70) -> 2640605.4
A9: Yusuf | B9: 2248108.4 | C9: 1486579 | D9: 11240542 | E9: 7340394.8 | F9: 38217843 | G9: =IFERROR(E9/D9,0) -> 0.65302854 | H9: 4090159.2 | I9: =_xlfn.XLOOKUP(A9,$A$48:$A$70,$B$48:$B$70) -> 8197132.9
A10: Sabah | B10: 1740757.5 | C10: 999311 | D10: 8703787.6 | E10: 5039866 | F10: 29592878 | G10: =IFERROR(E10/D10,0) -> 0.57904285 | H10: 3510870.3 | I10: =_xlfn.XLOOKUP(A10,$A$48:$A$70,$B$48:$B$70) -> 3034882.1
A11: Daria | B11: 1878569.9 | C11: 1513133 | D11: 9392849.7 | E11: 9617286 | F11: 31935689 | G11: =IFERROR(E11/D11,0) -> 1.0238944 | H11: 12317751 | I11: =_xlfn.XLOOKUP(A11,$A$48:$A$70,$B$48:$B$70) -> 1980461.2
A12: Rajiv | B12: 2238461.1 | C12: 2279577 | D12: 11192305 | E12: 11501814 | F12: 38053838 | G12: =IFERROR(E12/D12,0) -> 1.0276537 | H12: 5271884.8 | I12: =_xlfn.XLOOKUP(A12,$A$48:$A$70,$B$48:$B$70) -> 7215187.2
A13: Vinod | B13: 3230160.1 | C13: 200000 | D13: 16150800 | E13: 2056939.4 | F13: 54912721 | G13: =IFERROR(E13/D13,0) -> 0.12735836 | H13: 3957231.4 | I13: =_xlfn.XLOOKUP(A13,$A$48:$A$70,$B$48:$B$70) -> 4142840.9
A14: Omar | B14: 2458129.9 | C14: 2171492.8 | D14: 12290649 | E14: 9750271.5 | F14: 41788208 | G14: =IFERROR(E14/D14,0) -> 0.79330808 | H14: 20466705 | I14: =_xlfn.XLOOKUP(A14,$A$48:$A$70,$B$48:$B$70) -> 4744590
A15: Oksana | B15: 2106539.8 | C15: 2059510 | D15: 10532699 | E15: 10391011 | F15: 35811177 | G15: =IFERROR(E15/D15,0) -> 0.98654779 | H15: 5228871.5 | I15: =_xlfn.XLOOKUP(A15,$A$48:$A$70,$B$48:$B$70) -> 5422934.5
A16: Sarmad | B16: 3286315.3 | C16: 2498098 | D16: 16431576 | E16: 14591524 | F16: 55867360 | G16: =IFERROR(E16/D16,0) -> 0.88801731 | H16: 6509957 | I16: =_xlfn.XLOOKUP(A16,$A$48:$A$70,$B$48:$B$70) -> 8001301.3
... A26: Moustafa | B26: 1670123.7 | C26: 1101602 | D26: 8350618.5 | E26: 5871852 | F26: 28392103 | G26: =IFERROR(E26/D26,0) -> 0.70316372 | H26: 3612983.7 | I26: =_xlfn.XLOOKUP(A26,$A$48:$A$70,$B$48:$B$70) -> 4581377.6
A27: Total Dues | B27: =SUM(B5:B26) -> 50252771 | C27: =SUM(C5:C26) -> 34438498 | D27: =SUM(D5:D26) -> 2.5126385e+08 | E27: =SUM(E5:E26) -> 1.7426434e+08 | F27: =SUM(F5:F26) -> 854297104 | G27: =IFERROR(E27/D27,0) -> 0.69355115 | H27: =SUM(H5:H26) -> 1.2977049e+08 | I27: =SUM(I5:I26) -> 1.0721567e+08
A28: Advances
A29: Ayari | B29: 0 | C29: 1000000 | D29: 0 | E29: 6358613 | F29: 0 | G29: =IFERROR(E29/D29,0) -> 0 | H29: 5456392.9 | I29: =_xlfn.XLOOKUP(A29,$A$73:$A$84,$B$73:$B$84) -> 973340
A30: Ateev | B30: 0 | C30: 2511878 | D30: 0 | E30: 11913055 | F30: 0 | G30: =IFERROR(E30/D30,0) -> 0 | H30: 9493591 | I30: =_xlfn.XLOOKUP(A30,$A$73:$A$84,$B$73:$B$84) -> 3599020
A31: Abdulla | B31: 0 | C31: 1000000 | D31: 0 | E31: 4310770 | F31: 0 | G31: =IFERROR(E31/D31,0) -> 0 | H31: 3073221 | I31: =_xlfn.XLOOKUP(A31,$A$73:$A$84,$B$73:$B$84) -> 1563457
A32: Wael | B32: 0 | C32: 1000136.4 | D32: 0 | E32: 6750186 | F32: 0 | G32: =IFERROR(E32/D32,0) -> 0 | H32: 3920238 | I32: =_xlfn.XLOOKUP(A32,$A$73:$A$84,$B$73:$B$84) -> 2292038.6
A33: Nischitha | B33: 0 | C33: 0 | D33: 0 | E33: 0 | F33: 0 | G33: =IFERROR(E33/D33,0) -> 0 | H33: 0 | I33: =_xlfn.XLOOKUP(A33,$A$73:$A$84,$B$73:$B$84) -> 0
A34: Sherif | B34: 0 | C34: 637266 | D34: 0 | E34: 2560947 | F34: 0 | G34: =IFERROR(E34/D34,0) -> 0 | H34: 4680292.4 | I34: =_xlfn.XLOOKUP(A34,$A$73:$A$84,$B$73:$B$84) -> 840912
A35: Yogesh | B35: 0 | C35: 683324 | D35: 0 | E35: 1369006 | F35: 0 | G35: =IFERROR(E35/D35,0) -> 0 | H35: 1237047 | I35: =_xlfn.XLOOKUP(A35,$A$73:$A$84,$B$73:$B$84) -> 0
A36: Krizia | B36: 0 | C36: 0 | D36: 0 | E36: 1143453.6 | F36: 0 | G36: =IFERROR(E36/D36,0) -> 0 | H36: 561470 | I36: =_xlfn.XLOOKUP(A36,$A$73:$A$84,$B$73:$B$84) -> 860483.56
A37: Vijay | B37: 0 | C37: 1000129 | D37: 0 | E37: 4302140 | F37: 0 | G37: =IFERROR(E37/D37,0) -> 0 | H37: 1589332 | I37: =_xlfn.XLOOKUP(A37,$A$73:$A$84,$B$73:$B$84) -> 900324
A38: Jaidev | B38: 0 | C38: 1844238 | D38: 0 | E38: 5408647.5 | F38: 0 | G38: =IFERROR(E38/D38,0) -> 0 | H38: 3730663.7 | I38: =_xlfn.XLOOKUP(A38,$A$73:$A$84,$B$73:$B$84) -> 1672212
A39: Basma | B39: 0 | C39: 1477391 | D39: 0 | E39: 9515613 | F39: 0 | G39: =IFERROR(E39/D39,0) -> 0 | H39: 7291361 | I39: =_xlfn.XLOOKUP(A39,$A$73:$A$84,$B$73:$B$84) -> 7149935.5
A40: Noha | B40: 0 | C40: 586308 | D40: 0 | E40: 4823726.6 | F40: 0 | G40: =IFERROR(E40/D40,0) -> 0 | H40: 2924662.7 | I40: =_xlfn.XLOOKUP(A40,$A$73:$A$84,$B$73:$B$84) -> 1032657.9
A41: Total Advances | B41: =SUM(B29:B40) -> 0 | C41: =SUM(C29:C40) -> 11740670 | D41: =SUM(D29:D40) -> 0 | E41: =SUM(E29:E40) -> 58456158 | F41: =SUM(F29:F40) -> 0 | G41: =IFERROR(E41/D41,0) -> 0 | H41: =SUM(H29:H40) -> 43958272 | I41: =SUM(I29:I40) -> 20884381
A42: Grand Total | B42: =SUM(B27,B41) -> 50252771 | C42: =SUM(C27,C41) -> 46179169 | D42: =SUM(D27,D41) -> 2.5126385e+08 | E42: =SUM(E27,E41) -> 2.3272049e+08 | F42: =SUM(F27,F41) -> 854297104 | G42: =IFERROR(E42/D42,0) -> 0.92619965 | H42: =SUM(H27,H41) -> 1.7372877e+08 | I42: =SUM(I27,I41) -> 1.2810005e+08
A45: Sobha
A46: Collection Executive | B46: Not Approved | C46: In Process | D46: Resubmitted | E46: Rejected
A47: Dues
A48: Ali | B48: =SUM(C48:E48) -> 5003503.6 | C48: 1911450.8 | D48: 1035336 | E48: 2056716.9
A49: Anirudh | B49: =SUM(C49:E49) -> 4572457 | C49: 1415573 | D49: 388254 | E49: 2768630
A50: Ruhul | B50: =SUM(C50:E50) -> 4238208.5 | C50: 1282474.4 | D50: 2552809.1 | E50: 402925
A51: Karan | B51: =SUM(C51:E51) -> 2640605.4 | C51: 819291.03 | D51: 331587 | E51: 1489727.4
A52: Aqsa | B52: =SUM(C52:E52) -> 4216231.3 | C52: 527326 | D52: 481716 | E52: 3207189.3
A53: Hussein | B53: =SUM(C53:E53) -> 3657233.3 | C53: 2787121 | D53: 545312 | E53: 324800.3
A54: Yusuf | B54: =SUM(C54:E54) -> 8197132.9 | C54: 1966885 | D54: 775854.62 | E54: 5454393.3
A55: Sabah | B55: =SUM(C55:E55) -> 3034882.1 | C55: 630995 | D55: 919602.54 | E55: 1484284.6
A56: Daria | B56: =SUM(C56:E56) -> 1980461.2 | C56: 251525 | D56: 621644 | E56: 1107292.2
A57: Rajiv | B57: =SUM(C57:E57) -> 7215187.2 | C57: 6003574 | D57: 682599 | E57: 529014.21
A58: Abdellatif | B58: =SUM(C58:E58) -> 3159710.7 | C58: 724329.96 | D58: 968272.38 | E58: 1467108.4
A59: Vinod | B59: =SUM(C59:E59) -> 4142840.9 | C59: 344922.59 | D59: 3029965.8 | E59: 767952.5
... A70: Moustafa | B70: =SUM(C70:E70) -> 4581377.6 | C70: 426604 | D70: 1473080.8 | E70: 2681692.8
A71: Total Dues | B71: =SUM(B48:B70) -> 1.108729e+08 | C71: =SUM(C48:C70) -> 43996655 | D71: =SUM(D48:D70) -> 21673520 | E71: =SUM(E48:E70) -> 45202726
A72: Advances
A73: Ayari | B73: =SUM(C73:E73) -> 973340 | C73: 46000 | D73: 200000 | E73: 727340
A74: Ateev | B74: =SUM(C74:E74) -> 3599020 | C74: 1652682 | D74: 0 | E74: 1946338
A75: Abdulla | B75: =SUM(C75:E75) -> 1563457 | C75: 1563457 | D75: 0 | E75: 0
A76: Wael | B76: =SUM(C76:E76) -> 2292038.6 | C76: 718079.82 | D76: 490451.78 | E76: 1083507
A77: Nischitha | B77: =SUM(C77:E77) -> 0 | C77: 0 | D77: 0 | E77: 0
A78: Sherif | B78: =SUM(C78:E78) -> 840912 | C78: 840912 | D78: 0 | E78: 0
A79: Krizia | B79: =SUM(C79:E79) -> 860483.56 | C79: 133983.56 | D79: 726500 | E79: 0
A80: Noha | B80: =SUM(C80:E80) -> 1032657.9 | C80: 150073.87 | D80: 0 | E80: 882584
A81: Vijay | B81: =SUM(C81:E81) -> 900324 | C81: 720324 | D81: 0 | E81: 180000
A82: Jaidev | B82: =SUM(C82:E82) -> 1672212 | C82: 642426 | D82: 0 | E82: 1029786
A83: Basma | B83: =SUM(C83:E83) -> 7149935.5 | C83: 1731115.7 | D83: 0 | E83: 5418819.8
A84: Yogesh | B84: =SUM(C84:E84) -> 0 | C84: 0 | D84: 0 | E84: 0
A85: Total Advances | B85: =SUM(B73:B84) -> 20884381 | C85: =SUM(C73:C84) -> 8199054 | D85: =SUM(D73:D84) -> 1416951.8 | E85: =SUM(E73:E84) -> 11268375
A86: Grand Total | B86: =SUM(B85,B71) -> 1.3175728e+08 | C86: =SUM(C85,C71) -> 52195709 | D86: =SUM(D85,D71) -> 23090472 | E86: =SUM(E85,E71) -> 56471101
A89: SOBHA | C89: Cheque | I89: Other Mode of Payment
A90: Collection Executive | B90: PR Approved | C90: Cancelled | D90: Cleared | E90: PDC | F90: Processed-Sent for Banking | G90: Cheque Hold | H90: UnProcessed | I90: Unallocated | J90: Cancelled | K90: Cleared | L90: UnProcessed | M90: PDC Approved this Month / Amount to be allocated
A91: Dues
A92: Ali | B92: 6097448.4 | C92: 0 | D92: 229359 | E92: 0 | F92: 0 | G92: 0 | H92: 1618007 | I92: 0 | J92: 0 | K92: 4250082.4 | L92: 0 | M92: =B92-SUM(C92:L92) -> 0
A93: Anirudh | B93: 12626119 | C93: 0 | D93: 1913650 | E93: 3786094 | F93: 0 | G93: 0 | H93: 500000 | I93: 0 | J93: 0 | K93: 6426375.1 | L93: 0 | M93: =B93-SUM(C93:L93) -> 0
A94: Ruhul | B94: 5649097.7 | C94: 0 | D94: 0 | E94: 0 | F94: 0 | G94: 0 | H94: 0 | I94: 1108547.1 | J94: 0 | K94: 4540550.7 | L94: 0 | M94: =B94-SUM(C94:L94) -> 0
A95: Karan | B95: 1317193.7 | C95: 0 | D95: 0 | E95: 0 | F95: 0 | G95: 0 | H95: 0 | I95: 0 | J95: 0 | K95: 1317193.7 | L95: 0 | M95: =B95-SUM(C95:L95) -> 0
A96: Hussein | B96: 2699046 | C96: 0 | D96: 179200 | E96: 930746 | F96: 0 | G96: 0 | H96: 779728 | I96: 171505 | J96: 0 | K96: 637867 | L96: 0 | M96: =B96-SUM(C96:L96) -> 0
A97: Yusuf | B97: 4090159.2 | C97: 0 | D97: 0 | E97: 0 | F97: 0 | G97: 0 | H97: 0 | I97: 0 | J97: 0 | K97: 4090159.2 | L97: 0 | M97: =B97-SUM(C97:L97) -> 0
A98: Sabah | B98: 3510870.3 | C98: 0 | D98: 0 | E98: 0 | F98: 0 | G98: 0 | H98: 150000 | I98: 165207.41 | J98: 0 | K98: 3195662.9 | L98: 0 | M98: =B98-SUM(C98:L98) -> 0
A99: Daria | B99: 12317751 | C99: 0 | D99: 7800000 | E99: 0 | F99: 0 | G99: 0 | H99: 0 | I99: 205520.94 | J99: 0 | K99: 3660471.2 | L99: 0 | M99: =B99-SUM(C99:L99) -> 651759
A100: Rajiv | B100: 5271884.8 | C100: 0 | D100: 0 | E100: 0 | F100: 0 | G100: 0 | H100: 1212616 | I100: 0 | J100: 0 | K100: 4059268.8 | L100: 0 | M100: =B100-SUM(C100:L100) -> 0
A101: Abdellatif | B101: 7772319.3 | C101: 0 | D101: 0 | E101: 0 | F101: 0 | G101: 0 | H101: 684798.4 | I101: 0 | J101: 0 | K101: 7087520.9 | L101: 0 | M101: =B101-SUM(C101:L101) -> 0
A102: Aqsa | B102: 5336207 | C102: 0 | D102: 0 | E102: 0 | F102: 0 | G102: 0 | H102: 0 | I102: 0 | J102: 0 | K102: 5336207 | L102: 0 | M102: =B102-SUM(C102:L102) -> 0
A103: Vinod | B103: 3957231.4 | C103: 0 | D103: 502000 | E103: 0 | F103: 0 | G103: 0 | H103: 679221.7 | I103: 0 | J103: 0 | K103: 2776009.7 | L103: 0 | M103: =B103-SUM(C103:L103) -> 0
... A114: Moustafa | B114: 3612983.7 | C114: 0 | D114: 236429 | E114: 0 | F114: 0 | G114: 0 | H114: 129707 | I114: 0 | J114: 0 | K114: 3246847.7 | L114: 0 | M114: =B114-SUM(C114:L114) -> 0
A115: Total Dues | B115: =SUM(B92:B114) -> 1.3246954e+08 | C115: =SUM(C92:C114) -> 0 | D115: =SUM(D92:D114) -> 14246921 | E115: =SUM(E92:E114) -> 5647586 | F115: =SUM(F92:F114) -> 0 | G115: =SUM(G92:G114) -> 0 | H115: =SUM(H92:H114) -> 7978144.7 | I115: =SUM(I92:I114) -> 3111671.1 | ... M115: =SUM(M92:M114) -> 15018179
A116: Advances
A117: Ayari | B117: 5456392.9 | C117: 0 | D117: 223348.86 | E117: 0 | F117: 0 | G117: 0 | H117: 1935731 | I117: 0 | J117: 0 | K117: 3297313 | L117: 0 | M117: =B117-SUM(C117:L117) -> 0
A118: Abdulla | B118: 3073221 | C118: 0 | D118: 0 | E118: 0 | F118: 0 | G118: 0 | H118: 0 | I118: 0 | J118: 0 | K118: 3073221 | L118: 0 | M118: =B118-SUM(C118:L118) -> 0
A119: Ateev | B119: 9493591 | C119: 0 | D119: 936899 | E119: 0 | F119: 0 | G119: 0 | H119: 0 | I119: 0 | J119: 0 | K119: 8556692 | L119: 0 | M119: =B119-SUM(C119:L119) -> 0
A120: Wael | B120: 3920238 | C120: 0 | D120: 0 | E120: 0 | F120: 0 | G120: 0 | H120: 347417 | I120: 0 | J120: 0 | K120: 3572821 | L120: 0 | M120: =B120-SUM(C120:L120) -> 0
A121: Sherif | B121: 4680292.4 | C121: 0 | D121: 0 | E121: 0 | F121: 0 | G121: 0 | H121: 0 | I121: 0 | J121: 0 | K121: 4680292.4 | L121: 0 | M121: =B121-SUM(C121:L121) -> 0
A122: Nischitha | B122: 0 | C122: 0 | D122: 0 | E122: 0 | F122: 0 | G122: 0 | H122: 0 | I122: 0 | J122: 0 | K122: 0 | L122: 0 | M122: =B122-SUM(C122:L122) -> 0
A123: Krizia | B123: 561470 | C123: 0 | D123: 0 | E123: 0 | F123: 0 | G123: 0 | H123: 0 | I123: 0 | J123: 0 | K123: 561470 | L123: 0 | M123: =B123-SUM(C123:L123) -> 0
A124: Noha | B124: 2924662.7 | C124: 0 | D124: 2221036 | E124: 0 | F124: 0 | G124: 0 | H124: 0 | I124: 0 | J124: 0 | K124: 703626.74 | L124: 0 | M124: =B124-SUM(C124:L124) -> 0
A125: Vijay | B125: 1589332 | C125: 0 | D125: 0 | E125: 0 | F125: 0 | G125: 0 | H125: 0 | I125: 0 | J125: 0 | K125: 1589332 | L125: 0 | M125: =B125-SUM(C125:L125) -> 0
A126: Jaidev | B126: 3730663.7 | C126: 0 | D126: 519804 | E126: 0 | F126: 0 | G126: 0 | H126: 0 | I126: 417070.97 | J126: 0 | K126: 2793788.7 | L126: 0 | M126: =B126-SUM(C126:L126) -> 0
A127: Basma | B127: 7291361 | C127: 0 | D127: 0 | E127: 0 | F127: 0 | G127: 0 | H127: 0 | I127: 0 | J127: 0 | K127: 7291361 | L127: 0 | M127: =B127-SUM(C127:L127) -> 0
A128: Yogesh | B128: 1237047 | C128: 0 | D128: 0 | E128: 0 | F128: 0 | G128: 0 | H128: 0 | I128: 0 | J128: 0 | K128: 1128479 | L128: 108568 | M128: =B128-SUM(C128:L128) -> 0
A129: Total Advances | B129: =SUM(B117:B128) -> 43958272 | C129: =SUM(C117:C128) -> 0 | D129: =SUM(D117:D128) -> 3901087.9 | E129: =SUM(E117:E128) -> 0 | F129: =SUM(F117:F128) -> 0 | G129: =SUM(G117:G128) -> 0 | H129: =SUM(H117:H128) -> 2283148 | I129: =SUM(I117:I128) -> 417070.97 | ... M129: =SUM(M117:M128) -> 0
A130: Grand Total | B130: =SUM(B115,B129) -> 1.7642781e+08 | C130: =SUM(C129,C115) -> 0 | D130: =SUM(D129,D115) -> 18148009 | E130: =SUM(E129,E115) -> 5647586 | F130: =SUM(F129,F115) -> 0 | G130: =SUM(G129,G115) -> 0 | H130: =SUM(H129,H115) -> 10261293 | I130: =SUM(I129,I115) -> 3528742.1 | J130: =SUM(J129,J115) -> 0 | ... L130: =SUM(L129,L115) -> 118568 | M130: =SUM(M115,M129) -> 15018179

Sheet PR Report - SINIYA
A2: Siniya | B2: As per Tracker | H2: PR
A3: Collection Executive | B3: Daily Target 07/05 | C3: Collected 07-05-26 | D3: Target (01/05 - 07/05) | E3: Achieved (01/05 - 07/05) | F3: Monthly Target | G3: Total Achieved % | H3: PR Approved | I3: PR Not Approved
A4: Dues
A5: Monish | B5: 3823529.4 | C5: 2460211.9 | D5: 19117647 | E5: 12919024 | F5: 65000000 | G5: =IFERROR(E5/D5,0) -> 0.67576435 | H5: 6517845.8 | I5: =_xlfn.XLOOKUP(A5,$A$41:$A$59,$B$41:$B$59) -> 5676444.3
A6: Melvyn | B6: 2647058.8 | C6: 2617764.5 | D6: 13235294 | E6: 10927221 | F6: 45000000 | G6: =IFERROR(E6/D6,0) -> 0.82561229 | H6: 5979287.7 | I6: =_xlfn.XLOOKUP(A6,$A$41:$A$59,$B$41:$B$59) -> 4265516.2
A7: Anna | B7: 1176470.6 | C7: 420035.73 | D7: 5882352.9 | E7: 2932051.8 | F7: 20000000 | G7: =IFERROR(E7/D7,0) -> 0.4984488 | H7: 2112020 | I7: =_xlfn.XLOOKUP(A7,$A$41:$A$59,$B$41:$B$59) -> 506236.11
A8: Ruhul | B8: 0 | C8: 0 | D8: 0 | E8: 0 | F8: 0 | G8: =IFERROR(E8/D8,0) -> 0 | H8: 0 | I8: =_xlfn.XLOOKUP(A8,$A$41:$A$59,$B$41:$B$59) -> 0
A9: Walid | B9: 2941176.5 | C9: 567088 | D9: 14705882 | E9: 9386458.1 | F9: 50000000 | G9: =IFERROR(E9/D9,0) -> 0.63827915 | H9: 6515834.5 | I9: =_xlfn.XLOOKUP(A9,$A$41:$A$59,$B$41:$B$59) -> 3546005
A10: Ali | B10: 0 | C10: 0 | D10: 0 | E10: 0 | G10: =IFERROR(E10/D10,0) -> 0 | H10: 0 | I10: =_xlfn.XLOOKUP(A10,$A$41:$A$59,$B$41:$B$59) -> 0
A11: Anirudh | B11: 0 | C11: 0 | D11: 0 | E11: 0 | G11: =IFERROR(E11/D11,0) -> 0 | H11: 0 | I11: =_xlfn.XLOOKUP(A11,$A$41:$A$59,$B$41:$B$59) -> 0
A12: Aqsa | B12: 0 | C12: 0 | D12: 0 | E12: 0 | G12: =IFERROR(E12/D12,0) -> 0 | H12: 0 | I12: =_xlfn.XLOOKUP(A12,$A$41:$A$59,$B$41:$B$59) -> 0
A13: Hussein | B13: 0 | C13: 0 | D13: 0 | E13: 0 | G13: =IFERROR(E13/D13,0) -> 0 | H13: 505555 | I13: =_xlfn.XLOOKUP(A13,$A$41:$A$59,$B$41:$B$59) -> 0
A14: Karan | B14: 0 | C14: 0 | D14: 0 | E14: 0 | G14: =IFERROR(E14/D14,0) -> 0 | H14: 0 | I14: =_xlfn.XLOOKUP(A14,$A$41:$A$59,$B$41:$B$59) -> 342501
A15: Rajiv | B15: 0 | C15: 0 | D15: 0 | E15: 0 | G15: =IFERROR(E15/D15,0) -> 0 | H15: 0 | I15: =_xlfn.XLOOKUP(A15,$A$41:$A$59,$B$41:$B$59) -> 0
A16: Vinod | B16: 0 | C16: 0 | D16: 0 | E16: 0 | G16: =IFERROR(E16/D16,0) -> 0 | H16: 0 | I16: =_xlfn.XLOOKUP(A16,$A$41:$A$59,$B$41:$B$59) -> 0
A17: Sarmad | B17: 0 | C17: 0 | D17: 0 | E17: 0 | G17: =IFERROR(E17/D17,0) -> 0 | H17: 0 | I17: =_xlfn.XLOOKUP(A17,$A$41:$A$59,$B$41:$B$59) -> 0
A18: Zeba | B18: 0 | C18: 0 | D18: 0 | E18: 0 | G18: =IFERROR(E18/D18,0) -> 0 | H18: 0 | I18: =_xlfn.XLOOKUP(A18,$A$41:$A$59,$B$41:$B$59) -> 0
A19: Sabah | B19: 0 | C19: 0 | D19: 0 | E19: 0 | G19: =IFERROR(E19/D19,0) -> 0 | H19: 0 | I19: =_xlfn.XLOOKUP(A19,$A$41:$A$59,$B$41:$B$59) -> 0
A20: Sid | B20: 0 | C20: 0 | D20: 0 | E20: 0 | G20: =IFERROR(E20/D20,0) -> 0 | H20: 0 | I20: =_xlfn.XLOOKUP(A20,$A$41:$A$59,$B$41:$B$59) -> 0
A21: Abdellatif | B21: 0 | C21: 0 | D21: 0 | E21: 0 | G21: =IFERROR(E21/D21,0) -> 0 | H21: 0 | I21: =_xlfn.XLOOKUP(A21,$A$41:$A$59,$B$41:$B$59) -> 0
A22: Total Dues | B22: =SUM(B5:B21) -> 10588235 | C22: =SUM(C5:C21) -> 6065100.1 | D22: =SUM(D5:D21) -> 52941176 | E22: =SUM(E5:E21) -> 36164756 | F22: =SUM(F5:F21) -> 180000000 | G22: =IFERROR((E22)/(D22),0) -> 0.68311205 | H22: =SUM(H5:H21) -> 21630543 | I22: =SUM(I5:I21) -> 14336703
A23: Advances
A24: Abdulla | B24: 0 | C24: 0 | D24: 0 | E24: 216912 | F24: 0 | G24: =IFERROR(E24/D24,0) -> 0 | H24: 288016 | I24: =_xlfn.XLOOKUP(A24,$A$62:$A$72,$B$62:$B$72) -> 0
A25: Noha | B25: 0 | C25: 65000 | D25: 0 | E25: 389512 | F25: 0 | G25: =IFERROR(E25/D25,0) -> 0 | H25: 246507.85 | I25: =_xlfn.XLOOKUP(A25,$A$62:$A$72,$B$62:$B$72) -> 388807.68
A26: Krizia | B26: 0 | C26: 1747417 | D26: 0 | E26: 3436611 | F26: 0 | G26: =IFERROR(E26/D26,0) -> 0 | H26: 2091049 | I26: =_xlfn.XLOOKUP(A26,$A$62:$A$72,$B$62:$B$72) -> 661137
A27: Ateev | B27: 0 | C27: 0 | D27: 0 | E27: 0 | F27: 0 | G27: =IFERROR(E27/D27,0) -> 0 | H27: 0 | I27: =_xlfn.XLOOKUP(A27,$A$62:$A$72,$B$62:$B$72) -> 0
A28: Ayari | B28: 0 | C28: 0 | D28: 0 | E28: 0 | F28: 0 | G28: =IFERROR(E28/D28,0) -> 0 | H28: 0 | I28: =_xlfn.XLOOKUP(A28,$A$62:$A$72,$B$62:$B$72) -> 0
A29: Nischitha | B29: 0 | C29: 0 | D29: 0 | E29: 0 | F29: 0 | G29: =IFERROR(E29/D29,0) -> 0 | H29: 0 | I29: =_xlfn.XLOOKUP(A29,$A$62:$A$72,$B$62:$B$72) -> 0
A30: Sherif | B30: 0 | C30: 428000 | D30: 0 | E30: 428000 | F30: 0 | G30: =IFERROR(E30/D30,0) -> 0 | H30: 0 | I30: =_xlfn.XLOOKUP(A30,$A$62:$A$72,$B$62:$B$72) -> 0
A31: Wael | B31: 0 | C31: 0 | D31: 0 | E31: 0 | F31: 0 | G31: =IFERROR(E31/D31,0) -> 0 | H31: 35775 | I31: =_xlfn.XLOOKUP(A31,$A$62:$A$72,$B$62:$B$72) -> 138572
A32: Jaidev | B32: 0 | C32: 0 | D32: 0 | E32: 0 | F32: 0 | G32: =IFERROR(E32/D32,0) -> 0 | H32: 0 | I32: =_xlfn.XLOOKUP(A32,$A$62:$A$72,$B$62:$B$72) -> 0
A33: Basma | B33: 0 | C33: 522609 | D33: 0 | E33: 1228490 | F33: 0 | G33: =IFERROR(E33/D33,0) -> 0 | H33: 749881 | I33: =_xlfn.XLOOKUP(A33,$A$62:$A$72,$B$62:$B$72) -> 0
A34: Yogesh | B34: 0 | C34: 0 | D34: 0 | E34: 1781697 | F34: 0 | G34: =IFERROR(E34/D34,0) -> 0 | H34: 40000 | I34: =_xlfn.XLOOKUP(A34,$A$62:$A$72,$B$62:$B$72) -> 674242
A35: Total Advances | B35: =SUM(B24:B34) -> 0 | C35: =SUM(C24:C34) -> 2763026 | D35: =SUM(D24:D34) -> 0 | E35: =SUM(E24:E34) -> 7481222 | F35: =SUM(F24:F34) -> 0 | G35: =IFERROR(E35/D35,0) -> 0 | H35: =SUM(H24:H34) -> 3451228.9 | I35: =SUM(I24:I34) -> 1862758.7
A36: Grand Total | B36: =SUM(B22,B35) -> 10588235 | C36: =SUM(C22,C35) -> 8828126.1 | D36: =SUM(D22,D35) -> 52941176 | E36: =SUM(E22,E35) -> 43645978 | F36: =SUM(F22,F35) -> 180000000 | G36: =IFERROR(E36/D36,0) -> 0.82442402 | H36: =SUM(H22,H35) -> 25081772 | I36: =SUM(I22,I35) -> 16199461
A38: Siniya
A39: Collection Executive | B39: Not Approved | C39: In Process | D39: Resubmitted | E39: Rejected
A40: Dues
A41: Ali | B41: =SUM(C41:E41) -> 0 | C41: 0 | D41: 0 | E41: 0
A42: Anirudh | B42: =SUM(C42:E42) -> 0 | C42: 0 | D42: 0 | E42: 0
A43: Ruhul | B43: =SUM(C43:E43) -> 0 | C43: 0 | D43: 0 | E43: 0
A44: Karan | B44: =SUM(C44:E44) -> 342501 | C44: 156877 | D44: 0 | E44: 185624
A45: Aqsa | B45: =SUM(C45:E45) -> 0 | C45: 0 | D45: 0 | E45: 0
A46: Sid | B46: =SUM(C46:E46) -> 0 | C46: 0 | D46: 0 | E46: 0
A47: Hussein | B47: =SUM(C47:E47) -> 0 | C47: 0 | D47: 0 | E47: 0
A48: Sabah | B48: =SUM(C48:E48) -> 0 | C48: 0 | D48: 0 | E48: 0
A49: Sijit | B49: =SUM(C49:E49) -> 0 | C49: 0 | D49: 0 | E49: 0
A50: Rajiv | B50: =SUM(C50:E50) -> 0 | C50: 0 | D50: 0 | E50: 0
A51: Abdellatif | B51: =SUM(C51:E51) -> 0 | C51: 0 | D51: 0 | E51: 0
A52: Vinod | B52: =SUM(C52:E52) -> 0 | C52: 0 | D52: 0 | E52: 0
... A59: Anna | B59: =SUM(C59:E59) -> 506236.11 | C59: 356236.11 | D59: 0 | E59: 150000
A60: Total Dues | B60: =SUM(B41:B59) -> 14336703 | C60: =SUM(C41:C59) -> 5491159.3 | D60: =SUM(D41:D59) -> 3162335.8 | E60: =SUM(E41:E59) -> 5683207.6
A61: Advances
A62: Ayari | B62: =SUM(C62:E62) -> 0 | C62: 0 | D62: 0 | E62: 0
A63: Noha | B63: =SUM(C63:E63) -> 388807.68 | C63: 0 | D63: 169807.68 | E63: 219000
A64: Krizia | B64: =SUM(C64:E64) -> 661137 | C64: 189128 | D64: 278758 | E64: 193251
A65: Ateev | B65: =SUM(C65:E65) -> 0 | C65: 0 | D65: 0 | E65: 0
A66: Abdulla | B66: =SUM(C66:E66) -> 0 | C66: 0 | D66: 0 | E66: 0
A67: Wael | B67: =SUM(C67:E67) -> 138572 | C67: 138572 | D67: 0 | E67: 0
A68: Nischitha | B68: =SUM(C68:E68) -> 0 | C68: 0 | D68: 0 | E68: 0
A69: Sherif | B69: =SUM(C69:E69) -> 0 | C69: 0 | D69: 0 | E69: 0
A70: Jaidev | B70: =SUM(C70:E70) -> 0 | C70: 0 | D70: 0 | E70: 0
A71: Basma | B71: =SUM(C71:E71) -> 0 | C71: 0 | D71: 0 | E71: 0
A72: Yogesh | B72: =SUM(C72:E72) -> 674242 | C72: 115862 | D72: 558380 | E72: 0
A73: Total Advances | B73: =SUM(B62:B72) -> 1862758.7 | C73: =SUM(C62:C72) -> 443562 | D73: =SUM(D62:D72) -> 1006945.7 | E73: =SUM(E62:E72) -> 412251
A74: Grand Total | B74: =SUM(B73,B60) -> 16199461 | C74: =SUM(C73,C60) -> 5934721.3 | D74: =SUM(D73,D60) -> 4169281.5 | E74: =SUM(E73,E60) -> 6095458.6
A76: SINIYA | C76: Cheque | I76: Other Mode of Payment
A77: Collection Executive | B77: PR Approved | C77: Cancelled | D77: Cleared | E77: PDC | F77: Processed-Sent for Banking | G77: Cheque Hold | H77: UnProcessed | I77: Unallocated | J77: Cancelled | K77: Cleared | L77: UnProcessed | M77: PDC Approved this Month / Amount to be allocated
A78: Dues
A79: Monish | B79: 6517845.8 | C79: 0 | D79: 0 | E79: 0 | F79: 0 | G79: 0 | H79: 0 | I79: 0 | J79: 0 | K79: 6504500.8 | L79: 13345 | M79: =B79-SUM(C79:L79) -> 0
A80: Anna | B80: 2112020 | C80: 0 | D80: 0 | E80: 0 | F80: 0 | G80: 0 | H80: 0 | I80: 0 | J80: 0 | K80: 2112020 | L80: 0 | M80: =B80-SUM(C80:L80) -> 0
A81: Melvyn | B81: 5979287.7 | C81: 0 | D81: 0 | E81: 0 | F81: 0 | G81: 0 | H81: 0 | I81: 0 | J81: 0 | K81: 5648767.7 | L81: 0 | M81: =B81-SUM(C81:L81) -> 330520
A82: Ruhul | B82: 0 | C82: 0 | D82: 0 | E82: 0 | F82: 0 | G82: 0 | H82: 0 | I82: 0 | J82: 0 | K82: 0 | L82: 0 | M82: =B82-SUM(C82:L82) -> 0
A83: Walid | B83: 6515834.5 | C83: 0 | D83: 0 | E83: 0 | F83: 0 | G83: 0 | H83: 0 | I83: 10843 | J83: 0 | K83: 6504991.5 | L83: 0 | M83: =MAX(B83-SUM(C83:L83),0) -> 0
A84: Ali | B84: 0 | C84: 0 | D84: 0 | E84: 0 | F84: 0 | G84: 0 | H84: 0 | I84: 0 | J84: 0 | K84: 0 | L84: 0 | M84: =B84-SUM(C84:L84) -> 0
A85: Anirudh | B85: 0 | C85: 0 | D85: 0 | E85: 0 | F85: 0 | G85: 0 | H85: 0 | I85: 0 | J85: 0 | K85: 0 | L85: 0 | M85: =B85-SUM(C85:L85) -> 0
A86: Hussein | B86: 505555 | C86: 0 | D86: 0 | E86: 0 | F86: 0 | G86: 0 | H86: 0 | I86: 0 | J86: 0 | K86: 505555 | L86: 0 | M86: =B86-SUM(C86:L86) -> 0
A87: Karan | B87: 0 | C87: 0 | D87: 0 | E87: 0 | F87: 0 | G87: 0 | H87: 0 | I87: 0 | J87: 0 | K87: 0 | L87: 0 | M87: =B87-SUM(C87:L87) -> 0
A88: Rajiv | B88: 0 | C88: 0 | D88: 0 | E88: 0 | F88: 0 | G88: 0 | H88: 0 | I88: 0 | J88: 0 | K88: 0 | L88: 0 | M88: =B88-SUM(C88:L88) -> 0
A89: Aqsa | B89: 0 | C89: 0 | D89: 0 | E89: 0 | F89: 0 | G89: 0 | H89: 0 | I89: 0 | J89: 0 | K89: 0 | L89: 0 | M89: =B89-SUM(C89:L89) -> 0
A90: Lamis | B90: 0 | C90: 0 | D90: 0 | E90: 0 | F90: 0 | G90: 0 | H90: 0 | I90: 0 | J90: 0 | K90: 0 | L90: 0 | M90: =B90-SUM(C90:L90) -> 0
A91: Sabah | B91: 0 | C91: 0 | D91: 0 | E91: 0 | F91: 0 | G91: 0 | H91: 0 | I91: 0 | J91: 0 | K91: 0 | L91: 0 | M91: =B91-SUM(C91:L91) -> 0
A92: Sid | B92: 0 | C92: 0 | D92: 0 | E92: 0 | F92: 0 | G92: 0 | H92: 0 | I92: 0 | J92: 0 | K92: 0 | L92: 0 | M92: =B92-SUM(C92:L92) -> 0
A93: Abdellatif | B93: 0 | C93: 0 | D93: 0 | E93: 0 | F93: 0 | G93: 0 | H93: 0 | I93: 0 | J93: 0 | K93: 0 | L93: 0 | M93: =B93-SUM(C93:L93) -> 0
A94: Total Dues | B94: =SUM(B79:B93) -> 21630543 | C94: =SUM(C79:C93) -> 0 | D94: =SUM(D79:D93) -> 0 | E94: =SUM(E79:E93) -> 0 | F94: =SUM(F79:F93) -> 0 | G94: =SUM(G79:G93) -> 0 | H94: =SUM(H79:H93) -> 0 | I94: =SUM(I79:I93) -> 10843 | ... M94: =SUM(M79:M93) -> 330520
A95: Advances
A96: Abdulla | B96: 288016 | C96: 0 | D96: 0 | E96: 0 | F96: 0 | G96: 0 | H96: 0 | I96: 0 | J96: 0 | K96: 166912 | L96: 0 | M96: =B96-SUM(C96:L96) -> 121104
A97: Krizia | B97: 2091049 | C97: 0 | D97: 0 | E97: 0 | F97: 0 | G97: 0 | H97: 0 | I97: 163758 | J97: 0 | K97: 1927291 | L97: 0 | M97: =B97-SUM(C97:L97) -> 0
A98: Ateev | B98: 0 | C98: 0 | D98: 0 | E98: 0 | F98: 0 | G98: 0 | H98: 0 | I98: 0 | J98: 0 | K98: 0 | L98: 0 | M98: =B98-SUM(C98:L98) -> 0
A99: Ayari | B99: 0 | C99: 0 | D99: 0 | E99: 0 | F99: 0 | G99: 0 | H99: 0 | I99: 0 | J99: 0 | K99: 0 | L99: 0 | M99: =B99-SUM(C99:L99) -> 0
A100: Sherif | B100: 0 | C100: 0 | D100: 0 | E100: 0 | F100: 0 | G100: 0 | H100: 0 | I100: 0 | J100: 0 | K100: 0 | L100: 0 | M100: =B100-SUM(C100:L100) -> 0
A101: Wael | B101: 35775 | C101: 0 | D101: 0 | E101: 0 | F101: 0 | G101: 0 | H101: 0 | I101: 0 | J101: 0 | K101: 35775 | L101: 0 | M101: =B101-SUM(C101:L101) -> 0
A102: Nischitha | B102: 0 | C102: 0 | D102: 0 | E102: 0 | F102: 0 | G102: 0 | H102: 0 | I102: 0 | J102: 0 | K102: 0 | L102: 0 | M102: =B102-SUM(C102:L102) -> 0
A103: Noha | B103: 246507.85 | C103: 0 | D103: 0 | E103: 0 | F103: 0 | G103: 0 | H103: 0 | I103: 167907.85 | J103: 0 | K103: 78600 | L103: 0 | M103: =B103-SUM(C103:L103) -> 0
A104: Jaidev | B104: 0 | C104: 0 | D104: 0 | E104: 0 | F104: 0 | G104: 0 | H104: 0 | I104: 0 | J104: 0 | K104: 0 | L104: 0 | M104: =B104-SUM(C104:L104) -> 0
A105: Basma | B105: 749881 | C105: 0 | D105: 0 | E105: 0 | F105: 0 | G105: 0 | H105: 0 | I105: 705881 | J105: 0 | K105: 44000 | L105: 0 | M105: =B105-SUM(C105:L105) -> 0
A106: Yogesh | B106: 40000 | C106: 0 | D106: 0 | E106: 0 | F106: 0 | G106: 0 | H106: 0 | I106: 0 | J106: 0 | K106: 40000 | L106: 0 | M106: =B106-SUM(C106:L106) -> 0
A107: Total Advances | B107: =SUM(B96:B106) -> 3451228.9 | C107: =SUM(C96:C106) -> 0 | D107: =SUM(D96:D106) -> 0 | E107: =SUM(E96:E106) -> 0 | F107: =SUM(F96:F106) -> 0 | G107: =SUM(G96:G106) -> 0 | H107: =SUM(H96:H106) -> 0 | I107: =SUM(I96:I106) -> 1037546.8 | ... M107: =SUM(M96:M106) -> 121104
A108: Grand Total | B108: =SUM(B94,B107) -> 25081772 | C108: =SUM(C107,C94) -> 0 | D108: =SUM(D107,D94) -> 0 | E108: =SUM(E107,E94) -> 0 | F108: =SUM(F107,F94) -> 0 | G108: =SUM(G107,G94) -> 0 | H108: =SUM(H107,H94) -> 0 | I108: =SUM(I107,I94) -> 1048389.8 | J108: =SUM(J107,J94) -> 0 | ... L108: =SUM(L107,L94) -> 13345 | M108: =SUM(M94,M107) -> 451624

Sheet PR Report - DOWNTOWN
A2: Downtown | B2: As per Tracker | H2: PR
A3: Collection Executive | B3: Daily Target 07/05 | C3: Collected 07-05-26 | D3: Target (01/05 - 07/05) | E3: Achieved (01/05 - 07/05) | F3: Monthly Target | G3: Total Achieved % | H3: PR Approved | I3: PR Not Approved
A4: Dues
A5: Monish | B5: 0 | C5: 0 | D5: 0 | E5: 0 | F5: 0 | G5: =IFERROR(E5/D5,0) -> 0 | H5: 0 | I5: =_xlfn.XLOOKUP(A5,$A$42:$A$59,$B$42:$B$59) -> 0
A6: Melvyn | B6: 0 | C6: 0 | D6: 0 | E6: 0 | F6: 0 | G6: =IFERROR(E6/D6,0) -> 0 | H6: 0 | I6: =_xlfn.XLOOKUP(A6,$A$42:$A$59,$B$42:$B$59) -> 0
A7: Anna | B7: 0 | C7: 0 | D7: 0 | E7: 0 | F7: 0 | G7: =IFERROR(E7/D7,0) -> 0 | H7: 0 | I7: =_xlfn.XLOOKUP(A7,$A$42:$A$59,$B$42:$B$59) -> 0
A8: Ruhul | B8: 0 | C8: 0 | D8: 0 | E8: 0 | F8: 0 | G8: =IFERROR(E8/D8,0) -> 0 | H8: 0 | I8: =_xlfn.XLOOKUP(A8,$A$42:$A$59,$B$42:$B$59) -> 0
A9: Walid | B9: 882352.94 | C9: 1433318.8 | D9: 4411764.7 | E9: 6904702.4 | F9: 15000000 | G9: =IFERROR(E9/D9,0) -> 1.5650659 | H9: 4017950.3 | I9: =_xlfn.XLOOKUP(A9,$A$42:$A$59,$B$42:$B$59) -> 4568723.6
A10: Ali | B10: 0 | C10: 0 | D10: 0 | E10: 0 | F10: 0 | G10: =IFERROR(E10/D10,0) -> 0 | H10: 0 | I10: =_xlfn.XLOOKUP(A10,$A$42:$A$59,$B$42:$B$59) -> 0
A11: Anirudh | B11: 0 | C11: 0 | D11: 0 | E11: 0 | F11: 0 | G11: =IFERROR(E11/D11,0) -> 0 | H11: 0 | I11: =_xlfn.XLOOKUP(A11,$A$42:$A$59,$B$42:$B$59) -> 0
A12: Aqsa | B12: 0 | C12: 0 | D12: 0 | E12: 0 | F12: 0 | G12: =IFERROR(E12/D12,0) -> 0 | H12: 0 | I12: =_xlfn.XLOOKUP(A12,$A$42:$A$59,$B$42:$B$59) -> 0
A13: Daria | B13: 0 | C13: 0 | D13: 0 | E13: 0 | F13: 0 | G13: =IFERROR(E13/D13,0) -> 0 | H13: 0 | I13: =_xlfn.XLOOKUP(A13,$A$42:$A$59,$B$42:$B$59) -> 0
A14: Hussein | B14: 0 | C14: 0 | D14: 0 | E14: 0 | F14: 0 | G14: =IFERROR(E14/D14,0) -> 0 | H14: 0 | I14: =_xlfn.XLOOKUP(A14,$A$42:$A$59,$B$42:$B$59) -> 0
A15: Karan | B15: 0 | C15: 0 | D15: 0 | E15: 0 | F15: 0 | G15: =IFERROR(E15/D15,0) -> 0 | H15: 0 | I15: =_xlfn.XLOOKUP(A15,$A$42:$A$59,$B$42:$B$59) -> 0
A16: Rajiv | B16: 0 | C16: 0 | D16: 0 | E16: 0 | F16: 0 | G16: =IFERROR(E16/D16,0) -> 0 | H16: 0 | I16: =_xlfn.XLOOKUP(A16,$A$42:$A$59,$B$42:$B$59) -> 0
... A22: Abdellatif | B22: 0 | C22: 0 | D22: 0 | E22: 0 | F22: 0 | G22: =IFERROR(E22/D22,0) -> 0 | H22: 0 | I22: =_xlfn.XLOOKUP(A22,$A$42:$A$59,$B$42:$B$59) -> 0
A23: Total Dues | B23: =SUM(B5:B22) -> 882352.94 | C23: =SUM(C5:C22) -> 1433318.8 | D23: =SUM(D5:D22) -> 4411764.7 | E23: =SUM(E5:E22) -> 6904702.4 | F23: =SUM(F5:F22) -> 15000000 | G23: =IFERROR((E23)/(D23),0) -> 1.5650659 | H23: =SUM(H5:H22) -> 4017950.3 | I23: =SUM(I5:I22) -> 4568723.6
A24: Advances
A25: Abdulla | B25: 0 | C25: 0 | D25: 0 | E25: 0 | F25: 0 | G25: =IFERROR(E25/D25,0) -> 0 | H25: 0 | I25: =_xlfn.XLOOKUP(A25,$A$62:$A$73,$B$62:$B$73) -> 0
A26: Krizia | B26: 0 | C26: 0 | D26: 0 | E26: 0 | F26: 0 | G26: =IFERROR(E26/D26,0) -> 0 | H26: 0 | I26: =_xlfn.XLOOKUP(A26,$A$62:$A$73,$B$62:$B$73) -> 0
A27: Ateev | B27: 0 | C27: 0 | D27: 0 | E27: 0 | F27: 0 | G27: =IFERROR(E27/D27,0) -> 0 | H27: 0 | I27: =_xlfn.XLOOKUP(A27,$A$62:$A$73,$B$62:$B$73) -> 0
A28: Ayari | B28: 0 | C28: 0 | D28: 0 | E28: 0 | F28: 0 | G28: =IFERROR(E28/D28,0) -> 0 | H28: 0 | I28: =_xlfn.XLOOKUP(A28,$A$62:$A$73,$B$62:$B$73) -> 0
A29: Nischitha | B29: 0 | C29: 0 | D29: 0 | E29: 0 | F29: 0 | G29: =IFERROR(E29/D29,0) -> 0 | H29: 0 | I29: =_xlfn.XLOOKUP(A29,$A$62:$A$73,$B$62:$B$73) -> 0
A30: Sherif | B30: 0 | C30: 300758 | D30: 0 | E30: 932004 | F30: 0 | G30: =IFERROR(E30/D30,0) -> 0 | H30: 604342 | I30: =_xlfn.XLOOKUP(A30,$A$62:$A$73,$B$62:$B$73) -> 141386
A31: Wael | B31: 0 | C31: 0 | D31: 0 | E31: 0 | F31: 0 | G31: =IFERROR(E31/D31,0) -> 0 | H31: 0 | I31: =_xlfn.XLOOKUP(A31,$A$62:$A$73,$B$62:$B$73) -> 0
A32: Noha | B32: 0 | C32: 0 | D32: 0 | E32: 0 | F32: 0 | G32: =IFERROR(E32/D32,0) -> 0 | H32: 0 | I32: =_xlfn.XLOOKUP(A32,$A$62:$A$73,$B$62:$B$73) -> 0
A33: Vijay | B33: 0 | C33: 0 | D33: 0 | E33: 0 | F33: 0 | G33: =IFERROR(E33/D33,0) -> 0 | H33: 0 | I33: =_xlfn.XLOOKUP(A33,$A$62:$A$73,$B$62:$B$73) -> 0
A34: Basma | B34: 0 | C34: 0 | D34: 0 | E34: 0 | F34: 0 | G34: =IFERROR(E34/D34,0) -> 0 | H34: 0 | I34: =_xlfn.XLOOKUP(A34,$A$62:$A$73,$B$62:$B$73) -> 0
A35: Yogesh | B35: 0 | C35: 0 | D35: 0 | E35: 0 | F35: 0 | G35: =IFERROR(E35/D35,0) -> 0 | H35: 0 | I35: =_xlfn.XLOOKUP(A35,$A$62:$A$73,$B$62:$B$73) -> 0
A36: Total Advances | B36: =SUM(B25:B35) -> 0 | C36: =SUM(C25:C35) -> 300758 | D36: =SUM(D25:D35) -> 0 | E36: =SUM(E25:E35) -> 932004 | F36: =SUM(F25:F35) -> 0 | G36: =IFERROR(E36/D36,0) -> 0 | H36: =SUM(H25:H35) -> 604342 | I36: =SUM(I25:I35) -> 141386
A37: Grand Total | B37: =SUM(B23,B36) -> 882352.94 | C37: =SUM(C23,C36) -> 1734076.8 | D37: =SUM(D23,D36) -> 4411764.7 | E37: =SUM(E23,E36) -> 7836706.4 | F37: =SUM(F23,F36) -> 15000000 | G37: =IFERROR(E37/D37,0) -> 1.7763201 | H37: =SUM(H23,H36) -> 4622292.3 | I37: =SUM(I23,I36) -> 4710109.6
A39: Downtown
A40: Collection Executive | B40: Not Approved | C40: In Process | D40: Resubmitted | E40: Rejected
A41: Dues
A42: Ali | B42: =SUM(C42:E42) -> 0 | C42: 0 | D42: 0 | E42: 0
A43: Anirudh | B43: =SUM(C43:E43) -> 0 | C43: 0 | D43: 0 | E43: 0
A44: Ruhul | B44: =SUM(C44:E44) -> 0 | C44: 0 | D44: 0 | E44: 0
A45: Karan | B45: =SUM(C45:E45) -> 0 | C45: 0 | D45: 0 | E45: 0
A46: Aqsa | B46: =SUM(C46:E46) -> 0 | C46: 0 | D46: 0 | E46: 0
A47: Sid | B47: =SUM(C47:E47) -> 0 | C47: 0 | D47: 0 | E47: 0
A48: Hussein | B48: =SUM(C48:E48) -> 0 | C48: 0 | D48: 0 | E48: 0
A49: Sabah | B49: =SUM(C49:E49) -> 0 | C49: 0 | D49: 0 | E49: 0
A50: Daria | B50: =SUM(C50:E50) -> 0 | C50: 0 | D50: 0 | E50: 0
A51: Rajiv | B51: =SUM(C51:E51) -> 0 | C51: 0 | D51: 0 | E51: 0
A52: Abdellatif | B52: =SUM(C52:E52) -> 0 | C52: 0 | D52: 0 | E52: 0
A53: Vinod | B53: =SUM(C53:E53) -> 0 | C53: 0 | D53: 0 | E53: 0
... A59: Anna | B59: =SUM(C59:E59) -> 0 | C59: 0 | D59: 0 | E59: 0
A60: Total Dues | B60: =SUM(B42:B59) -> 4568723.6 | C60: =SUM(C42:C59) -> 804509.8 | D60: =SUM(D42:D59) -> 226112.67 | E60: =SUM(E42:E59) -> 3538101.2
A61: Advances
A62: Ayari | B62: =SUM(C62:E62) -> 0 | C62: 0 | D62: 0 | E62: 0
A63: Krizia | B63: =SUM(C63:E63) -> 0 | C63: 0 | D63: 0 | E63: 0
A64: Ateev | B64: =SUM(C64:E64) -> 0 | C64: 0 | D64: 0 | E64: 0
A65: Abdulla | B65: =SUM(C65:E65) -> 0 | C65: 0 | D65: 0 | E65: 0
A66: Wael | B66: =SUM(C66:E66) -> 0 | C66: 0 | D66: 0 | E66: 0
A67: Nischitha | B67: =SUM(C67:E67) -> 0 | C67: 0 | D67: 0 | E67: 0
A68: Sherif | B68: =SUM(C68:E68) -> 141386 | C68: 0 | D68: 0 | E68: 141386
A69: Noha | B69: =SUM(C69:E69) -> 0 | C69: 0 | D69: 0 | E69: 0
A70: Vijay | B70: =SUM(C70:E70) -> 0 | C70: 0 | D70: 0 | E70: 0
A71: Basma | B71: =SUM(C71:E71) -> 0 | C71: 0 | D71: 0 | E71: 0
A72: Yogesh | B72: =SUM(C72:E72) -> 0 | C72: 0 | D72: 0 | E72: 0
A73: Anirudh | B73: =SUM(C73:E73) -> 0 | C73: 0 | D73: 0 | E73: 0
A74: Total Advances | B74: =SUM(B62:B73) -> 141386 | C74: =SUM(C62:C73) -> 0 | D74: =SUM(D62:D73) -> 0 | E74: =SUM(E62:E73) -> 141386
A75: Grand Total | B75: =SUM(B74,B60) -> 4710109.6 | C75: =SUM(C74,C60) -> 804509.8 | D75: =SUM(D74,D60) -> 226112.67 | E75: =SUM(E74,E60) -> 3679487.2
A77: Downtown | C77: Cheque | I77: Other Mode of Payment
A78: Collection Executive | B78: PR Approved | C78: Cancelled | D78: Cleared | E78: PDC | F78: Processed-Sent for Banking | G78: Cheque Hold | H78: UnProcessed | I78: Unallocated | J78: Cancelled | K78: Cleared | L78: UnProcessed | M78: PDC Approved this Month / Amount to be allocated
A79: Dues
A80: Ali | B80: 0 | C80: 0 | D80: 0 | E80: 0 | F80: 0 | G80: 0 | H80: 0 | I80: =SUMIFS('PR Data'!$P:$P,'PR Data'!$Q:$Q,'PR Report - DOWNTOWN'!$A80,'PR Data'!$R:$R,"Approved",'PR Data'!$W:$W,I$78,'PR Data'!$U:$U,'PR Report - DOWNTOWN'!$A$77,'PR Data'!$B:$B,"<>" & "Cheque") -> 0 | J80: =SUMIFS('PR Data'!$P:$P,'PR Data'!$Q:$Q,'PR Report - DOWNTOWN'!$A80,'PR Data'!$R:$R,"Approved",'PR Data'!$W:$W,J$78,'PR Data'!$U:$U,'PR Report - DOWNTOWN'!$A$77,'PR Data'!$B:$B,"<>" & "Cheque") -> 0 | K80: =SUMIFS('PR Data'!$P:$P,'PR Data'!$Q:$Q,'PR Report - DOWNTOWN'!$A80,'PR Data'!$R:$R,"Approved",'PR Data'!$W:$W,K$78,'PR Data'!$U:$U,'PR Report - DOWNTOWN'!$A$77,'PR Data'!$B:$B,"<>" & "Cheque") -> 0 | L80: =SUMIFS('PR Data'!$P:$P,'PR Data'!$Q:$Q,'PR Report - DOWNTOWN'!$A80,'PR Data'!$R:$R,"Approved",'PR Data'!$W:$W,L$78,'PR Data'!$U:$U,'PR Report - DOWNTOWN'!$A$77,'PR Data'!$B:$B,"<>" & "Cheque") -> 0 | M80: =B80-SUM(C80:L80) -> 0
A81: Anirudh | B81: 0 | C81: 0 | D81: 0 | E81: 0 | F81: 0 | G81: 0 | H81: 0 | I81: =SUMIFS('PR Data'!$P:$P,'PR Data'!$Q:$Q,'PR Report - DOWNTOWN'!$A81,'PR Data'!$R:$R,"Approved",'PR Data'!$W:$W,I$78,'PR Data'!$U:$U,'PR Report - DOWNTOWN'!$A$77,'PR Data'!$B:$B,"<>" & "Cheque") -> 0 | J81: =SUMIFS('PR Data'!$P:$P,'PR Data'!$Q:$Q,'PR Report - DOWNTOWN'!$A81,'PR Data'!$R:$R,"Approved",'PR Data'!$W:$W,J$78,'PR Data'!$U:$U,'PR Report - DOWNTOWN'!$A$77,'PR Data'!$B:$B,"<>" & "Cheque") -> 0 | K81: =SUMIFS('PR Data'!$P:$P,'PR Data'!$Q:$Q,'PR Report - DOWNTOWN'!$A81,'PR Data'!$R:$R,"Approved",'PR Data'!$W:$W,K$78,'PR Data'!$U:$U,'PR Report - DOWNTOWN'!$A$77,'PR Data'!$B:$B,"<>" & "Cheque") -> 0 | L81: =SUMIFS('PR Data'!$P:$P,'PR Data'!$Q:$Q,'PR Report - DOWNTOWN'!$A81,'PR Data'!$R:$R,"Approved",'PR Data'!$W:$W,L$78,'PR Data'!$U:$U,'PR Report - DOWNTOWN'!$A$77,'PR Data'!$B:$B,"<>" & "Cheque") -> 0 | M81: =B81-SUM(C81:L81) -> 0
A82: Ruhul | B82: 0 | C82: 0 | D82: 0 | E82: 0 | F82: 0 | G82: 0 | H82: 0 | I82: =SUMIFS('PR Data'!$P:$P,'PR Data'!$Q:$Q,'PR Report - DOWNTOWN'!$A82,'PR Data'!$R:$R,"Approved",'PR Data'!$W:$W,I$78,'PR Data'!$U:$U,'PR Report - DOWNTOWN'!$A$77,'PR Data'!$B:$B,"<>" & "Cheque") -> 0 | J82: =SUMIFS('PR Data'!$P:$P,'PR Data'!$Q:$Q,'PR Report - DOWNTOWN'!$A82,'PR Data'!$R:$R,"Approved",'PR Data'!$W:$W,J$78,'PR Data'!$U:$U,'PR Report - DOWNTOWN'!$A$77,'PR Data'!$B:$B,"<>" & "Cheque") -> 0 | K82: =SUMIFS('PR Data'!$P:$P,'PR Data'!$Q:$Q,'PR Report - DOWNTOWN'!$A82,'PR Data'!$R:$R,"Approved",'PR Data'!$W:$W,K$78,'PR Data'!$U:$U,'PR Report - DOWNTOWN'!$A$77,'PR Data'!$B:$B,"<>" & "Cheque") -> 0 | L82: =SUMIFS('PR Data'!$P:$P,'PR Data'!$Q:$Q,'PR Report - DOWNTOWN'!$A82,'PR Data'!$R:$R,"Approved",'PR Data'!$W:$W,L$78,'PR Data'!$U:$U,'PR Report - DOWNTOWN'!$A$77,'PR Data'!$B:$B,"<>" & "Cheque") -> 0 | M82: =B82-SUM(C82:L82) -> 0
A83: Karan | B83: 0 | C83: 0 | D83: 0 | E83: 0 | F83: 0 | G83: 0 | H83: 0 | I83: =SUMIFS('PR Data'!$P:$P,'PR Data'!$Q:$Q,'PR Report - DOWNTOWN'!$A83,'PR Data'!$R:$R,"Approved",'PR Data'!$W:$W,I$78,'PR Data'!$U:$U,'PR Report - DOWNTOWN'!$A$77,'PR Data'!$B:$B,"<>" & "Cheque") -> 0 | J83: =SUMIFS('PR Data'!$P:$P,'PR Data'!$Q:$Q,'PR Report - DOWNTOWN'!$A83,'PR Data'!$R:$R,"Approved",'PR Data'!$W:$W,J$78,'PR Data'!$U:$U,'PR Report - DOWNTOWN'!$A$77,'PR Data'!$B:$B,"<>" & "Cheque") -> 0 | K83: =SUMIFS('PR Data'!$P:$P,'PR Data'!$Q:$Q,'PR Report - DOWNTOWN'!$A83,'PR Data'!$R:$R,"Approved",'PR Data'!$W:$W,K$78,'PR Data'!$U:$U,'PR Report - DOWNTOWN'!$A$77,'PR Data'!$B:$B,"<>" & "Cheque") -> 0 | L83: =SUMIFS('PR Data'!$P:$P,'PR Data'!$Q:$Q,'PR Report - DOWNTOWN'!$A83,'PR Data'!$R:$R,"Approved",'PR Data'!$W:$W,L$78,'PR Data'!$U:$U,'PR Report - DOWNTOWN'!$A$77,'PR Data'!$B:$B,"<>" & "Cheque") -> 0 | M83: =B83-SUM(C83:L83) -> 0
A84: Sid | B84: 0 | C84: 0 | D84: 0 | E84: 0 | F84: 0 | G84: 0 | H84: 0 | I84: =SUMIFS('PR Data'!$P:$P,'PR Data'!$Q:$Q,'PR Report - DOWNTOWN'!$A84,'PR Data'!$R:$R,"Approved",'PR Data'!$W:$W,I$78,'PR Data'!$U:$U,'PR Report - DOWNTOWN'!$A$77,'PR Data'!$B:$B,"<>" & "Cheque") -> 0 | J84: =SUMIFS('PR Data'!$P:$P,'PR Data'!$Q:$Q,'PR Report - DOWNTOWN'!$A84,'PR Data'!$R:$R,"Approved",'PR Data'!$W:$W,J$78,'PR Data'!$U:$U,'PR Report - DOWNTOWN'!$A$77,'PR Data'!$B:$B,"<>" & "Cheque") -> 0 | K84: =SUMIFS('PR Data'!$P:$P,'PR Data'!$Q:$Q,'PR Report - DOWNTOWN'!$A84,'PR Data'!$R:$R,"Approved",'PR Data'!$W:$W,K$78,'PR Data'!$U:$U,'PR Report - DOWNTOWN'!$A$77,'PR Data'!$B:$B,"<>" & "Cheque") -> 0 | L84: =SUMIFS('PR Data'!$P:$P,'PR Data'!$Q:$Q,'PR Report - DOWNTOWN'!$A84,'PR Data'!$R:$R,"Approved",'PR Data'!$W:$W,L$78,'PR Data'!$U:$U,'PR Report - DOWNTOWN'!$A$77,'PR Data'!$B:$B,"<>" & "Cheque") -> 0 | M84: =B84-SUM(C84:L84) -> 0
A85: Hussein | B85: 0 | C85: 0 | D85: 0 | E85: 0 | F85: 0 | G85: 0 | H85: 0 | I85: =SUMIFS('PR Data'!$P:$P,'PR Data'!$Q:$Q,'PR Report - DOWNTOWN'!$A85,'PR Data'!$R:$R,"Approved",'PR Data'!$W:$W,I$78,'PR Data'!$U:$U,'PR Report - DOWNTOWN'!$A$77,'PR Data'!$B:$B,"<>" & "Cheque") -> 0 | J85: =SUMIFS('PR Data'!$P:$P,'PR Data'!$Q:$Q,'PR Report - DOWNTOWN'!$A85,'PR Data'!$R:$R,"Approved",'PR Data'!$W:$W,J$78,'PR Data'!$U:$U,'PR Report - DOWNTOWN'!$A$77,'PR Data'!$B:$B,"<>" & "Cheque") -> 0 | K85: =SUMIFS('PR Data'!$P:$P,'PR Data'!$Q:$Q,'PR Report - DOWNTOWN'!$A85,'PR Data'!$R:$R,"Approved",'PR Data'!$W:$W,K$78,'PR Data'!$U:$U,'PR Report - DOWNTOWN'!$A$77,'PR Data'!$B:$B,"<>" & "Cheque") -> 0 | L85: =SUMIFS('PR Data'!$P:$P,'PR Data'!$Q:$Q,'PR Report - DOWNTOWN'!$A85,'PR Data'!$R:$R,"Approved",'PR Data'!$W:$W,L$78,'PR Data'!$U:$U,'PR Report - DOWNTOWN'!$A$77,'PR Data'!$B:$B,"<>" & "Cheque") -> 0 | M85: =B85-SUM(C85:L85) -> 0
A86: Sabah | B86: 0 | C86: 0 | D86: 0 | E86: 0 | F86: 0 | G86: 0 | H86: 0 | I86: =SUMIFS('PR Data'!$P:$P,'PR Data'!$Q:$Q,'PR Report - DOWNTOWN'!$A86,'PR Data'!$R:$R,"Approved",'PR Data'!$W:$W,I$78,'PR Data'!$U:$U,'PR Report - DOWNTOWN'!$A$77,'PR Data'!$B:$B,"<>" & "Cheque") -> 0 | J86: =SUMIFS('PR Data'!$P:$P,'PR Data'!$Q:$Q,'PR Report - DOWNTOWN'!$A86,'PR Data'!$R:$R,"Approved",'PR Data'!$W:$W,J$78,'PR Data'!$U:$U,'PR Report - DOWNTOWN'!$A$77,'PR Data'!$B:$B,"<>" & "Cheque") -> 0 | K86: =SUMIFS('PR Data'!$P:$P,'PR Data'!$Q:$Q,'PR Report - DOWNTOWN'!$A86,'PR Data'!$R:$R,"Approved",'PR Data'!$W:$W,K$78,'PR Data'!$U:$U,'PR Report - DOWNTOWN'!$A$77,'PR Data'!$B:$B,"<>" & "Cheque") -> 0 | L86: =SUMIFS('PR Data'!$P:$P,'PR Data'!$Q:$Q,'PR Report - DOWNTOWN'!$A86,'PR Data'!$R:$R,"Approved",'PR Data'!$W:$W,L$78,'PR Data'!$U:$U,'PR Report - DOWNTOWN'!$A$77,'PR Data'!$B:$B,"<>" & "Cheque") -> 0 | M86: =B86-SUM(C86:L86) -> 0
A87: Daria | B87: 0 | C87: 0 | D87: 0 | E87: 0 | F87: 0 | G87: 0 | H87: 0 | I87: =SUMIFS('PR Data'!$P:$P,'PR Data'!$Q:$Q,'PR Report - DOWNTOWN'!$A87,'PR Data'!$R:$R,"Approved",'PR Data'!$W:$W,I$78,'PR Data'!$U:$U,'PR Report - DOWNTOWN'!$A$77,'PR Data'!$B:$B,"<>" & "Cheque") -> 0 | J87: =SUMIFS('PR Data'!$P:$P,'PR Data'!$Q:$Q,'PR Report - DOWNTOWN'!$A87,'PR Data'!$R:$R,"Approved",'PR Data'!$W:$W,J$78,'PR Data'!$U:$U,'PR Report - DOWNTOWN'!$A$77,'PR Data'!$B:$B,"<>" & "Cheque") -> 0 | K87: =SUMIFS('PR Data'!$P:$P,'PR Data'!$Q:$Q,'PR Report - DOWNTOWN'!$A87,'PR Data'!$R:$R,"Approved",'PR Data'!$W:$W,K$78,'PR Data'!$U:$U,'PR Report - DOWNTOWN'!$A$77,'PR Data'!$B:$B,"<>" & "Cheque") -> 0 | L87: =SUMIFS('PR Data'!$P:$P,'PR Data'!$Q:$Q,'PR Report - DOWNTOWN'!$A87,'PR Data'!$R:$R,"Approved",'PR Data'!$W:$W,L$78,'PR Data'!$U:$U,'PR Report - DOWNTOWN'!$A$77,'PR Data'!$B:$B,"<>" & "Cheque") -> 0 | M87: =B87-SUM(C87:L87) -> 0
A88: Rajiv | B88: 0 | C88: 0 | D88: 0 | E88: 0 | F88: 0 | G88: 0 | H88: 0 | I88: =SUMIFS('PR Data'!$P:$P,'PR Data'!$Q:$Q,'PR Report - DOWNTOWN'!$A88,'PR Data'!$R:$R,"Approved",'PR Data'!$W:$W,I$78,'PR Data'!$U:$U,'PR Report - DOWNTOWN'!$A$77,'PR Data'!$B:$B,"<>" & "Cheque") -> 0 | J88: =SUMIFS('PR Data'!$P:$P,'PR Data'!$Q:$Q,'PR Report - DOWNTOWN'!$A88,'PR Data'!$R:$R,"Approved",'PR Data'!$W:$W,J$78,'PR Data'!$U:$U,'PR Report - DOWNTOWN'!$A$77,'PR Data'!$B:$B,"<>" & "Cheque") -> 0 | K88: =SUMIFS('PR Data'!$P:$P,'PR Data'!$Q:$Q,'PR Report - DOWNTOWN'!$A88,'PR Data'!$R:$R,"Approved",'PR Data'!$W:$W,K$78,'PR Data'!$U:$U,'PR Report - DOWNTOWN'!$A$77,'PR Data'!$B:$B,"<>" & "Cheque") -> 0 | L88: =SUMIFS('PR Data'!$P:$P,'PR Data'!$Q:$Q,'PR Report - DOWNTOWN'!$A88,'PR Data'!$R:$R,"Approved",'PR Data'!$W:$W,L$78,'PR Data'!$U:$U,'PR Report - DOWNTOWN'!$A$77,'PR Data'!$B:$B,"<>" & "Cheque") -> 0 | M88: =B88-SUM(C88:L88) -> 0
A89: Abdellatif | B89: 0 | C89: 0 | D89: 0 | E89: 0 | F89: 0 | G89: 0 | H89: 0 | I89: =SUMIFS('PR Data'!$P:$P,'PR Data'!$Q:$Q,'PR Report - DOWNTOWN'!$A89,'PR Data'!$R:$R,"Approved",'PR Data'!$W:$W,I$78,'PR Data'!$U:$U,'PR Report - DOWNTOWN'!$A$77,'PR Data'!$B:$B,"<>" & "Cheque") -> 0 | J89: =SUMIFS('PR Data'!$P:$P,'PR Data'!$Q:$Q,'PR Report - DOWNTOWN'!$A89,'PR Data'!$R:$R,"Approved",'PR Data'!$W:$W,J$78,'PR Data'!$U:$U,'PR Report - DOWNTOWN'!$A$77,'PR Data'!$B:$B,"<>" & "Cheque") -> 0 | K89: =SUMIFS('PR Data'!$P:$P,'PR Data'!$Q:$Q,'PR Report - DOWNTOWN'!$A89,'PR Data'!$R:$R,"Approved",'PR Data'!$W:$W,K$78,'PR Data'!$U:$U,'PR Report - DOWNTOWN'!$A$77,'PR Data'!$B:$B,"<>" & "Cheque") -> 0 | L89: =SUMIFS('PR Data'!$P:$P,'PR Data'!$Q:$Q,'PR Report - DOWNTOWN'!$A89,'PR Data'!$R:$R,"Approved",'PR Data'!$W:$W,L$78,'PR Data'!$U:$U,'PR Report - DOWNTOWN'!$A$77,'PR Data'!$B:$B,"<>" & "Cheque") -> 0 | M89: =B89-SUM(C89:L89) -> 0
A90: Aqsa | B90: 0 | C90: 0 | D90: 0 | E90: 0 | F90: 0 | G90: 0 | H90: 0 | I90: =SUMIFS('PR Data'!$P:$P,'PR Data'!$Q:$Q,'PR Report - DOWNTOWN'!$A90,'PR Data'!$R:$R,"Approved",'PR Data'!$W:$W,I$78,'PR Data'!$U:$U,'PR Report - DOWNTOWN'!$A$77,'PR Data'!$B:$B,"<>" & "Cheque") -> 0 | J90: =SUMIFS('PR Data'!$P:$P,'PR Data'!$Q:$Q,'PR Report - DOWNTOWN'!$A90,'PR Data'!$R:$R,"Approved",'PR Data'!$W:$W,J$78,'PR Data'!$U:$U,'PR Report - DOWNTOWN'!$A$77,'PR Data'!$B:$B,"<>" & "Cheque") -> 0 | K90: =SUMIFS('PR Data'!$P:$P,'PR Data'!$Q:$Q,'PR Report - DOWNTOWN'!$A90,'PR Data'!$R:$R,"Approved",'PR Data'!$W:$W,K$78,'PR Data'!$U:$U,'PR Report - DOWNTOWN'!$A$77,'PR Data'!$B:$B,"<>" & "Cheque") -> 0 | L90: =SUMIFS('PR Data'!$P:$P,'PR Data'!$Q:$Q,'PR Report - DOWNTOWN'!$A90,'PR Data'!$R:$R,"Approved",'PR Data'!$W:$W,L$78,'PR Data'!$U:$U,'PR Report - DOWNTOWN'!$A$77,'PR Data'!$B:$B,"<>" & "Cheque") -> 0 | M90: =B90-SUM(C90:L90) -> 0
A91: Vinod | B91: 0 | C91: 0 | D91: 0 | E91: 0 | F91: 0 | G91: 0 | H91: 0 | I91: =SUMIFS('PR Data'!$P:$P,'PR Data'!$Q:$Q,'PR Report - DOWNTOWN'!$A91,'PR Data'!$R:$R,"Approved",'PR Data'!$W:$W,I$78,'PR Data'!$U:$U,'PR Report - DOWNTOWN'!$A$77,'PR Data'!$B:$B,"<>" & "Cheque") -> 0 | J91: =SUMIFS('PR Data'!$P:$P,'PR Data'!$Q:$Q,'PR Report - DOWNTOWN'!$A91,'PR Data'!$R:$R,"Approved",'PR Data'!$W:$W,J$78,'PR Data'!$U:$U,'PR Report - DOWNTOWN'!$A$77,'PR Data'!$B:$B,"<>" & "Cheque") -> 0 | K91: =SUMIFS('PR Data'!$P:$P,'PR Data'!$Q:$Q,'PR Report - DOWNTOWN'!$A91,'PR Data'!$R:$R,"Approved",'PR Data'!$W:$W,K$78,'PR Data'!$U:$U,'PR Report - DOWNTOWN'!$A$77,'PR Data'!$B:$B,"<>" & "Cheque") -> 0 | L91: =SUMIFS('PR Data'!$P:$P,'PR Data'!$Q:$Q,'PR Report - DOWNTOWN'!$A91,'PR Data'!$R:$R,"Approved",'PR Data'!$W:$W,L$78,'PR Data'!$U:$U,'PR Report - DOWNTOWN'!$A$77,'PR Data'!$B:$B,"<>" & "Cheque") -> 0 | M91: =B91-SUM(C91:L91) -> 0
... A98: Anna | B98: 0 | C98: 0 | D98: 0 | E98: 0 | F98: 0 | G98: 0 | H98: 0 | I98: =SUMIFS('PR Data'!$P:$P,'PR Data'!$Q:$Q,'PR Report - DOWNTOWN'!$A98,'PR Data'!$R:$R,"Approved",'PR Data'!$W:$W,I$78,'PR Data'!$U:$U,'PR Report - DOWNTOWN'!$A$77,'PR Data'!$B:$B,"<>" & "Cheque") -> 0 | J98: =SUMIFS('PR Data'!$P:$P,'PR Data'!$Q:$Q,'PR Report - DOWNTOWN'!$A98,'PR Data'!$R:$R,"Approved",'PR Data'!$W:$W,J$78,'PR Data'!$U:$U,'PR Report - DOWNTOWN'!$A$77,'PR Data'!$B:$B,"<>" & "Cheque") -> 0 | K98: =SUMIFS('PR Data'!$P:$P,'PR Data'!$Q:$Q,'PR Report - DOWNTOWN'!$A98,'PR Data'!$R:$R,"Approved",'PR Data'!$W:$W,K$78,'PR Data'!$U:$U,'PR Report - DOWNTOWN'!$A$77,'PR Data'!$B:$B,"<>" & "Cheque") -> 0 | L98: =SUMIFS('PR Data'!$P:$P,'PR Data'!$Q:$Q,'PR Report - DOWNTOWN'!$A98,'PR Data'!$R:$R,"Approved",'PR Data'!$W:$W,L$78,'PR Data'!$U:$U,'PR Report - DOWNTOWN'!$A$77,'PR Data'!$B:$B,"<>" & "Cheque") -> 0 | M98: =B98-SUM(C98:L98) -> 0
A99: Total Dues | B99: =SUM(B80:B97) -> 4017950.3 | C99: =SUM(C80:C97) -> 0 | D99: =SUM(D80:D97) -> 0 | E99: =SUM(E80:E97) -> 0 | F99: =SUM(F80:F97) -> 0 | G99: =SUM(G80:G97) -> 0 | H99: =SUM(H80:H97) -> 0 | I99: =SUM(I80:I97) -> 54215.9 | ... M99: =SUM(M80:M97) -> 0
A100: Advances
A101: Ayari | B101: 0 | C101: 0 | D101: 0 | E101: 0 | F101: 0 | G101: 0 | H101: 0 | I101: =SUMIFS('PR Data'!$P:$P,'PR Data'!$Q:$Q,'PR Report - DOWNTOWN'!$A101,'PR Data'!$R:$R,"Approved",'PR Data'!$W:$W,I$78,'PR Data'!$U:$U,'PR Report - DOWNTOWN'!$A$77,'PR Data'!$B:$B,"<>" & "Cheque") -> 0 | J101: =SUMIFS('PR Data'!$P:$P,'PR Data'!$Q:$Q,'PR Report - DOWNTOWN'!$A101,'PR Data'!$R:$R,"Approved",'PR Data'!$W:$W,J$78,'PR Data'!$U:$U,'PR Report - DOWNTOWN'!$A$77,'PR Data'!$B:$B,"<>" & "Cheque") -> 0 | K101: =SUMIFS('PR Data'!$P:$P,'PR Data'!$Q:$Q,'PR Report - DOWNTOWN'!$A101,'PR Data'!$R:$R,"Approved",'PR Data'!$W:$W,K$78,'PR Data'!$U:$U,'PR Report - DOWNTOWN'!$A$77,'PR Data'!$B:$B,"<>" & "Cheque") -> 0 | L101: =SUMIFS('PR Data'!$P:$P,'PR Data'!$Q:$Q,'PR Report - DOWNTOWN'!$A101,'PR Data'!$R:$R,"Approved",'PR Data'!$W:$W,L$78,'PR Data'!$U:$U,'PR Report - DOWNTOWN'!$A$77,'PR Data'!$B:$B,"<>" & "Cheque") -> 0 | M101: =B101-SUM(C101:L101) -> 0
A102: Krizia | B102: 0 | C102: 0 | D102: 0 | E102: 0 | F102: 0 | G102: 0 | H102: 0 | I102: =SUMIFS('PR Data'!$P:$P,'PR Data'!$Q:$Q,'PR Report - DOWNTOWN'!$A102,'PR Data'!$R:$R,"Approved",'PR Data'!$W:$W,I$78,'PR Data'!$U:$U,'PR Report - DOWNTOWN'!$A$77,'PR Data'!$B:$B,"<>" & "Cheque") -> 0 | J102: =SUMIFS('PR Data'!$P:$P,'PR Data'!$Q:$Q,'PR Report - DOWNTOWN'!$A102,'PR Data'!$R:$R,"Approved",'PR Data'!$W:$W,J$78,'PR Data'!$U:$U,'PR Report - DOWNTOWN'!$A$77,'PR Data'!$B:$B,"<>" & "Cheque") -> 0 | K102: =SUMIFS('PR Data'!$P:$P,'PR Data'!$Q:$Q,'PR Report - DOWNTOWN'!$A102,'PR Data'!$R:$R,"Approved",'PR Data'!$W:$W,K$78,'PR Data'!$U:$U,'PR Report - DOWNTOWN'!$A$77,'PR Data'!$B:$B,"<>" & "Cheque") -> 0 | L102: =SUMIFS('PR Data'!$P:$P,'PR Data'!$Q:$Q,'PR Report - DOWNTOWN'!$A102,'PR Data'!$R:$R,"Approved",'PR Data'!$W:$W,L$78,'PR Data'!$U:$U,'PR Report - DOWNTOWN'!$A$77,'PR Data'!$B:$B,"<>" & "Cheque") -> 0 | M102: =B102-SUM(C102:L102) -> 0
A103: Abdulla | B103: 0 | C103: 0 | D103: 0 | E103: 0 | F103: 0 | G103: 0 | H103: 0 | I103: =SUMIFS('PR Data'!$P:$P,'PR Data'!$Q:$Q,'PR Report - DOWNTOWN'!$A103,'PR Data'!$R:$R,"Approved",'PR Data'!$W:$W,I$78,'PR Data'!$U:$U,'PR Report - DOWNTOWN'!$A$77,'PR Data'!$B:$B,"<>" & "Cheque") -> 0 | J103: =SUMIFS('PR Data'!$P:$P,'PR Data'!$Q:$Q,'PR Report - DOWNTOWN'!$A103,'PR Data'!$R:$R,"Approved",'PR Data'!$W:$W,J$78,'PR Data'!$U:$U,'PR Report - DOWNTOWN'!$A$77,'PR Data'!$B:$B,"<>" & "Cheque") -> 0 | K103: =SUMIFS('PR Data'!$P:$P,'PR Data'!$Q:$Q,'PR Report - DOWNTOWN'!$A103,'PR Data'!$R:$R,"Approved",'PR Data'!$W:$W,K$78,'PR Data'!$U:$U,'PR Report - DOWNTOWN'!$A$77,'PR Data'!$B:$B,"<>" & "Cheque") -> 0 | L103: =SUMIFS('PR Data'!$P:$P,'PR Data'!$Q:$Q,'PR Report - DOWNTOWN'!$A103,'PR Data'!$R:$R,"Approved",'PR Data'!$W:$W,L$78,'PR Data'!$U:$U,'PR Report - DOWNTOWN'!$A$77,'PR Data'!$B:$B,"<>" & "Cheque") -> 0 | M103: =B103-SUM(C103:L103) -> 0
A104: Ateev | B104: 0 | C104: 0 | D104: 0 | E104: 0 | F104: 0 | G104: 0 | H104: 0 | I104: =SUMIFS('PR Data'!$P:$P,'PR Data'!$Q:$Q,'PR Report - DOWNTOWN'!$A104,'PR Data'!$R:$R,"Approved",'PR Data'!$W:$W,I$78,'PR Data'!$U:$U,'PR Report - DOWNTOWN'!$A$77,'PR Data'!$B:$B,"<>" & "Cheque") -> 0 | J104: =SUMIFS('PR Data'!$P:$P,'PR Data'!$Q:$Q,'PR Report - DOWNTOWN'!$A104,'PR Data'!$R:$R,"Approved",'PR Data'!$W:$W,J$78,'PR Data'!$U:$U,'PR Report - DOWNTOWN'!$A$77,'PR Data'!$B:$B,"<>" & "Cheque") -> 0 | K104: =SUMIFS('PR Data'!$P:$P,'PR Data'!$Q:$Q,'PR Report - DOWNTOWN'!$A104,'PR Data'!$R:$R,"Approved",'PR Data'!$W:$W,K$78,'PR Data'!$U:$U,'PR Report - DOWNTOWN'!$A$77,'PR Data'!$B:$B,"<>" & "Cheque") -> 0 | L104: =SUMIFS('PR Data'!$P:$P,'PR Data'!$Q:$Q,'PR Report - DOWNTOWN'!$A104,'PR Data'!$R:$R,"Approved",'PR Data'!$W:$W,L$78,'PR Data'!$U:$U,'PR Report - DOWNTOWN'!$A$77,'PR Data'!$B:$B,"<>" & "Cheque") -> 0 | M104: =B104-SUM(C104:L104) -> 0
A105: Wael | B105: 0 | C105: 0 | D105: 0 | E105: 0 | F105: 0 | G105: 0 | H105: 0 | I105: =SUMIFS('PR Data'!$P:$P,'PR Data'!$Q:$Q,'PR Report - DOWNTOWN'!$A105,'PR Data'!$R:$R,"Approved",'PR Data'!$W:$W,I$78,'PR Data'!$U:$U,'PR Report - DOWNTOWN'!$A$77,'PR Data'!$B:$B,"<>" & "Cheque") -> 0 | J105: =SUMIFS('PR Data'!$P:$P,'PR Data'!$Q:$Q,'PR Report - DOWNTOWN'!$A105,'PR Data'!$R:$R,"Approved",'PR Data'!$W:$W,J$78,'PR Data'!$U:$U,'PR Report - DOWNTOWN'!$A$77,'PR Data'!$B:$B,"<>" & "Cheque") -> 0 | K105: =SUMIFS('PR Data'!$P:$P,'PR Data'!$Q:$Q,'PR Report - DOWNTOWN'!$A105,'PR Data'!$R:$R,"Approved",'PR Data'!$W:$W,K$78,'PR Data'!$U:$U,'PR Report - DOWNTOWN'!$A$77,'PR Data'!$B:$B,"<>" & "Cheque") -> 0 | L105: =SUMIFS('PR Data'!$P:$P,'PR Data'!$Q:$Q,'PR Report - DOWNTOWN'!$A105,'PR Data'!$R:$R,"Approved",'PR Data'!$W:$W,L$78,'PR Data'!$U:$U,'PR Report - DOWNTOWN'!$A$77,'PR Data'!$B:$B,"<>" & "Cheque") -> 0 | M105: =B105-SUM(C105:L105) -> 0
A106: Sherif | B106: 604342 | C106: 0 | D106: 0 | E106: 0 | F106: 0 | G106: 0 | H106: 0 | I106: =SUMIFS('PR Data'!$P:$P,'PR Data'!$Q:$Q,'PR Report - DOWNTOWN'!$A106,'PR Data'!$R:$R,"Approved",'PR Data'!$W:$W,I$78,'PR Data'!$U:$U,'PR Report - DOWNTOWN'!$A$77,'PR Data'!$B:$B,"<>" & "Cheque") -> 150000 | J106: =SUMIFS('PR Data'!$P:$P,'PR Data'!$Q:$Q,'PR Report - DOWNTOWN'!$A106,'PR Data'!$R:$R,"Approved",'PR Data'!$W:$W,J$78,'PR Data'!$U:$U,'PR Report - DOWNTOWN'!$A$77,'PR Data'!$B:$B,"<>" & "Cheque") -> 0 | K106: =SUMIFS('PR Data'!$P:$P,'PR Data'!$Q:$Q,'PR Report - DOWNTOWN'!$A106,'PR Data'!$R:$R,"Approved",'PR Data'!$W:$W,K$78,'PR Data'!$U:$U,'PR Report - DOWNTOWN'!$A$77,'PR Data'!$B:$B,"<>" & "Cheque") -> 454342 | L106: =SUMIFS('PR Data'!$P:$P,'PR Data'!$Q:$Q,'PR Report - DOWNTOWN'!$A106,'PR Data'!$R:$R,"Approved",'PR Data'!$W:$W,L$78,'PR Data'!$U:$U,'PR Report - DOWNTOWN'!$A$77,'PR Data'!$B:$B,"<>" & "Cheque") -> 0 | M106: =B106-SUM(C106:L106) -> 0
A107: Nischitha | B107: 0 | C107: 0 | D107: 0 | E107: 0 | F107: 0 | G107: 0 | H107: 0 | I107: =SUMIFS('PR Data'!$P:$P,'PR Data'!$Q:$Q,'PR Report - DOWNTOWN'!$A107,'PR Data'!$R:$R,"Approved",'PR Data'!$W:$W,I$78,'PR Data'!$U:$U,'PR Report - DOWNTOWN'!$A$77,'PR Data'!$B:$B,"<>" & "Cheque") -> 0 | J107: =SUMIFS('PR Data'!$P:$P,'PR Data'!$Q:$Q,'PR Report - DOWNTOWN'!$A107,'PR Data'!$R:$R,"Approved",'PR Data'!$W:$W,J$78,'PR Data'!$U:$U,'PR Report - DOWNTOWN'!$A$77,'PR Data'!$B:$B,"<>" & "Cheque") -> 0 | K107: =SUMIFS('PR Data'!$P:$P,'PR Data'!$Q:$Q,'PR Report - DOWNTOWN'!$A107,'PR Data'!$R:$R,"Approved",'PR Data'!$W:$W,K$78,'PR Data'!$U:$U,'PR Report - DOWNTOWN'!$A$77,'PR Data'!$B:$B,"<>" & "Cheque") -> 0 | L107: =SUMIFS('PR Data'!$P:$P,'PR Data'!$Q:$Q,'PR Report - DOWNTOWN'!$A107,'PR Data'!$R:$R,"Approved",'PR Data'!$W:$W,L$78,'PR Data'!$U:$U,'PR Report - DOWNTOWN'!$A$77,'PR Data'!$B:$B,"<>" & "Cheque") -> 0 | M107: =B107-SUM(C107:L107) -> 0
A108: Noha | B108: 0 | C108: 0 | D108: 0 | E108: 0 | F108: 0 | G108: 0 | H108: 0 | I108: =SUMIFS('PR Data'!$P:$P,'PR Data'!$Q:$Q,'PR Report - DOWNTOWN'!$A108,'PR Data'!$R:$R,"Approved",'PR Data'!$W:$W,I$78,'PR Data'!$U:$U,'PR Report - DOWNTOWN'!$A$77,'PR Data'!$B:$B,"<>" & "Cheque") -> 0 | J108: =SUMIFS('PR Data'!$P:$P,'PR Data'!$Q:$Q,'PR Report - DOWNTOWN'!$A108,'PR Data'!$R:$R,"Approved",'PR Data'!$W:$W,J$78,'PR Data'!$U:$U,'PR Report - DOWNTOWN'!$A$77,'PR Data'!$B:$B,"<>" & "Cheque") -> 0 | K108: =SUMIFS('PR Data'!$P:$P,'PR Data'!$Q:$Q,'PR Report - DOWNTOWN'!$A108,'PR Data'!$R:$R,"Approved",'PR Data'!$W:$W,K$78,'PR Data'!$U:$U,'PR Report - DOWNTOWN'!$A$77,'PR Data'!$B:$B,"<>" & "Cheque") -> 0 | L108: =SUMIFS('PR Data'!$P:$P,'PR Data'!$Q:$Q,'PR Report - DOWNTOWN'!$A108,'PR Data'!$R:$R,"Approved",'PR Data'!$W:$W,L$78,'PR Data'!$U:$U,'PR Report - DOWNTOWN'!$A$77,'PR Data'!$B:$B,"<>" & "Cheque") -> 0 | M108: =B108-SUM(C108:L108) -> 0
A109: Vijay | B109: 0 | C109: 0 | D109: 0 | E109: 0 | F109: 0 | G109: 0 | H109: 0 | I109: =SUMIFS('PR Data'!$P:$P,'PR Data'!$Q:$Q,'PR Report - DOWNTOWN'!$A109,'PR Data'!$R:$R,"Approved",'PR Data'!$W:$W,I$78,'PR Data'!$U:$U,'PR Report - DOWNTOWN'!$A$77,'PR Data'!$B:$B,"<>" & "Cheque") -> 0 | J109: =SUMIFS('PR Data'!$P:$P,'PR Data'!$Q:$Q,'PR Report - DOWNTOWN'!$A109,'PR Data'!$R:$R,"Approved",'PR Data'!$W:$W,J$78,'PR Data'!$U:$U,'PR Report - DOWNTOWN'!$A$77,'PR Data'!$B:$B,"<>" & "Cheque") -> 0 | K109: =SUMIFS('PR Data'!$P:$P,'PR Data'!$Q:$Q,'PR Report - DOWNTOWN'!$A109,'PR Data'!$R:$R,"Approved",'PR Data'!$W:$W,K$78,'PR Data'!$U:$U,'PR Report - DOWNTOWN'!$A$77,'PR Data'!$B:$B,"<>" & "Cheque") -> 0 | L109: =SUMIFS('PR Data'!$P:$P,'PR Data'!$Q:$Q,'PR Report - DOWNTOWN'!$A109,'PR Data'!$R:$R,"Approved",'PR Data'!$W:$W,L$78,'PR Data'!$U:$U,'PR Report - DOWNTOWN'!$A$77,'PR Data'!$B:$B,"<>" & "Cheque") -> 0
A110: Basma | B110: 0 | C110: 0 | D110: 0 | E110: 0 | F110: 0 | G110: 0 | H110: 0 | I110: =SUMIFS('PR Data'!$P:$P,'PR Data'!$Q:$Q,'PR Report - DOWNTOWN'!$A110,'PR Data'!$R:$R,"Approved",'PR Data'!$W:$W,I$78,'PR Data'!$U:$U,'PR Report - DOWNTOWN'!$A$77,'PR Data'!$B:$B,"<>" & "Cheque") -> 0 | J110: =SUMIFS('PR Data'!$P:$P,'PR Data'!$Q:$Q,'PR Report - DOWNTOWN'!$A110,'PR Data'!$R:$R,"Approved",'PR Data'!$W:$W,J$78,'PR Data'!$U:$U,'PR Report - DOWNTOWN'!$A$77,'PR Data'!$B:$B,"<>" & "Cheque") -> 0 | K110: =SUMIFS('PR Data'!$P:$P,'PR Data'!$Q:$Q,'PR Report - DOWNTOWN'!$A110,'PR Data'!$R:$R,"Approved",'PR Data'!$W:$W,K$78,'PR Data'!$U:$U,'PR Report - DOWNTOWN'!$A$77,'PR Data'!$B:$B,"<>" & "Cheque") -> 0 | L110: =SUMIFS('PR Data'!$P:$P,'PR Data'!$Q:$Q,'PR Report - DOWNTOWN'!$A110,'PR Data'!$R:$R,"Approved",'PR Data'!$W:$W,L$78,'PR Data'!$U:$U,'PR Report - DOWNTOWN'!$A$77,'PR Data'!$B:$B,"<>" & "Cheque") -> 0 | M110: =B110-SUM(C110:L110) -> 0
A111: Yogesh | B111: 0 | C111: 0 | D111: 0 | E111: 0 | F111: 0 | G111: 0 | H111: 0 | I111: =SUMIFS('PR Data'!$P:$P,'PR Data'!$Q:$Q,'PR Report - DOWNTOWN'!$A111,'PR Data'!$R:$R,"Approved",'PR Data'!$W:$W,I$78,'PR Data'!$U:$U,'PR Report - DOWNTOWN'!$A$77,'PR Data'!$B:$B,"<>" & "Cheque") -> 0 | J111: =SUMIFS('PR Data'!$P:$P,'PR Data'!$Q:$Q,'PR Report - DOWNTOWN'!$A111,'PR Data'!$R:$R,"Approved",'PR Data'!$W:$W,J$78,'PR Data'!$U:$U,'PR Report - DOWNTOWN'!$A$77,'PR Data'!$B:$B,"<>" & "Cheque") -> 0 | K111: =SUMIFS('PR Data'!$P:$P,'PR Data'!$Q:$Q,'PR Report - DOWNTOWN'!$A111,'PR Data'!$R:$R,"Approved",'PR Data'!$W:$W,K$78,'PR Data'!$U:$U,'PR Report - DOWNTOWN'!$A$77,'PR Data'!$B:$B,"<>" & "Cheque") -> 0 | L111: =SUMIFS('PR Data'!$P:$P,'PR Data'!$Q:$Q,'PR Report - DOWNTOWN'!$A111,'PR Data'!$R:$R,"Approved",'PR Data'!$W:$W,L$78,'PR Data'!$U:$U,'PR Report - DOWNTOWN'!$A$77,'PR Data'!$B:$B,"<>" & "Cheque") -> 0 | M111: =B111-SUM(C111:L111) -> 0
A112: Total Advances | B112: =SUM(B101:B111) -> 604342 | C112: =SUM(C101:C111) -> 0 | D112: =SUM(D101:D111) -> 0 | E112: =SUM(E101:E111) -> 0 | F112: =SUM(F101:F111) -> 0 | G112: =SUM(G101:G111) -> 0 | H112: =SUM(H101:H111) -> 0 | I112: =SUM(I101:I111) -> 150000 | ... M112: =SUM(M101:M111) -> 0
A113: Grand Total | B113: =SUM(B99,B112) -> 4622292.3 | C113: =SUM(C112,C99) -> 0 | D113: =SUM(D112,D99) -> 0 | E113: =SUM(E112,E99) -> 0 | F113: =SUM(F112,F99) -> 0 | G113: =SUM(G112,G99) -> 0 | H113: =SUM(H112,H99) -> 0 | I113: =SUM(I112,I99) -> 204215.9 | J113: =SUM(J112,J99) -> 0 | ... L113: =SUM(L112,L99) -> 178450 | M113: =SUM(M99,M112) -> 0

Sheet PR Report - SOBHA AUH
A1: Sobha AUH | B1: As per Tracker | H1: PR
A2: Collection Executive | B2: Daily Target 07/05 | C2: Collected 07-05-26 | D2: Target (01/05 - 07/05) | E2: Achieved (01/05 - 07/05) | F2: Monthly Target | G2: Total Achieved % | H2: PR Approved | I2: PR Not Approved
A3: Dues
A4: Monish | B4: 0 | C4: 0 | D4: 0 | E4: 0 | F4: 0 | G4: =IFERROR(E4/D4,0) -> 0 | H4: 0 | I4: =_xlfn.XLOOKUP(A4,$A$41:$A$58,$B$41:$B$58) -> 0
A5: Melvyn | B5: 0 | C5: 0 | D5: 0 | E5: 0 | F5: 0 | G5: =IFERROR(E5/D5,0) -> 0 | H5: 0 | I5: =_xlfn.XLOOKUP(A5,$A$41:$A$58,$B$41:$B$58) -> 0
A6: Anna | B6: 0 | C6: 0 | D6: 0 | E6: 0 | F6: 0 | G6: =IFERROR(E6/D6,0) -> 0 | H6: 0 | I6: =_xlfn.XLOOKUP(A6,$A$41:$A$58,$B$41:$B$58) -> 0
A7: Ruhul | B7: 0 | C7: 0 | D7: 0 | E7: 0 | F7: 0 | G7: =IFERROR(E7/D7,0) -> 0 | H7: 559683 | I7: =_xlfn.XLOOKUP(A7,$A$41:$A$58,$B$41:$B$58) -> 0
A8: Walid | B8: 0 | C8: 0 | D8: 0 | E8: 0 | F8: 0 | G8: =IFERROR(E8/D8,0) -> 0 | H8: 0 | I8: =_xlfn.XLOOKUP(A8,$A$41:$A$58,$B$41:$B$58) -> 0
A9: Ali | B9: 0 | C9: 0 | D9: 0 | E9: 0 | F9: 0 | G9: =IFERROR(E9/D9,0) -> 0 | H9: 0 | I9: =_xlfn.XLOOKUP(A9,$A$41:$A$58,$B$41:$B$58) -> 0
A10: Anirudh | B10: 0 | C10: 0 | D10: 0 | E10: 0 | F10: 0 | G10: =IFERROR(E10/D10,0) -> 0 | H10: 0 | I10: =_xlfn.XLOOKUP(A10,$A$41:$A$58,$B$41:$B$58) -> 0
A11: Aqsa | B11: 0 | C11: 0 | D11: 0 | E11: 0 | F11: 0 | G11: =IFERROR(E11/D11,0) -> 0 | H11: 0 | I11: =_xlfn.XLOOKUP(A11,$A$41:$A$58,$B$41:$B$58) -> 0
A12: Daria | B12: 0 | C12: 0 | D12: 0 | E12: 0 | F12: 0 | G12: =IFERROR(E12/D12,0) -> 0 | H12: 0 | I12: =_xlfn.XLOOKUP(A12,$A$41:$A$58,$B$41:$B$58) -> 0
A13: Hussein | B13: 0 | C13: 0 | D13: 0 | E13: 0 | F13: 0 | G13: =IFERROR(E13/D13,0) -> 0 | H13: 0 | I13: =_xlfn.XLOOKUP(A13,$A$41:$A$58,$B$41:$B$58) -> 0
A14: Karan | B14: 0 | C14: 0 | D14: 0 | E14: 0 | F14: 0 | G14: =IFERROR(E14/D14,0) -> 0 | H14: 0 | I14: =_xlfn.XLOOKUP(A14,$A$41:$A$58,$B$41:$B$58) -> 0
A15: Rajiv | B15: 0 | C15: 0 | D15: 0 | E15: 0 | F15: 0 | G15: =IFERROR(E15/D15,0) -> 0 | H15: 0 | I15: =_xlfn.XLOOKUP(A15,$A$41:$A$58,$B$41:$B$58) -> 0
... A21: Abdellatif | B21: 0 | C21: 0 | D21: 0 | E21: 0 | F21: 0 | G21: =IFERROR(E21/D21,0) -> 0 | H21: 0 | I21: =_xlfn.XLOOKUP(A21,$A$41:$A$58,$B$41:$B$58) -> 0
A22: Total Dues | B22: =SUM(B4:B21) -> 0 | C22: =SUM(C4:C21) -> 0 | D22: =SUM(D4:D21) -> 0 | E22: =SUM(E4:E21) -> 0 | F22: =SUM(F4:F21) -> 0 | G22: =IFERROR((E22)/(D22),0) -> 0 | H22: =SUM(H4:H21) -> 559683 | I22: =SUM(I4:I21) -> 0
A23: Advances
A24: Abdulla | B24: 0 | C24: 0 | D24: 0 | E24: 0 | F24: 0 | G24: =IFERROR(E24/D24,0) -> 0 | H24: 0 | I24: =_xlfn.XLOOKUP(A24,$A$61:$A$72,$B$61:$B$72) -> 0
A25: Krizia | B25: 0 | C25: 0 | D25: 0 | E25: 0 | F25: 0 | G25: =IFERROR(E25/D25,0) -> 0 | H25: 0 | I25: =_xlfn.XLOOKUP(A25,$A$61:$A$72,$B$61:$B$72) -> 0
A26: Ateev | B26: 0 | C26: 0 | D26: 0 | E26: 0 | F26: 0 | G26: =IFERROR(E26/D26,0) -> 0 | H26: 0 | I26: =_xlfn.XLOOKUP(A26,$A$61:$A$72,$B$61:$B$72) -> 0
A27: Ayari | B27: 0 | C27: 0 | D27: 0 | E27: 0 | F27: 0 | G27: =IFERROR(E27/D27,0) -> 0 | H27: 0 | I27: =_xlfn.XLOOKUP(A27,$A$61:$A$72,$B$61:$B$72) -> 0
A28: Nischitha | B28: 0 | C28: 0 | D28: 0 | E28: 0 | F28: 0 | G28: =IFERROR(E28/D28,0) -> 0 | H28: 0 | I28: =_xlfn.XLOOKUP(A28,$A$61:$A$72,$B$61:$B$72) -> 0
A29: Sherif | B29: 0 | C29: 30000 | D29: 0 | E29: 1253891 | F29: 0 | G29: =IFERROR(E29/D29,0) -> 0 | H29: 782197.82 | I29: =_xlfn.XLOOKUP(A29,$A$61:$A$72,$B$61:$B$72) -> 55000
A30: Wael | B30: 0 | C30: 0 | D30: 0 | E30: 0 | F30: 0 | G30: =IFERROR(E30/D30,0) -> 0 | H30: 0 | I30: =_xlfn.XLOOKUP(A30,$A$61:$A$72,$B$61:$B$72) -> 0
A31: Noha | B31: 0 | C31: 0 | D31: 0 | E31: 0 | F31: 0 | G31: =IFERROR(E31/D31,0) -> 0 | H31: 0 | I31: =_xlfn.XLOOKUP(A31,$A$61:$A$72,$B$61:$B$72) -> 0
A32: Vijay | B32: 0 | C32: 0 | D32: 0 | E32: 0 | F32: 0 | G32: =IFERROR(E32/D32,0) -> 0 | H32: 0 | I32: =_xlfn.XLOOKUP(A32,$A$61:$A$72,$B$61:$B$72) -> 0
A33: Basma | B33: 0 | C33: 0 | D33: 0 | E33: 0 | F33: 0 | G33: =IFERROR(E33/D33,0) -> 0 | H33: 0 | I33: =_xlfn.XLOOKUP(A33,$A$61:$A$72,$B$61:$B$72) -> 0
A34: Yogesh | B34: 0 | C34: 0 | D34: 0 | E34: 0 | F34: 0 | G34: =IFERROR(E34/D34,0) -> 0 | H34: 0 | I34: =_xlfn.XLOOKUP(A34,$A$61:$A$72,$B$61:$B$72) -> 0
A35: Total Advances | B35: =SUM(B24:B34) -> 0 | C35: =SUM(C24:C34) -> 30000 | D35: =SUM(D24:D34) -> 0 | E35: =SUM(E24:E34) -> 1253891 | F35: =SUM(F24:F34) -> 0 | G35: =IFERROR(E35/D35,0) -> 0 | H35: =SUM(H24:H34) -> 782197.82 | I35: =SUM(I24:I34) -> 55000
A36: Grand Total | B36: =SUM(B22,B35) -> 0 | C36: =SUM(C22,C35) -> 30000 | D36: =SUM(D22,D35) -> 0 | E36: =SUM(E22,E35) -> 1253891 | F36: =SUM(F22,F35) -> 0 | G36: =IFERROR(E36/D36,0) -> 0 | H36: =SUM(H22,H35) -> 1341880.8 | I36: =SUM(I22,I35) -> 55000
A38: Sobha AUH
A39: Collection Executive | B39: Not Approved | C39: In Process | D39: Resubmitted | E39: Rejected
A40: Dues
A41: Ali | B41: =SUM(C41:E41) -> 0 | C41: 0 | D41: 0 | E41: 0
A42: Anirudh | B42: =SUM(C42:E42) -> 0 | C42: 0 | D42: 0 | E42: 0
A43: Ruhul | B43: =SUM(C43:E43) -> 0 | C43: 0 | D43: 0 | E43: 0
A44: Karan | B44: =SUM(C44:E44) -> 0 | C44: 0 | D44: 0 | E44: 0
A45: Aqsa | B45: =SUM(C45:E45) -> 0 | C45: 0 | D45: 0 | E45: 0
A46: Sid | B46: =SUM(C46:E46) -> 0 | C46: 0 | D46: 0 | E46: 0
A47: Hussein | B47: =SUM(C47:E47) -> 0 | C47: 0 | D47: 0 | E47: 0
A48: Sabah | B48: =SUM(C48:E48) -> 0 | C48: 0 | D48: 0 | E48: 0
A49: Daria | B49: =SUM(C49:E49) -> 0 | C49: 0 | D49: 0 | E49: 0
A50: Rajiv | B50: =SUM(C50:E50) -> 0 | C50: 0 | D50: 0 | E50: 0
A51: Abdellatif | B51: =SUM(C51:E51) -> 0 | C51: 0 | D51: 0 | E51: 0
A52: Vinod | B52: =SUM(C52:E52) -> 0 | C52: 0 | D52: 0 | E52: 0
... A58: Anna | B58: =SUM(C58:E58) -> 0 | C58: 0 | D58: 0 | E58: 0
A59: Total Dues | B59: =SUM(B41:B58) -> 0 | C59: =SUM(C41:C58) -> 0 | D59: =SUM(D41:D58) -> 0 | E59: =SUM(E41:E58) -> 0
A60: Advances
A61: Ayari | B61: =SUM(C61:E61) -> 0 | C61: 0 | D61: 0 | E61: 0
A62: Krizia | B62: =SUM(C62:E62) -> 0 | C62: 0 | D62: 0 | E62: 0
A63: Ateev | B63: =SUM(C63:E63) -> 0 | C63: 0 | D63: 0 | E63: 0
A64: Abdulla | B64: =SUM(C64:E64) -> 0 | C64: 0 | D64: 0 | E64: 0
A65: Wael | B65: =SUM(C65:E65) -> 0 | C65: 0 | D65: 0 | E65: 0
A66: Nischitha | B66: =SUM(C66:E66) -> 0 | C66: 0 | D66: 0 | E66: 0
A67: Sherif | B67: =SUM(C67:E67) -> 55000 | C67: 0 | D67: 0 | E67: 55000
A68: Noha | B68: =SUM(C68:E68) -> 0 | C68: 0 | D68: 0 | E68: 0
A69: Vijay | B69: =SUM(C69:E69) -> 0 | C69: 0 | D69: 0 | E69: 0
A70: Basma | B70: =SUM(C70:E70) -> 0 | C70: 0 | D70: 0 | E70: 0
A71: Yogesh | B71: =SUM(C71:E71) -> 0 | C71: 0 | D71: 0 | E71: 0
A72: Anirudh | B72: =SUM(C72:E72) -> 0 | C72: 0 | D72: 0 | E72: 0
A73: Total Advances | B73: =SUM(B61:B72) -> 55000 | C73: =SUM(C61:C72) -> 0 | D73: =SUM(D61:D72) -> 0 | E73: =SUM(E61:E72) -> 55000
A74: Grand Total | B74: =SUM(B73,B59) -> 55000 | C74: =SUM(C73,C59) -> 0 | D74: =SUM(D73,D59) -> 0 | E74: =SUM(E73,E59) -> 55000
A77: Sobha AUH | C77: Cheque | I77: Other Mode of Payment
A78: Collection Executive | B78: PR Approved | C78: Cancelled | D78: Cleared | E78: PDC | F78: Processed-Sent for Banking | G78: Cheque Hold | H78: UnProcessed | I78: Unallocated | J78: Cancelled | K78: Cleared | L78: UnProcessed | M78: PDC Approved this Month / Amount to be allocated
A79: Dues
A80: Ali | B80: 0 | C80: 0 | D80: 0 | E80: 0 | F80: 0 | G80: 0 | H80: 0 | I80: =SUMIFS('PR Data'!$P:$P,'PR Data'!$Q:$Q,'PR Report - SOBHA AUH'!$A80,'PR Data'!$R:$R,"Approved",'PR Data'!$W:$W,I$78,'PR Data'!$U:$U,'PR Report - SOBHA AUH'!$A$77,'PR Data'!$B:$B,"<>" & "Cheque") -> 0 | J80: =SUMIFS('PR Data'!$P:$P,'PR Data'!$Q:$Q,'PR Report - SOBHA AUH'!$A80,'PR Data'!$R:$R,"Approved",'PR Data'!$W:$W,J$78,'PR Data'!$U:$U,'PR Report - SOBHA AUH'!$A$77,'PR Data'!$B:$B,"<>" & "Cheque") -> 0 | K80: =SUMIFS('PR Data'!$P:$P,'PR Data'!$Q:$Q,'PR Report - SOBHA AUH'!$A80,'PR Data'!$R:$R,"Approved",'PR Data'!$W:$W,K$78,'PR Data'!$U:$U,'PR Report - SOBHA AUH'!$A$77,'PR Data'!$B:$B,"<>" & "Cheque") -> 0 | L80: =SUMIFS('PR Data'!$P:$P,'PR Data'!$Q:$Q,'PR Report - SOBHA AUH'!$A80,'PR Data'!$R:$R,"Approved",'PR Data'!$W:$W,L$78,'PR Data'!$U:$U,'PR Report - SOBHA AUH'!$A$77,'PR Data'!$B:$B,"<>" & "Cheque") -> 0 | M80: =B80-SUM(C80:L80) -> 0
A81: Anirudh | B81: 0 | C81: 0 | D81: 0 | E81: 0 | F81: 0 | G81: 0 | H81: 0 | I81: =SUMIFS('PR Data'!$P:$P,'PR Data'!$Q:$Q,'PR Report - SOBHA AUH'!$A81,'PR Data'!$R:$R,"Approved",'PR Data'!$W:$W,I$78,'PR Data'!$U:$U,'PR Report - SOBHA AUH'!$A$77,'PR Data'!$B:$B,"<>" & "Cheque") -> 0 | J81: =SUMIFS('PR Data'!$P:$P,'PR Data'!$Q:$Q,'PR Report - SOBHA AUH'!$A81,'PR Data'!$R:$R,"Approved",'PR Data'!$W:$W,J$78,'PR Data'!$U:$U,'PR Report - SOBHA AUH'!$A$77,'PR Data'!$B:$B,"<>" & "Cheque") -> 0 | K81: =SUMIFS('PR Data'!$P:$P,'PR Data'!$Q:$Q,'PR Report - SOBHA AUH'!$A81,'PR Data'!$R:$R,"Approved",'PR Data'!$W:$W,K$78,'PR Data'!$U:$U,'PR Report - SOBHA AUH'!$A$77,'PR Data'!$B:$B,"<>" & "Cheque") -> 0 | L81: =SUMIFS('PR Data'!$P:$P,'PR Data'!$Q:$Q,'PR Report - SOBHA AUH'!$A81,'PR Data'!$R:$R,"Approved",'PR Data'!$W:$W,L$78,'PR Data'!$U:$U,'PR Report - SOBHA AUH'!$A$77,'PR Data'!$B:$B,"<>" & "Cheque") -> 0 | M81: =B81-SUM(C81:L81) -> 0
A82: Ruhul | B82: 559683 | C82: 0 | D82: 0 | E82: 0 | F82: 0 | G82: 0 | H82: 0 | I82: =SUMIFS('PR Data'!$P:$P,'PR Data'!$Q:$Q,'PR Report - SOBHA AUH'!$A82,'PR Data'!$R:$R,"Approved",'PR Data'!$W:$W,I$78,'PR Data'!$U:$U,'PR Report - SOBHA AUH'!$A$77,'PR Data'!$B:$B,"<>" & "Cheque") -> 0 | J82: =SUMIFS('PR Data'!$P:$P,'PR Data'!$Q:$Q,'PR Report - SOBHA AUH'!$A82,'PR Data'!$R:$R,"Approved",'PR Data'!$W:$W,J$78,'PR Data'!$U:$U,'PR Report - SOBHA AUH'!$A$77,'PR Data'!$B:$B,"<>" & "Cheque") -> 0 | K82: =SUMIFS('PR Data'!$P:$P,'PR Data'!$Q:$Q,'PR Report - SOBHA AUH'!$A82,'PR Data'!$R:$R,"Approved",'PR Data'!$W:$W,K$78,'PR Data'!$U:$U,'PR Report - SOBHA AUH'!$A$77,'PR Data'!$B:$B,"<>" & "Cheque") -> 0 | L82: =SUMIFS('PR Data'!$P:$P,'PR Data'!$Q:$Q,'PR Report - SOBHA AUH'!$A82,'PR Data'!$R:$R,"Approved",'PR Data'!$W:$W,L$78,'PR Data'!$U:$U,'PR Report - SOBHA AUH'!$A$77,'PR Data'!$B:$B,"<>" & "Cheque") -> 0 | M82: =B82-SUM(C82:L82) -> 559683
A83: Karan | B83: 0 | C83: 0 | D83: 0 | E83: 0 | F83: 0 | G83: 0 | H83: 0 | I83: =SUMIFS('PR Data'!$P:$P,'PR Data'!$Q:$Q,'PR Report - SOBHA AUH'!$A83,'PR Data'!$R:$R,"Approved",'PR Data'!$W:$W,I$78,'PR Data'!$U:$U,'PR Report - SOBHA AUH'!$A$77,'PR Data'!$B:$B,"<>" & "Cheque") -> 0 | J83: =SUMIFS('PR Data'!$P:$P,'PR Data'!$Q:$Q,'PR Report - SOBHA AUH'!$A83,'PR Data'!$R:$R,"Approved",'PR Data'!$W:$W,J$78,'PR Data'!$U:$U,'PR Report - SOBHA AUH'!$A$77,'PR Data'!$B:$B,"<>" & "Cheque") -> 0 | K83: =SUMIFS('PR Data'!$P:$P,'PR Data'!$Q:$Q,'PR Report - SOBHA AUH'!$A83,'PR Data'!$R:$R,"Approved",'PR Data'!$W:$W,K$78,'PR Data'!$U:$U,'PR Report - SOBHA AUH'!$A$77,'PR Data'!$B:$B,"<>" & "Cheque") -> 0 | L83: =SUMIFS('PR Data'!$P:$P,'PR Data'!$Q:$Q,'PR Report - SOBHA AUH'!$A83,'PR Data'!$R:$R,"Approved",'PR Data'!$W:$W,L$78,'PR Data'!$U:$U,'PR Report - SOBHA AUH'!$A$77,'PR Data'!$B:$B,"<>" & "Cheque") -> 0 | M83: =B83-SUM(C83:L83) -> 0
A84: Sid | B84: 0 | C84: 0 | D84: 0 | E84: 0 | F84: 0 | G84: 0 | H84: 0 | I84: =SUMIFS('PR Data'!$P:$P,'PR Data'!$Q:$Q,'PR Report - SOBHA AUH'!$A84,'PR Data'!$R:$R,"Approved",'PR Data'!$W:$W,I$78,'PR Data'!$U:$U,'PR Report - SOBHA AUH'!$A$77,'PR Data'!$B:$B,"<>" & "Cheque") -> 0 | J84: =SUMIFS('PR Data'!$P:$P,'PR Data'!$Q:$Q,'PR Report - SOBHA AUH'!$A84,'PR Data'!$R:$R,"Approved",'PR Data'!$W:$W,J$78,'PR Data'!$U:$U,'PR Report - SOBHA AUH'!$A$77,'PR Data'!$B:$B,"<>" & "Cheque") -> 0 | K84: =SUMIFS('PR Data'!$P:$P,'PR Data'!$Q:$Q,'PR Report - SOBHA AUH'!$A84,'PR Data'!$R:$R,"Approved",'PR Data'!$W:$W,K$78,'PR Data'!$U:$U,'PR Report - SOBHA AUH'!$A$77,'PR Data'!$B:$B,"<>" & "Cheque") -> 0 | L84: =SUMIFS('PR Data'!$P:$P,'PR Data'!$Q:$Q,'PR Report - SOBHA AUH'!$A84,'PR Data'!$R:$R,"Approved",'PR Data'!$W:$W,L$78,'PR Data'!$U:$U,'PR Report - SOBHA AUH'!$A$77,'PR Data'!$B:$B,"<>" & "Cheque") -> 0 | M84: =B84-SUM(C84:L84) -> 0
A85: Hussein | B85: 0 | C85: 0 | D85: 0 | E85: 0 | F85: 0 | G85: 0 | H85: 0 | I85: =SUMIFS('PR Data'!$P:$P,'PR Data'!$Q:$Q,'PR Report - SOBHA AUH'!$A85,'PR Data'!$R:$R,"Approved",'PR Data'!$W:$W,I$78,'PR Data'!$U:$U,'PR Report - SOBHA AUH'!$A$77,'PR Data'!$B:$B,"<>" & "Cheque") -> 0 | J85: =SUMIFS('PR Data'!$P:$P,'PR Data'!$Q:$Q,'PR Report - SOBHA AUH'!$A85,'PR Data'!$R:$R,"Approved",'PR Data'!$W:$W,J$78,'PR Data'!$U:$U,'PR Report - SOBHA AUH'!$A$77,'PR Data'!$B:$B,"<>" & "Cheque") -> 0 | K85: =SUMIFS('PR Data'!$P:$P,'PR Data'!$Q:$Q,'PR Report - SOBHA AUH'!$A85,'PR Data'!$R:$R,"Approved",'PR Data'!$W:$W,K$78,'PR Data'!$U:$U,'PR Report - SOBHA AUH'!$A$77,'PR Data'!$B:$B,"<>" & "Cheque") -> 0 | L85: =SUMIFS('PR Data'!$P:$P,'PR Data'!$Q:$Q,'PR Report - SOBHA AUH'!$A85,'PR Data'!$R:$R,"Approved",'PR Data'!$W:$W,L$78,'PR Data'!$U:$U,'PR Report - SOBHA AUH'!$A$77,'PR Data'!$B:$B,"<>" & "Cheque") -> 0 | M85: =B85-SUM(C85:L85) -> 0
A86: Sabah | B86: 0 | C86: 0 | D86: 0 | E86: 0 | F86: 0 | G86: 0 | H86: 0 | I86: =SUMIFS('PR Data'!$P:$P,'PR Data'!$Q:$Q,'PR Report - SOBHA AUH'!$A86,'PR Data'!$R:$R,"Approved",'PR Data'!$W:$W,I$78,'PR Data'!$U:$U,'PR Report - SOBHA AUH'!$A$77,'PR Data'!$B:$B,"<>" & "Cheque") -> 0 | J86: =SUMIFS('PR Data'!$P:$P,'PR Data'!$Q:$Q,'PR Report - SOBHA AUH'!$A86,'PR Data'!$R:$R,"Approved",'PR Data'!$W:$W,J$78,'PR Data'!$U:$U,'PR Report - SOBHA AUH'!$A$77,'PR Data'!$B:$B,"<>" & "Cheque") -> 0 | K86: =SUMIFS('PR Data'!$P:$P,'PR Data'!$Q:$Q,'PR Report - SOBHA AUH'!$A86,'PR Data'!$R:$R,"Approved",'PR Data'!$W:$W,K$78,'PR Data'!$U:$U,'PR Report - SOBHA AUH'!$A$77,'PR Data'!$B:$B,"<>" & "Cheque") -> 0 | L86: =SUMIFS('PR Data'!$P:$P,'PR Data'!$Q:$Q,'PR Report - SOBHA AUH'!$A86,'PR Data'!$R:$R,"Approved",'PR Data'!$W:$W,L$78,'PR Data'!$U:$U,'PR Report - SOBHA AUH'!$A$77,'PR Data'!$B:$B,"<>" & "Cheque") -> 0 | M86: =B86-SUM(C86:L86) -> 0
A87: Daria | B87: 0 | C87: 0 | D87: 0 | E87: 0 | F87: 0 | G87: 0 | H87: 0 | I87: =SUMIFS('PR Data'!$P:$P,'PR Data'!$Q:$Q,'PR Report - SOBHA AUH'!$A87,'PR Data'!$R:$R,"Approved",'PR Data'!$W:$W,I$78,'PR Data'!$U:$U,'PR Report - SOBHA AUH'!$A$77,'PR Data'!$B:$B,"<>" & "Cheque") -> 0 | J87: =SUMIFS('PR Data'!$P:$P,'PR Data'!$Q:$Q,'PR Report - SOBHA AUH'!$A87,'PR Data'!$R:$R,"Approved",'PR Data'!$W:$W,J$78,'PR Data'!$U:$U,'PR Report - SOBHA AUH'!$A$77,'PR Data'!$B:$B,"<>" & "Cheque") -> 0 | K87: =SUMIFS('PR Data'!$P:$P,'PR Data'!$Q:$Q,'PR Report - SOBHA AUH'!$A87,'PR Data'!$R:$R,"Approved",'PR Data'!$W:$W,K$78,'PR Data'!$U:$U,'PR Report - SOBHA AUH'!$A$77,'PR Data'!$B:$B,"<>" & "Cheque") -> 0 | L87: =SUMIFS('PR Data'!$P:$P,'PR Data'!$Q:$Q,'PR Report - SOBHA AUH'!$A87,'PR Data'!$R:$R,"Approved",'PR Data'!$W:$W,L$78,'PR Data'!$U:$U,'PR Report - SOBHA AUH'!$A$77,'PR Data'!$B:$B,"<>" & "Cheque") -> 0 | M87: =B87-SUM(C87:L87) -> 0
A88: Rajiv | B88: 0 | C88: 0 | D88: 0 | E88: 0 | F88: 0 | G88: 0 | H88: 0 | I88: =SUMIFS('PR Data'!$P:$P,'PR Data'!$Q:$Q,'PR Report - SOBHA AUH'!$A88,'PR Data'!$R:$R,"Approved",'PR Data'!$W:$W,I$78,'PR Data'!$U:$U,'PR Report - SOBHA AUH'!$A$77,'PR Data'!$B:$B,"<>" & "Cheque") -> 0 | J88: =SUMIFS('PR Data'!$P:$P,'PR Data'!$Q:$Q,'PR Report - SOBHA AUH'!$A88,'PR Data'!$R:$R,"Approved",'PR Data'!$W:$W,J$78,'PR Data'!$U:$U,'PR Report - SOBHA AUH'!$A$77,'PR Data'!$B:$B,"<>" & "Cheque") -> 0 | K88: =SUMIFS('PR Data'!$P:$P,'PR Data'!$Q:$Q,'PR Report - SOBHA AUH'!$A88,'PR Data'!$R:$R,"Approved",'PR Data'!$W:$W,K$78,'PR Data'!$U:$U,'PR Report - SOBHA AUH'!$A$77,'PR Data'!$B:$B,"<>" & "Cheque") -> 0 | L88: =SUMIFS('PR Data'!$P:$P,'PR Data'!$Q:$Q,'PR Report - SOBHA AUH'!$A88,'PR Data'!$R:$R,"Approved",'PR Data'!$W:$W,L$78,'PR Data'!$U:$U,'PR Report - SOBHA AUH'!$A$77,'PR Data'!$B:$B,"<>" & "Cheque") -> 0 | M88: =B88-SUM(C88:L88) -> 0
A89: Abdellatif | B89: 0 | C89: 0 | D89: 0 | E89: 0 | F89: 0 | G89: 0 | H89: 0 | I89: =SUMIFS('PR Data'!$P:$P,'PR Data'!$Q:$Q,'PR Report - SOBHA AUH'!$A89,'PR Data'!$R:$R,"Approved",'PR Data'!$W:$W,I$78,'PR Data'!$U:$U,'PR Report - SOBHA AUH'!$A$77,'PR Data'!$B:$B,"<>" & "Cheque") -> 0 | J89: =SUMIFS('PR Data'!$P:$P,'PR Data'!$Q:$Q,'PR Report - SOBHA AUH'!$A89,'PR Data'!$R:$R,"Approved",'PR Data'!$W:$W,J$78,'PR Data'!$U:$U,'PR Report - SOBHA AUH'!$A$77,'PR Data'!$B:$B,"<>" & "Cheque") -> 0 | K89: =SUMIFS('PR Data'!$P:$P,'PR Data'!$Q:$Q,'PR Report - SOBHA AUH'!$A89,'PR Data'!$R:$R,"Approved",'PR Data'!$W:$W,K$78,'PR Data'!$U:$U,'PR Report - SOBHA AUH'!$A$77,'PR Data'!$B:$B,"<>" & "Cheque") -> 0 | L89: =SUMIFS('PR Data'!$P:$P,'PR Data'!$Q:$Q,'PR Report - SOBHA AUH'!$A89,'PR Data'!$R:$R,"Approved",'PR Data'!$W:$W,L$78,'PR Data'!$U:$U,'PR Report - SOBHA AUH'!$A$77,'PR Data'!$B:$B,"<>" & "Cheque") -> 0 | M89: =B89-SUM(C89:L89) -> 0
A90: Aqsa | B90: 0 | C90: 0 | D90: 0 | E90: 0 | F90: 0 | G90: 0 | H90: 0 | I90: =SUMIFS('PR Data'!$P:$P,'PR Data'!$Q:$Q,'PR Report - SOBHA AUH'!$A90,'PR Data'!$R:$R,"Approved",'PR Data'!$W:$W,I$78,'PR Data'!$U:$U,'PR Report - SOBHA AUH'!$A$77,'PR Data'!$B:$B,"<>" & "Cheque") -> 0 | J90: =SUMIFS('PR Data'!$P:$P,'PR Data'!$Q:$Q,'PR Report - SOBHA AUH'!$A90,'PR Data'!$R:$R,"Approved",'PR Data'!$W:$W,J$78,'PR Data'!$U:$U,'PR Report - SOBHA AUH'!$A$77,'PR Data'!$B:$B,"<>" & "Cheque") -> 0 | K90: =SUMIFS('PR Data'!$P:$P,'PR Data'!$Q:$Q,'PR Report - SOBHA AUH'!$A90,'PR Data'!$R:$R,"Approved",'PR Data'!$W:$W,K$78,'PR Data'!$U:$U,'PR Report - SOBHA AUH'!$A$77,'PR Data'!$B:$B,"<>" & "Cheque") -> 0 | L90: =SUMIFS('PR Data'!$P:$P,'PR Data'!$Q:$Q,'PR Report - SOBHA AUH'!$A90,'PR Data'!$R:$R,"Approved",'PR Data'!$W:$W,L$78,'PR Data'!$U:$U,'PR Report - SOBHA AUH'!$A$77,'PR Data'!$B:$B,"<>" & "Cheque") -> 0 | M90: =B90-SUM(C90:L90) -> 0
A91: Vinod | B91: 0 | C91: 0 | D91: 0 | E91: 0 | F91: 0 | G91: 0 | H91: 0 | I91: =SUMIFS('PR Data'!$P:$P,'PR Data'!$Q:$Q,'PR Report - SOBHA AUH'!$A91,'PR Data'!$R:$R,"Approved",'PR Data'!$W:$W,I$78,'PR Data'!$U:$U,'PR Report - SOBHA AUH'!$A$77,'PR Data'!$B:$B,"<>" & "Cheque") -> 0 | J91: =SUMIFS('PR Data'!$P:$P,'PR Data'!$Q:$Q,'PR Report - SOBHA AUH'!$A91,'PR Data'!$R:$R,"Approved",'PR Data'!$W:$W,J$78,'PR Data'!$U:$U,'PR Report - SOBHA AUH'!$A$77,'PR Data'!$B:$B,"<>" & "Cheque") -> 0 | K91: =SUMIFS('PR Data'!$P:$P,'PR Data'!$Q:$Q,'PR Report - SOBHA AUH'!$A91,'PR Data'!$R:$R,"Approved",'PR Data'!$W:$W,K$78,'PR Data'!$U:$U,'PR Report - SOBHA AUH'!$A$77,'PR Data'!$B:$B,"<>" & "Cheque") -> 0 | L91: =SUMIFS('PR Data'!$P:$P,'PR Data'!$Q:$Q,'PR Report - SOBHA AUH'!$A91,'PR Data'!$R:$R,"Approved",'PR Data'!$W:$W,L$78,'PR Data'!$U:$U,'PR Report - SOBHA AUH'!$A$77,'PR Data'!$B:$B,"<>" & "Cheque") -> 0 | M91: =B91-SUM(C91:L91) -> 0
... A98: Anna | B98: 0 | C98: 0 | D98: 0 | E98: 0 | F98: 0 | G98: 0 | H98: 0 | I98: =SUMIFS('PR Data'!$P:$P,'PR Data'!$Q:$Q,'PR Report - SOBHA AUH'!$A98,'PR Data'!$R:$R,"Approved",'PR Data'!$W:$W,I$78,'PR Data'!$U:$U,'PR Report - SOBHA AUH'!$A$77,'PR Data'!$B:$B,"<>" & "Cheque") -> 0 | J98: =SUMIFS('PR Data'!$P:$P,'PR Data'!$Q:$Q,'PR Report - SOBHA AUH'!$A98,'PR Data'!$R:$R,"Approved",'PR Data'!$W:$W,J$78,'PR Data'!$U:$U,'PR Report - SOBHA AUH'!$A$77,'PR Data'!$B:$B,"<>" & "Cheque") -> 0 | K98: =SUMIFS('PR Data'!$P:$P,'PR Data'!$Q:$Q,'PR Report - SOBHA AUH'!$A98,'PR Data'!$R:$R,"Approved",'PR Data'!$W:$W,K$78,'PR Data'!$U:$U,'PR Report - SOBHA AUH'!$A$77,'PR Data'!$B:$B,"<>" & "Cheque") -> 0 | L98: =SUMIFS('PR Data'!$P:$P,'PR Data'!$Q:$Q,'PR Report - SOBHA AUH'!$A98,'PR Data'!$R:$R,"Approved",'PR Data'!$W:$W,L$78,'PR Data'!$U:$U,'PR Report - SOBHA AUH'!$A$77,'PR Data'!$B:$B,"<>" & "Cheque") -> 0 | M98: =B98-SUM(C98:L98) -> 0
A99: Total Dues | B99: =SUM(B80:B97) -> 559683 | C99: =SUM(C80:C97) -> 0 | D99: =SUM(D80:D97) -> 0 | E99: =SUM(E80:E97) -> 0 | F99: =SUM(F80:F97) -> 0 | G99: =SUM(G80:G97) -> 0 | H99: =SUM(H80:H97) -> 0 | I99: =SUM(I80:I97) -> 0 | ... M99: =SUM(M80:M97) -> 559683
A100: Advances
A101: Ayari | B101: 0 | C101: 0 | D101: 0 | E101: 0 | F101: 0 | G101: 0 | H101: 0 | I101: =SUMIFS('PR Data'!$P:$P,'PR Data'!$Q:$Q,'PR Report - SOBHA AUH'!$A101,'PR Data'!$R:$R,"Approved",'PR Data'!$W:$W,I$78,'PR Data'!$U:$U,'PR Report - SOBHA AUH'!$A$77,'PR Data'!$B:$B,"<>" & "Cheque") -> 0 | J101: =SUMIFS('PR Data'!$P:$P,'PR Data'!$Q:$Q,'PR Report - SOBHA AUH'!$A101,'PR Data'!$R:$R,"Approved",'PR Data'!$W:$W,J$78,'PR Data'!$U:$U,'PR Report - SOBHA AUH'!$A$77,'PR Data'!$B:$B,"<>" & "Cheque") -> 0 | K101: =SUMIFS('PR Data'!$P:$P,'PR Data'!$Q:$Q,'PR Report - SOBHA AUH'!$A101,'PR Data'!$R:$R,"Approved",'PR Data'!$W:$W,K$78,'PR Data'!$U:$U,'PR Report - SOBHA AUH'!$A$77,'PR Data'!$B:$B,"<>" & "Cheque") -> 0 | L101: =SUMIFS('PR Data'!$P:$P,'PR Data'!$Q:$Q,'PR Report - SOBHA AUH'!$A101,'PR Data'!$R:$R,"Approved",'PR Data'!$W:$W,L$78,'PR Data'!$U:$U,'PR Report - SOBHA AUH'!$A$77,'PR Data'!$B:$B,"<>" & "Cheque") -> 0 | M101: =B101-SUM(C101:L101) -> 0
A102: Krizia | B102: 0 | C102: 0 | D102: 0 | E102: 0 | F102: 0 | G102: 0 | H102: 0 | I102: =SUMIFS('PR Data'!$P:$P,'PR Data'!$Q:$Q,'PR Report - SOBHA AUH'!$A102,'PR Data'!$R:$R,"Approved",'PR Data'!$W:$W,I$78,'PR Data'!$U:$U,'PR Report - SOBHA AUH'!$A$77,'PR Data'!$B:$B,"<>" & "Cheque") -> 0 | J102: =SUMIFS('PR Data'!$P:$P,'PR Data'!$Q:$Q,'PR Report - SOBHA AUH'!$A102,'PR Data'!$R:$R,"Approved",'PR Data'!$W:$W,J$78,'PR Data'!$U:$U,'PR Report - SOBHA AUH'!$A$77,'PR Data'!$B:$B,"<>" & "Cheque") -> 0 | K102: =SUMIFS('PR Data'!$P:$P,'PR Data'!$Q:$Q,'PR Report - SOBHA AUH'!$A102,'PR Data'!$R:$R,"Approved",'PR Data'!$W:$W,K$78,'PR Data'!$U:$U,'PR Report - SOBHA AUH'!$A$77,'PR Data'!$B:$B,"<>" & "Cheque") -> 0 | L102: =SUMIFS('PR Data'!$P:$P,'PR Data'!$Q:$Q,'PR Report - SOBHA AUH'!$A102,'PR Data'!$R:$R,"Approved",'PR Data'!$W:$W,L$78,'PR Data'!$U:$U,'PR Report - SOBHA AUH'!$A$77,'PR Data'!$B:$B,"<>" & "Cheque") -> 0 | M102: =B102-SUM(C102:L102) -> 0
A103: Abdulla | B103: 0 | C103: 0 | D103: 0 | E103: 0 | F103: 0 | G103: 0 | H103: 0 | I103: =SUMIFS('PR Data'!$P:$P,'PR Data'!$Q:$Q,'PR Report - SOBHA AUH'!$A103,'PR Data'!$R:$R,"Approved",'PR Data'!$W:$W,I$78,'PR Data'!$U:$U,'PR Report - SOBHA AUH'!$A$77,'PR Data'!$B:$B,"<>" & "Cheque") -> 0 | J103: =SUMIFS('PR Data'!$P:$P,'PR Data'!$Q:$Q,'PR Report - SOBHA AUH'!$A103,'PR Data'!$R:$R,"Approved",'PR Data'!$W:$W,J$78,'PR Data'!$U:$U,'PR Report - SOBHA AUH'!$A$77,'PR Data'!$B:$B,"<>" & "Cheque") -> 0 | K103: =SUMIFS('PR Data'!$P:$P,'PR Data'!$Q:$Q,'PR Report - SOBHA AUH'!$A103,'PR Data'!$R:$R,"Approved",'PR Data'!$W:$W,K$78,'PR Data'!$U:$U,'PR Report - SOBHA AUH'!$A$77,'PR Data'!$B:$B,"<>" & "Cheque") -> 0 | L103: =SUMIFS('PR Data'!$P:$P,'PR Data'!$Q:$Q,'PR Report - SOBHA AUH'!$A103,'PR Data'!$R:$R,"Approved",'PR Data'!$W:$W,L$78,'PR Data'!$U:$U,'PR Report - SOBHA AUH'!$A$77,'PR Data'!$B:$B,"<>" & "Cheque") -> 0 | M103: =B103-SUM(C103:L103) -> 0
A104: Ateev | B104: 0 | C104: 0 | D104: 0 | E104: 0 | F104: 0 | G104: 0 | H104: 0 | I104: =SUMIFS('PR Data'!$P:$P,'PR Data'!$Q:$Q,'PR Report - SOBHA AUH'!$A104,'PR Data'!$R:$R,"Approved",'PR Data'!$W:$W,I$78,'PR Data'!$U:$U,'PR Report - SOBHA AUH'!$A$77,'PR Data'!$B:$B,"<>" & "Cheque") -> 0 | J104: =SUMIFS('PR Data'!$P:$P,'PR Data'!$Q:$Q,'PR Report - SOBHA AUH'!$A104,'PR Data'!$R:$R,"Approved",'PR Data'!$W:$W,J$78,'PR Data'!$U:$U,'PR Report - SOBHA AUH'!$A$77,'PR Data'!$B:$B,"<>" & "Cheque") -> 0 | K104: =SUMIFS('PR Data'!$P:$P,'PR Data'!$Q:$Q,'PR Report - SOBHA AUH'!$A104,'PR Data'!$R:$R,"Approved",'PR Data'!$W:$W,K$78,'PR Data'!$U:$U,'PR Report - SOBHA AUH'!$A$77,'PR Data'!$B:$B,"<>" & "Cheque") -> 0 | L104: =SUMIFS('PR Data'!$P:$P,'PR Data'!$Q:$Q,'PR Report - SOBHA AUH'!$A104,'PR Data'!$R:$R,"Approved",'PR Data'!$W:$W,L$78,'PR Data'!$U:$U,'PR Report - SOBHA AUH'!$A$77,'PR Data'!$B:$B,"<>" & "Cheque") -> 0 | M104: =B104-SUM(C104:L104) -> 0
A105: Wael | B105: 0 | C105: 0 | D105: 0 | E105: 0 | F105: 0 | G105: 0 | H105: 0 | I105: =SUMIFS('PR Data'!$P:$P,'PR Data'!$Q:$Q,'PR Report - SOBHA AUH'!$A105,'PR Data'!$R:$R,"Approved",'PR Data'!$W:$W,I$78,'PR Data'!$U:$U,'PR Report - SOBHA AUH'!$A$77,'PR Data'!$B:$B,"<>" & "Cheque") -> 0 | J105: =SUMIFS('PR Data'!$P:$P,'PR Data'!$Q:$Q,'PR Report - SOBHA AUH'!$A105,'PR Data'!$R:$R,"Approved",'PR Data'!$W:$W,J$78,'PR Data'!$U:$U,'PR Report - SOBHA AUH'!$A$77,'PR Data'!$B:$B,"<>" & "Cheque") -> 0 | K105: =SUMIFS('PR Data'!$P:$P,'PR Data'!$Q:$Q,'PR Report - SOBHA AUH'!$A105,'PR Data'!$R:$R,"Approved",'PR Data'!$W:$W,K$78,'PR Data'!$U:$U,'PR Report - SOBHA AUH'!$A$77,'PR Data'!$B:$B,"<>" & "Cheque") -> 0 | L105: =SUMIFS('PR Data'!$P:$P,'PR Data'!$Q:$Q,'PR Report - SOBHA AUH'!$A105,'PR Data'!$R:$R,"Approved",'PR Data'!$W:$W,L$78,'PR Data'!$U:$U,'PR Report - SOBHA AUH'!$A$77,'PR Data'!$B:$B,"<>" & "Cheque") -> 0 | M105: =B105-SUM(C105:L105) -> 0
A106: Sherif | B106: 782197.82 | C106: 0 | D106: 226839.82 | E106: 0 | F106: 0 | G106: 0 | H106: 0 | I106: =SUMIFS('PR Data'!$P:$P,'PR Data'!$Q:$Q,'PR Report - SOBHA AUH'!$A106,'PR Data'!$R:$R,"Approved",'PR Data'!$W:$W,I$78,'PR Data'!$U:$U,'PR Report - SOBHA AUH'!$A$77,'PR Data'!$B:$B,"<>" & "Cheque") -> 0 | J106: =SUMIFS('PR Data'!$P:$P,'PR Data'!$Q:$Q,'PR Report - SOBHA AUH'!$A106,'PR Data'!$R:$R,"Approved",'PR Data'!$W:$W,J$78,'PR Data'!$U:$U,'PR Report - SOBHA AUH'!$A$77,'PR Data'!$B:$B,"<>" & "Cheque") -> 0 | K106: =SUMIFS('PR Data'!$P:$P,'PR Data'!$Q:$Q,'PR Report - SOBHA AUH'!$A106,'PR Data'!$R:$R,"Approved",'PR Data'!$W:$W,K$78,'PR Data'!$U:$U,'PR Report - SOBHA AUH'!$A$77,'PR Data'!$B:$B,"<>" & "Cheque") -> 555358 | L106: =SUMIFS('PR Data'!$P:$P,'PR Data'!$Q:$Q,'PR Report - SOBHA AUH'!$A106,'PR Data'!$R:$R,"Approved",'PR Data'!$W:$W,L$78,'PR Data'!$U:$U,'PR Report - SOBHA AUH'!$A$77,'PR Data'!$B:$B,"<>" & "Cheque") -> 0 | M106: =B106-SUM(C106:L106) -> 0
A107: Nischitha | B107: 0 | C107: 0 | D107: 0 | E107: 0 | F107: 0 | G107: 0 | H107: 0 | I107: =SUMIFS('PR Data'!$P:$P,'PR Data'!$Q:$Q,'PR Report - SOBHA AUH'!$A107,'PR Data'!$R:$R,"Approved",'PR Data'!$W:$W,I$78,'PR Data'!$U:$U,'PR Report - SOBHA AUH'!$A$77,'PR Data'!$B:$B,"<>" & "Cheque") -> 0 | J107: =SUMIFS('PR Data'!$P:$P,'PR Data'!$Q:$Q,'PR Report - SOBHA AUH'!$A107,'PR Data'!$R:$R,"Approved",'PR Data'!$W:$W,J$78,'PR Data'!$U:$U,'PR Report - SOBHA AUH'!$A$77,'PR Data'!$B:$B,"<>" & "Cheque") -> 0 | K107: =SUMIFS('PR Data'!$P:$P,'PR Data'!$Q:$Q,'PR Report - SOBHA AUH'!$A107,'PR Data'!$R:$R,"Approved",'PR Data'!$W:$W,K$78,'PR Data'!$U:$U,'PR Report - SOBHA AUH'!$A$77,'PR Data'!$B:$B,"<>" & "Cheque") -> 0 | L107: =SUMIFS('PR Data'!$P:$P,'PR Data'!$Q:$Q,'PR Report - SOBHA AUH'!$A107,'PR Data'!$R:$R,"Approved",'PR Data'!$W:$W,L$78,'PR Data'!$U:$U,'PR Report - SOBHA AUH'!$A$77,'PR Data'!$B:$B,"<>" & "Cheque") -> 0 | M107: =B107-SUM(C107:L107) -> 0
A108: Noha | B108: 0 | C108: 0 | D108: 0 | E108: 0 | F108: 0 | G108: 0 | H108: 0 | I108: =SUMIFS('PR Data'!$P:$P,'PR Data'!$Q:$Q,'PR Report - SOBHA AUH'!$A108,'PR Data'!$R:$R,"Approved",'PR Data'!$W:$W,I$78,'PR Data'!$U:$U,'PR Report - SOBHA AUH'!$A$77,'PR Data'!$B:$B,"<>" & "Cheque") -> 0 | J108: =SUMIFS('PR Data'!$P:$P,'PR Data'!$Q:$Q,'PR Report - SOBHA AUH'!$A108,'PR Data'!$R:$R,"Approved",'PR Data'!$W:$W,J$78,'PR Data'!$U:$U,'PR Report - SOBHA AUH'!$A$77,'PR Data'!$B:$B,"<>" & "Cheque") -> 0 | K108: =SUMIFS('PR Data'!$P:$P,'PR Data'!$Q:$Q,'PR Report - SOBHA AUH'!$A108,'PR Data'!$R:$R,"Approved",'PR Data'!$W:$W,K$78,'PR Data'!$U:$U,'PR Report - SOBHA AUH'!$A$77,'PR Data'!$B:$B,"<>" & "Cheque") -> 0 | L108: =SUMIFS('PR Data'!$P:$P,'PR Data'!$Q:$Q,'PR Report - SOBHA AUH'!$A108,'PR Data'!$R:$R,"Approved",'PR Data'!$W:$W,L$78,'PR Data'!$U:$U,'PR Report - SOBHA AUH'!$A$77,'PR Data'!$B:$B,"<>" & "Cheque") -> 0 | M108: =B108-SUM(C108:L108) -> 0
A109: Vijay | B109: 0 | C109: 0 | D109: 0 | E109: 0 | F109: 0 | G109: 0 | H109: 0 | I109: =SUMIFS('PR Data'!$P:$P,'PR Data'!$Q:$Q,'PR Report - SOBHA AUH'!$A109,'PR Data'!$R:$R,"Approved",'PR Data'!$W:$W,I$78,'PR Data'!$U:$U,'PR Report - SOBHA AUH'!$A$77,'PR Data'!$B:$B,"<>" & "Cheque") -> 0 | J109: =SUMIFS('PR Data'!$P:$P,'PR Data'!$Q:$Q,'PR Report - SOBHA AUH'!$A109,'PR Data'!$R:$R,"Approved",'PR Data'!$W:$W,J$78,'PR Data'!$U:$U,'PR Report - SOBHA AUH'!$A$77,'PR Data'!$B:$B,"<>" & "Cheque") -> 0 | K109: =SUMIFS('PR Data'!$P:$P,'PR Data'!$Q:$Q,'PR Report - SOBHA AUH'!$A109,'PR Data'!$R:$R,"Approved",'PR Data'!$W:$W,K$78,'PR Data'!$U:$U,'PR Report - SOBHA AUH'!$A$77,'PR Data'!$B:$B,"<>" & "Cheque") -> 0 | L109: =SUMIFS('PR Data'!$P:$P,'PR Data'!$Q:$Q,'PR Report - SOBHA AUH'!$A109,'PR Data'!$R:$R,"Approved",'PR Data'!$W:$W,L$78,'PR Data'!$U:$U,'PR Report - SOBHA AUH'!$A$77,'PR Data'!$B:$B,"<>" & "Cheque") -> 0 | M109: =B109-SUM(C109:L109) -> 0
A110: Basma | B110: 0 | C110: 0 | D110: 0 | E110: 0 | F110: 0 | G110: 0 | H110: 0 | I110: =SUMIFS('PR Data'!$P:$P,'PR Data'!$Q:$Q,'PR Report - SOBHA AUH'!$A110,'PR Data'!$R:$R,"Approved",'PR Data'!$W:$W,I$78,'PR Data'!$U:$U,'PR Report - SOBHA AUH'!$A$77,'PR Data'!$B:$B,"<>" & "Cheque") -> 0 | J110: =SUMIFS('PR Data'!$P:$P,'PR Data'!$Q:$Q,'PR Report - SOBHA AUH'!$A110,'PR Data'!$R:$R,"Approved",'PR Data'!$W:$W,J$78,'PR Data'!$U:$U,'PR Report - SOBHA AUH'!$A$77,'PR Data'!$B:$B,"<>" & "Cheque") -> 0 | K110: =SUMIFS('PR Data'!$P:$P,'PR Data'!$Q:$Q,'PR Report - SOBHA AUH'!$A110,'PR Data'!$R:$R,"Approved",'PR Data'!$W:$W,K$78,'PR Data'!$U:$U,'PR Report - SOBHA AUH'!$A$77,'PR Data'!$B:$B,"<>" & "Cheque") -> 0 | L110: =SUMIFS('PR Data'!$P:$P,'PR Data'!$Q:$Q,'PR Report - SOBHA AUH'!$A110,'PR Data'!$R:$R,"Approved",'PR Data'!$W:$W,L$78,'PR Data'!$U:$U,'PR Report - SOBHA AUH'!$A$77,'PR Data'!$B:$B,"<>" & "Cheque") -> 0 | M110: =B110-SUM(C110:L110) -> 0
A111: Yogesh | B111: 0 | C111: 0 | D111: 0 | E111: 0 | F111: 0 | G111: 0 | H111: 0 | I111: =SUMIFS('PR Data'!$P:$P,'PR Data'!$Q:$Q,'PR Report - SOBHA AUH'!$A111,'PR Data'!$R:$R,"Approved",'PR Data'!$W:$W,I$78,'PR Data'!$U:$U,'PR Report - SOBHA AUH'!$A$77,'PR Data'!$B:$B,"<>" & "Cheque") -> 0 | J111: =SUMIFS('PR Data'!$P:$P,'PR Data'!$Q:$Q,'PR Report - SOBHA AUH'!$A111,'PR Data'!$R:$R,"Approved",'PR Data'!$W:$W,J$78,'PR Data'!$U:$U,'PR Report - SOBHA AUH'!$A$77,'PR Data'!$B:$B,"<>" & "Cheque") -> 0 | K111: =SUMIFS('PR Data'!$P:$P,'PR Data'!$Q:$Q,'PR Report - SOBHA AUH'!$A111,'PR Data'!$R:$R,"Approved",'PR Data'!$W:$W,K$78,'PR Data'!$U:$U,'PR Report - SOBHA AUH'!$A$77,'PR Data'!$B:$B,"<>" & "Cheque") -> 0 | L111: =SUMIFS('PR Data'!$P:$P,'PR Data'!$Q:$Q,'PR Report - SOBHA AUH'!$A111,'PR Data'!$R:$R,"Approved",'PR Data'!$W:$W,L$78,'PR Data'!$U:$U,'PR Report - SOBHA AUH'!$A$77,'PR Data'!$B:$B,"<>" & "Cheque") -> 0 | M111: =B111-SUM(C111:L111) -> 0
A112: Total Advances | B112: =SUM(B101:B111) -> 782197.82 | C112: =SUM(C101:C111) -> 0 | D112: =SUM(D101:D111) -> 226839.82 | E112: =SUM(E101:E111) -> 0 | F112: =SUM(F101:F111) -> 0 | G112: =SUM(G101:G111) -> 0 | H112: =SUM(H101:H111) -> 0 | I112: =SUM(I101:I111) -> 0 | ... M112: =SUM(M101:M111) -> 0
A113: Grand Total | B113: =SUM(B99,B112) -> 1341880.8 | C113: =SUM(C112,C99) -> 0 | D113: =SUM(D112,D99) -> 226839.82 | E113: =SUM(E112,E99) -> 0 | F113: =SUM(F112,F99) -> 0 | G113: =SUM(G112,G99) -> 0 | H113: =SUM(H112,H99) -> 0 | I113: =SUM(I112,I99) -> 0 | J113: =SUM(J112,J99) -> 0 | ... L113: =SUM(L112,L99) -> 0 | M113: =SUM(M99,M112) -> 559683

Sheet PR Report - Total
A2: TOTAL | B2: As per Tracker | H2: PR
A3: Collection Executive | B3: Daily Target 07/05 | C3: Collected 07-05-26 | D3: ='PR Report - SOBHA '!D3 -> Target (01/05 - 07/05) | E3: ='PR Report - SOBHA '!E3 -> Achieved (01/05 - 07/05) | F3: Monthly Target | G3: Total Achieved % | H3: PR Approved | I3: PR Not Approved
A4: Dues
A5: Monish | B5: =SUMIFS('PR Report - SINIYA'!$B$5:$B$21,'PR Report - SINIYA'!$A$5:$A$21,A5)+SUMIFS('PR Report - DOWNTOWN'!$B$5:$B$22,'PR Report - DOWNTOWN'!$A$5:$A$22,A5) -> 3823529.4 | C5: =SUMIFS('PR Report - SINIYA'!$C$5:$C$21,'PR Report - SINIYA'!$A$5:$A$21,$A5)+SUMIFS('PR Report - DOWNTOWN'!$C$5:$C$22,'PR Report - DOWNTOWN'!$A$5:$A$22,A5) -> 2460211.9 | D5: =SUMIFS('PR Report - SINIYA'!$D$5:$D$21,'PR Report - SINIYA'!$A$5:$A$21,$A5)+SUMIFS('PR Report - DOWNTOWN'!$D$5:$D$22,'PR Report - DOWNTOWN'!$A$5:$A$22,$A5) -> 19117647 | E5: =SUMIFS('PR Report - SINIYA'!$E$5:$E$21,'PR Report - SINIYA'!$A$5:$A$21,$A5)+SUMIFS('PR Report - SOBHA '!$E$5:$E$26,'PR Report - SOBHA '!$A$5:$A$26,$A5)+SUMIFS('PR Report - DOWNTOWN'!$E$5:$E$22,'PR Report - DOWNTOWN'!$A$5:$A$22,A5) -> 12919024 | F5: =SUMIFS('PR Report - SINIYA'!$F$5:$F$21,'PR Report - SINIYA'!$A$5:$A$21,$A5)+SUMIFS('PR Report - SOBHA '!$F$5:$F$26,'PR Report - SOBHA '!$A$5:$A$26,$A5)+SUMIFS('PR Report - DOWNTOWN'!$F$5:$F$22,'PR Report - DOWNTOWN'!$A$5:$A$22,A5) -> 65000000 | G5: =IFERROR(E5/D5,0) -> 0.67576435 | H5: =SUMIFS('PR Report - SINIYA'!$H$5:$H$21,'PR Report - SINIYA'!$A$5:$A$21,$A5)+SUMIFS('PR Report - SOBHA '!$H$5:$H$26,'PR Report - SOBHA '!$A$5:$A$26,$A5)+SUMIFS('PR Report - DOWNTOWN'!$H$5:$H$22,'PR Report - DOWNTOWN'!$A$5:$A$22,A5) -> 6517845.8 | I5: =SUMIFS('PR Report - SINIYA'!$I$5:$I$21,'PR Report - SINIYA'!$A$5:$A$21,$A5)+SUMIFS('PR Report - SOBHA '!$I$5:$I$26,'PR Report - SOBHA '!$A$5:$A$26,$A5)+SUMIFS('PR Report - DOWNTOWN'!$I$5:$I$22,'PR Report - DOWNTOWN'!$A$5:$A$22,A5) -> 5676444.3
A6: Walid | B6: =SUMIFS('PR Report - SINIYA'!$B$5:$B$21,'PR Report - SINIYA'!$A$5:$A$21,A6)+SUMIFS('PR Report - DOWNTOWN'!$B$5:$B$22,'PR Report - DOWNTOWN'!$A$5:$A$22,A6) -> 3823529.4 | C6: =SUMIFS('PR Report - SINIYA'!$C$5:$C$21,'PR Report - SINIYA'!$A$5:$A$21,$A6)+SUMIFS('PR Report - DOWNTOWN'!$C$5:$C$22,'PR Report - DOWNTOWN'!$A$5:$A$22,A6) -> 2000406.8 | D6: =SUMIFS('PR Report - SINIYA'!$D$5:$D$21,'PR Report - SINIYA'!$A$5:$A$21,$A6)+SUMIFS('PR Report - DOWNTOWN'!$D$5:$D$22,'PR Report - DOWNTOWN'!$A$5:$A$22,$A6) -> 19117647 | E6: =SUMIFS('PR Report - SINIYA'!$E$5:$E$21,'PR Report - SINIYA'!$A$5:$A$21,$A6)+SUMIFS('PR Report - DOWNTOWN'!$E$5:$E$22,'PR Report - DOWNTOWN'!$A$5:$A$22,A6) -> 16291161 | F6: =SUMIFS('PR Report - SINIYA'!$F$5:$F$21,'PR Report - SINIYA'!$A$5:$A$21,$A6)+SUMIFS('PR Report - DOWNTOWN'!$F$5:$F$22,'PR Report - DOWNTOWN'!$A$5:$A$22,A6) -> 65000000 | G6: =IFERROR(E6/D6,0) -> 0.85215301 | H6: =SUMIFS('PR Report - SINIYA'!$H$5:$H$21,'PR Report - SINIYA'!$A$5:$A$21,$A6)+SUMIFS('PR Report - DOWNTOWN'!$H$5:$H$22,'PR Report - DOWNTOWN'!$A$5:$A$22,A6) -> 10533785 | I6: =SUMIFS('PR Report - SINIYA'!$I$5:$I$21,'PR Report - SINIYA'!$A$5:$A$21,$A6)+SUMIFS('PR Report - DOWNTOWN'!$I$5:$I$22,'PR Report - DOWNTOWN'!$A$5:$A$22,A6) -> 8114728.6
A7: Melvyn | B7: =SUMIFS('PR Report - SINIYA'!$B$5:$B$21,'PR Report - SINIYA'!$A$5:$A$21,A7)+SUMIFS('PR Report - DOWNTOWN'!$B$5:$B$22,'PR Report - DOWNTOWN'!$A$5:$A$22,A7) -> 2647058.8 | C7: =SUMIFS('PR Report - SINIYA'!$C$5:$C$21,'PR Report - SINIYA'!$A$5:$A$21,$A7)+SUMIFS('PR Report - DOWNTOWN'!$C$5:$C$22,'PR Report - DOWNTOWN'!$A$5:$A$22,A7) -> 2617764.5 | D7: =SUMIFS('PR Report - SINIYA'!$D$5:$D$21,'PR Report - SINIYA'!$A$5:$A$21,$A7)+SUMIFS('PR Report - DOWNTOWN'!$D$5:$D$22,'PR Report - DOWNTOWN'!$A$5:$A$22,$A7) -> 13235294 | E7: =SUMIFS('PR Report - SINIYA'!$E$5:$E$21,'PR Report - SINIYA'!$A$5:$A$21,$A7)+SUMIFS('PR Report - SOBHA '!$E$5:$E$26,'PR Report - SOBHA '!$A$5:$A$26,$A7)+SUMIFS('PR Report - DOWNTOWN'!$E$5:$E$22,'PR Report - DOWNTOWN'!$A$5:$A$22,A7) -> 10927221 | F7: =SUMIFS('PR Report - SINIYA'!$F$5:$F$21,'PR Report - SINIYA'!$A$5:$A$21,$A7)+SUMIFS('PR Report - SOBHA '!$F$5:$F$26,'PR Report - SOBHA '!$A$5:$A$26,$A7)+SUMIFS('PR Report - DOWNTOWN'!$F$5:$F$22,'PR Report - DOWNTOWN'!$A$5:$A$22,A7) -> 45000000 | G7: =IFERROR(E7/D7,0) -> 0.82561229 | H7: =SUMIFS('PR Report - SINIYA'!$H$5:$H$21,'PR Report - SINIYA'!$A$5:$A$21,$A7)+SUMIFS('PR Report - SOBHA '!$H$5:$H$26,'PR Report - SOBHA '!$A$5:$A$26,$A7)+SUMIFS('PR Report - DOWNTOWN'!$H$5:$H$22,'PR Report - DOWNTOWN'!$A$5:$A$22,A7) -> 5979287.7 | I7: =SUMIFS('PR Report - SINIYA'!$I$5:$I$21,'PR Report - SINIYA'!$A$5:$A$21,$A7)+SUMIFS('PR Report - SOBHA '!$I$5:$I$26,'PR Report - SOBHA '!$A$5:$A$26,$A7)+SUMIFS('PR Report - DOWNTOWN'!$I$5:$I$22,'PR Report - DOWNTOWN'!$A$5:$A$22,A7) -> 4265516.2
A8: Anna | B8: =SUMIFS('PR Report - SINIYA'!$B$5:$B$21,'PR Report - SINIYA'!$A$5:$A$21,A8)+SUMIFS('PR Report - DOWNTOWN'!$B$5:$B$22,'PR Report - DOWNTOWN'!$A$5:$A$22,A8) -> 1176470.6 | C8: =SUMIFS('PR Report - SINIYA'!$C$5:$C$21,'PR Report - SINIYA'!$A$5:$A$21,$A8)+SUMIFS('PR Report - DOWNTOWN'!$C$5:$C$22,'PR Report - DOWNTOWN'!$A$5:$A$22,A8) -> 420035.73 | D8: =SUMIFS('PR Report - SINIYA'!$D$5:$D$21,'PR Report - SINIYA'!$A$5:$A$21,$A8)+SUMIFS('PR Report - DOWNTOWN'!$D$5:$D$22,'PR Report - DOWNTOWN'!$A$5:$A$22,$A8) -> 5882352.9 | E8: =SUMIFS('PR Report - SINIYA'!$E$5:$E$21,'PR Report - SINIYA'!$A$5:$A$21,$A8)+SUMIFS('PR Report - SOBHA '!$E$5:$E$26,'PR Report - SOBHA '!$A$5:$A$26,$A8)+SUMIFS('PR Report - DOWNTOWN'!$E$5:$E$22,'PR Report - DOWNTOWN'!$A$5:$A$22,A8) -> 2932051.8 | F8: =SUMIFS('PR Report - SINIYA'!$F$5:$F$21,'PR Report - SINIYA'!$A$5:$A$21,$A8)+SUMIFS('PR Report - SOBHA '!$F$5:$F$26,'PR Report - SOBHA '!$A$5:$A$26,$A8)+SUMIFS('PR Report - DOWNTOWN'!$F$5:$F$22,'PR Report - DOWNTOWN'!$A$5:$A$22,A8) -> 20000000 | G8: =IFERROR(E8/D8,0) -> 0.4984488 | H8: =SUMIFS('PR Report - SINIYA'!$H$5:$H$21,'PR Report - SINIYA'!$A$5:$A$21,$A8)+SUMIFS('PR Report - SOBHA '!$H$5:$H$26,'PR Report - SOBHA '!$A$5:$A$26,$A8)+SUMIFS('PR Report - DOWNTOWN'!$H$5:$H$22,'PR Report - DOWNTOWN'!$A$5:$A$22,A8) -> 2112020 | I8: =SUMIFS('PR Report - SINIYA'!$I$5:$I$21,'PR Report - SINIYA'!$A$5:$A$21,$A8)+SUMIFS('PR Report - SOBHA '!$I$5:$I$26,'PR Report - SOBHA '!$A$5:$A$26,$A8)+SUMIFS('PR Report - DOWNTOWN'!$I$5:$I$22,'PR Report - DOWNTOWN'!$A$5:$A$22,A8) -> 506236.11
A9: UAQ Sub Total | B9: =SUM(B5:B8) -> 11470588 | C9: =SUM(C5:C8) -> 7498418.9 | D9: =SUM(D5:D8) -> 57352941 | E9: =SUM(E5:E8) -> 43069458 | F9: =SUM(F5:F8) -> 195000000 | G9: =IFERROR(E9/D9,0) -> 0.75095465 | H9: =SUM(H5:H8) -> 25142938 | I9: =SUM(I5:I8) -> 18562925
A10: Ruhul | B10: =SUMIFS('PR Report - SOBHA '!$B$5:$B$26,'PR Report - SOBHA '!$A$5:$A$26,A10) -> 2774274.2 | C10: =SUMIFS('PR Report - SOBHA '!$C$5:$C$26,'PR Report - SOBHA '!$A$5:$A$26,$A10) -> 524510 | D10: =SUMIFS('PR Report - SOBHA '!$D$5:$D$26,'PR Report - SOBHA '!$A$5:$A$26,$A10) -> 13871371 | E10: =SUMIFS('PR Report - SOBHA '!$E$5:$E$26,'PR Report - SOBHA '!$A$5:$A$26,$A10) -> 1833821 | F10: =SUMIFS('PR Report - SOBHA '!$F$5:$F$26,'PR Report - SOBHA '!$A$5:$A$26,$A10) -> 47162662 | G10: =IFERROR(E10/D10,0) -> 0.13220185 | H10: =SUMIFS('PR Report - SOBHA '!$H$5:$H$26,'PR Report - SOBHA '!$A$5:$A$26,$A10) -> 5649097.7 | I10: =SUMIFS('PR Report - SOBHA '!$I$5:$I$26,'PR Report - SOBHA '!$A$5:$A$26,$A10) -> 4238208.5
A11: Ali | B11: =SUMIFS('PR Report - SOBHA '!$B$5:$B$26,'PR Report - SOBHA '!$A$5:$A$26,A11) -> 2176503.6 | C11: =SUMIFS('PR Report - SOBHA '!$C$5:$C$26,'PR Report - SOBHA '!$A$5:$A$26,$A11) -> 782720 | D11: =SUMIFS('PR Report - SOBHA '!$D$5:$D$26,'PR Report - SOBHA '!$A$5:$A$26,$A11) -> 10882518 | E11: =SUMIFS('PR Report - SOBHA '!$E$5:$E$26,'PR Report - SOBHA '!$A$5:$A$26,$A11) -> 6917700 | F11: =SUMIFS('PR Report - SOBHA '!$F$5:$F$26,'PR Report - SOBHA '!$A$5:$A$26,$A11) -> 37000562 | G11: =IFERROR(E11/D11,0) -> 0.63567089 | H11: =SUMIFS('PR Report - SOBHA '!$H$5:$H$26,'PR Report - SOBHA '!$A$5:$A$26,$A11) -> 6097448.4 | I11: =SUMIFS('PR Report - SOBHA '!$I$5:$I$26,'PR Report - SOBHA '!$A$5:$A$26,$A11) -> 5003503.6
A12: Anirudh | B12: =SUMIFS('PR Report - SOBHA '!$B$5:$B$26,'PR Report - SOBHA '!$A$5:$A$26,A12) -> 2840497.8 | C12: =SUMIFS('PR Report - SOBHA '!$C$5:$C$26,'PR Report - SOBHA '!$A$5:$A$26,$A12) -> 1817369.1 | D12: =SUMIFS('PR Report - SOBHA '!$D$5:$D$26,'PR Report - SOBHA '!$A$5:$A$26,$A12) -> 14202489 | E12: =SUMIFS('PR Report - SOBHA '!$E$5:$E$26,'PR Report - SOBHA '!$A$5:$A$26,$A12) -> 9826728.7 | F12: =SUMIFS('PR Report - SOBHA '!$F$5:$F$26,'PR Report - SOBHA '!$A$5:$A$26,$A12) -> 48288463 | G12: =IFERROR(E12/D12,0) -> 0.69190187 | H12: =SUMIFS('PR Report - SOBHA '!$H$5:$H$26,'PR Report - SOBHA '!$A$5:$A$26,$A12) -> 12626119 | I12: =SUMIFS('PR Report - SOBHA '!$I$5:$I$26,'PR Report - SOBHA '!$A$5:$A$26,$A12) -> 4572457
A13: Aqsa | B13: =SUMIFS('PR Report - SOBHA '!$B$5:$B$26,'PR Report - SOBHA '!$A$5:$A$26,A13) -> 3450528.4 | C13: =SUMIFS('PR Report - SOBHA '!$C$5:$C$26,'PR Report - SOBHA '!$A$5:$A$26,$A13) -> 1978777 | D13: =SUMIFS('PR Report - SOBHA '!$D$5:$D$26,'PR Report - SOBHA '!$A$5:$A$26,$A13) -> 17252642 | E13: =SUMIFS('PR Report - SOBHA '!$E$5:$E$26,'PR Report - SOBHA '!$A$5:$A$26,$A13) -> 11759965 | F13: =SUMIFS('PR Report - SOBHA '!$F$5:$F$26,'PR Report - SOBHA '!$A$5:$A$26,$A13) -> 58658983 | G13: =IFERROR(E13/D13,0) -> 0.68163271 | H13: =SUMIFS('PR Report - SOBHA '!$H$5:$H$26,'PR Report - SOBHA '!$A$5:$A$26,$A13) -> 5336207 | I13: =SUMIFS('PR Report - SOBHA '!$I$5:$I$26,'PR Report - SOBHA '!$A$5:$A$26,$A13) -> 4216231.3
A14: Karan | B14: =SUMIFS('PR Report - SOBHA '!$B$5:$B$26,'PR Report - SOBHA '!$A$5:$A$26,A14) -> 2554015.1 | C14: =SUMIFS('PR Report - SOBHA '!$C$5:$C$26,'PR Report - SOBHA '!$A$5:$A$26,$A14) -> 1311551 | D14: =SUMIFS('PR Report - SOBHA '!$D$5:$D$26,'PR Report - SOBHA '!$A$5:$A$26,$A14) -> 12770076 | E14: =SUMIFS('PR Report - SOBHA '!$E$5:$E$26,'PR Report - SOBHA '!$A$5:$A$26,$A14) -> 6990927 | F14: =SUMIFS('PR Report - SOBHA '!$F$5:$F$26,'PR Report - SOBHA '!$A$5:$A$26,$A14) -> 43418257 | G14: =IFERROR(E14/D14,0) -> 0.54744602 | H14: =SUMIFS('PR Report - SOBHA '!$H$5:$H$26,'PR Report - SOBHA '!$A$5:$A$26,$A14) -> 1317193.7 | I14: =SUMIFS('PR Report - SOBHA '!$I$5:$I$26,'PR Report - SOBHA '!$A$5:$A$26,$A14) -> 2640605.4
A15: Rajiv | B15: =SUMIFS('PR Report - SOBHA '!$B$5:$B$26,'PR Report - SOBHA '!$A$5:$A$26,A15) -> 2238461.1 | C15: =SUMIFS('PR Report - SOBHA '!$C$5:$C$26,'PR Report - SOBHA '!$A$5:$A$26,$A15) -> 2279577 | D15: =SUMIFS('PR Report - SOBHA '!$D$5:$D$26,'PR Report - SOBHA '!$A$5:$A$26,$A15) -> 11192305 | E15: =SUMIFS('PR Report - SOBHA '!$E$5:$E$26,'PR Report - SOBHA '!$A$5:$A$26,$A15) -> 11501814 | F15: =SUMIFS('PR Report - SOBHA '!$F$5:$F$26,'PR Report - SOBHA '!$A$5:$A$26,$A15) -> 38053838 | G15: =IFERROR(E15/D15,0) -> 1.0276537 | H15: =SUMIFS('PR Report - SOBHA '!$H$5:$H$26,'PR Report - SOBHA '!$A$5:$A$26,$A15) -> 5271884.8 | I15: =SUMIFS('PR Report - SOBHA '!$I$5:$I$26,'PR Report - SOBHA '!$A$5:$A$26,$A15) -> 7215187.2
A16: Vinod | B16: =SUMIFS('PR Report - SOBHA '!$B$5:$B$26,'PR Report - SOBHA '!$A$5:$A$26,A16) -> 3230160.1 | C16: =SUMIFS('PR Report - SOBHA '!$C$5:$C$26,'PR Report - SOBHA '!$A$5:$A$26,$A16) -> 200000 | D16: =SUMIFS('PR Report - SOBHA '!$D$5:$D$26,'PR Report - SOBHA '!$A$5:$A$26,$A16) -> 16150800 | E16: =SUMIFS('PR Report - SOBHA '!$E$5:$E$26,'PR Report - SOBHA '!$A$5:$A$26,$A16) -> 2056939.4 | F16: =SUMIFS('PR Report - SOBHA '!$F$5:$F$26,'PR Report - SOBHA '!$A$5:$A$26,$A16) -> 54912721 | G16: =IFERROR(E16/D16,0) -> 0.12735836 | H16: =SUMIFS('PR Report - SOBHA '!$H$5:$H$26,'PR Report - SOBHA '!$A$5:$A$26,$A16) -> 3957231.4 | I16: =SUMIFS('PR Report - SOBHA '!$I$5:$I$26,'PR Report - SOBHA '!$A$5:$A$26,$A16) -> 4142840.9
A17: Sarmad | B17: =SUMIFS('PR Report - SOBHA '!$B$5:$B$26,'PR Report - SOBHA '!$A$5:$A$26,A17) -> 3286315.3 | C17: =SUMIFS('PR Report - SOBHA '!$C$5:$C$26,'PR Report - SOBHA '!$A$5:$A$26,$A17) -> 2498098 | D17: =SUMIFS('PR Report - SOBHA '!$D$5:$D$26,'PR Report - SOBHA '!$A$5:$A$26,$A17) -> 16431576 | E17: =SUMIFS('PR Report - SOBHA '!$E$5:$E$26,'PR Report - SOBHA '!$A$5:$A$26,$A17) -> 14591524 | F17: =SUMIFS('PR Report - SOBHA '!$F$5:$F$26,'PR Report - SOBHA '!$A$5:$A$26,$A17) -> 55867360 | G17: =IFERROR(E17/D17,0) -> 0.88801731 | H17: =SUMIFS('PR Report - SOBHA '!$H$5:$H$26,'PR Report - SOBHA '!$A$5:$A$26,$A17) -> 6509957 | I17: =SUMIFS('PR Report - SOBHA '!$I$5:$I$26,'PR Report - SOBHA '!$A$5:$A$26,$A17) -> 8001301.3
A18: Zeba | B18: =SUMIFS('PR Report - SOBHA '!$B$5:$B$26,'PR Report - SOBHA '!$A$5:$A$26,A18) -> 2363747 | C18: =SUMIFS('PR Report - SOBHA '!$C$5:$C$26,'PR Report - SOBHA '!$A$5:$A$26,$A18) -> 1158239 | D18: =SUMIFS('PR Report - SOBHA '!$D$5:$D$26,'PR Report - SOBHA '!$A$5:$A$26,$A18) -> 11818735 | E18: =SUMIFS('PR Report - SOBHA '!$E$5:$E$26,'PR Report - SOBHA '!$A$5:$A$26,$A18) -> 10504253 | F18: =SUMIFS('PR Report - SOBHA '!$F$5:$F$26,'PR Report - SOBHA '!$A$5:$A$26,$A18) -> 40183699 | G18: =IFERROR(E18/D18,0) -> 0.88877983 | H18: =SUMIFS('PR Report - SOBHA '!$H$5:$H$26,'PR Report - SOBHA '!$A$5:$A$26,$A18) -> 5863137.4 | I18: =SUMIFS('PR Report - SOBHA '!$I$5:$I$26,'PR Report - SOBHA '!$A$5:$A$26,$A18) -> 6262318.3
A19: Oksana | B19: =SUMIFS('PR Report - SOBHA '!$B$5:$B$26,'PR Report - SOBHA '!$A$5:$A$26,A19) -> 2106539.8 | C19: =SUMIFS('PR Report - SOBHA '!$C$5:$C$26,'PR Report - SOBHA '!$A$5:$A$26,$A19) -> 2059510 | D19: =SUMIFS('PR Report - SOBHA '!$D$5:$D$26,'PR Report - SOBHA '!$A$5:$A$26,$A19) -> 10532699 | E19: =SUMIFS('PR Report - SOBHA '!$E$5:$E$26,'PR Report - SOBHA '!$A$5:$A$26,$A19) -> 10391011 | F19: =SUMIFS('PR Report - SOBHA '!$F$5:$F$26,'PR Report - SOBHA '!$A$5:$A$26,$A19) -> 35811177 | G19: =IFERROR(E19/D19,0) -> 0.98654779 | H19: =SUMIFS('PR Report - SOBHA '!$H$5:$H$26,'PR Report - SOBHA '!$A$5:$A$26,$A19) -> 5228871.5 | I19: =SUMIFS('PR Report - SOBHA '!$I$5:$I$26,'PR Report - SOBHA '!$A$5:$A$26,$A19) -> 5422934.5
A20: Omar | B20: =SUMIFS('PR Report - SOBHA '!$B$5:$B$26,'PR Report - SOBHA '!$A$5:$A$26,A20) -> 2458129.9 | C20: =SUMIFS('PR Report - SOBHA '!$C$5:$C$26,'PR Report - SOBHA '!$A$5:$A$26,$A20) -> 2171492.8 | D20: =SUMIFS('PR Report - SOBHA '!$D$5:$D$26,'PR Report - SOBHA '!$A$5:$A$26,$A20) -> 12290649 | E20: =SUMIFS('PR Report - SOBHA '!$E$5:$E$26,'PR Report - SOBHA '!$A$5:$A$26,$A20) -> 9750271.5 | F20: =SUMIFS('PR Report - SOBHA '!$F$5:$F$26,'PR Report - SOBHA '!$A$5:$A$26,$A20) -> 41788208 | G20: =IFERROR(E20/D20,0) -> 0.79330808 | H20: =SUMIFS('PR Report - SOBHA '!$H$5:$H$26,'PR Report - SOBHA '!$A$5:$A$26,$A20) -> 20466705 | I20: =SUMIFS('PR Report - SOBHA '!$I$5:$I$26,'PR Report - SOBHA '!$A$5:$A$26,$A20) -> 4744590
A21: Sabah | B21: =SUMIFS('PR Report - SOBHA '!$B$5:$B$26,'PR Report - SOBHA '!$A$5:$A$26,A21) -> 1740757.5 | C21: =SUMIFS('PR Report - SOBHA '!$C$5:$C$26,'PR Report - SOBHA '!$A$5:$A$26,$A21) -> 999311 | D21: =SUMIFS('PR Report - SOBHA '!$D$5:$D$26,'PR Report - SOBHA '!$A$5:$A$26,$A21) -> 8703787.6 | E21: =SUMIFS('PR Report - SOBHA '!$E$5:$E$26,'PR Report - SOBHA '!$A$5:$A$26,$A21) -> 5039866 | F21: =SUMIFS('PR Report - SOBHA '!$F$5:$F$26,'PR Report - SOBHA '!$A$5:$A$26,$A21) -> 29592878 | G21: =IFERROR(E21/D21,0) -> 0.57904285 | H21: =SUMIFS('PR Report - SOBHA '!$H$5:$H$26,'PR Report - SOBHA '!$A$5:$A$26,$A21) -> 3510870.3 | I21: =SUMIFS('PR Report - SOBHA '!$I$5:$I$26,'PR Report - SOBHA '!$A$5:$A$26,$A21) -> 3034882.1
... A31: Moustafa | B31: =SUMIFS('PR Report - SOBHA '!$B$5:$B$26,'PR Report - SOBHA '!$A$5:$A$26,A31) -> 1670123.7 | C31: =SUMIFS('PR Report - SOBHA '!$C$5:$C$26,'PR Report - SOBHA '!$A$5:$A$26,$A31) -> 1101602 | D31: =SUMIFS('PR Report - SOBHA '!$D$5:$D$26,'PR Report - SOBHA '!$A$5:$A$26,$A31) -> 8350618.5 | E31: =SUMIFS('PR Report - SOBHA '!$E$5:$E$26,'PR Report - SOBHA '!$A$5:$A$26,$A31) -> 5871852 | F31: =SUMIFS('PR Report - SOBHA '!$F$5:$F$26,'PR Report - SOBHA '!$A$5:$A$26,$A31) -> 28392103 | G31: =IFERROR(E31/D31,0) -> 0.70316372 | H31: =SUMIFS('PR Report - SOBHA '!$H$5:$H$26,'PR Report - SOBHA '!$A$5:$A$26,$A31) -> 3612983.7 | I31: =SUMIFS('PR Report - SOBHA '!$I$5:$I$26,'PR Report - SOBHA '!$A$5:$A$26,$A31) -> 4581377.6
A32: SOBHA Sub Total | B32: =SUM(B10:B31) -> 50252771 | C32: =SUM(C10:C31) -> 34438498 | D32: =SUM(D10:D31) -> 2.5126385e+08 | E32: =SUM(E10:E31) -> 1.7426434e+08 | F32: =SUM(F10:F31) -> 854297104 | G32: =IFERROR(E32/D32,0) -> 0.69355115 | H32: =SUM(H10:H31) -> 1.2977049e+08 | I32: =SUM(I10:I31) -> 1.0721567e+08
A33: Omar | B33: =SUMIFS('PR Report - SOBHA AUH'!B$4:B$21,'PR Report - SOBHA AUH'!$A$4:$A$21,$A33) -> 0 | C33: =SUMIFS('PR Report - SOBHA AUH'!C$4:C$21,'PR Report - SOBHA AUH'!$A$4:$A$21,$A$33) -> 0 | D33: =SUMIFS('PR Report - SOBHA AUH'!D$4:D$21,'PR Report - SOBHA AUH'!$A$4:$A$21,$A$33) -> 0 | E33: =SUMIFS('PR Report - SOBHA AUH'!E$4:E$21,'PR Report - SOBHA AUH'!$A$4:$A$21,$A$33) -> 0 | F33: =SUMIFS('PR Report - SOBHA AUH'!F$4:F$21,'PR Report - SOBHA AUH'!$A$4:$A$21,$A$33) -> 0 | G33: =IFERROR(E33/D33,0) -> 0 | H33: =SUMIFS('PR Report - SOBHA AUH'!H$4:H$21,'PR Report - SOBHA AUH'!$A$4:$A$21,$A$33) -> 0 | I33: =SUMIFS('PR Report - SOBHA AUH'!I$4:I$21,'PR Report - SOBHA AUH'!$A$4:$A$21,$A$33) -> 0
A34: Ruhul | B34: =SUMIFS('PR Report - SOBHA AUH'!B$4:B$21,'PR Report - SOBHA AUH'!$A$4:$A$21,$A34) -> 0 | C34: =SUMIFS('PR Report - SOBHA AUH'!C$4:C$21,'PR Report - SOBHA AUH'!$A$4:$A$21,$A34) -> 0 | D34: =SUMIFS('PR Report - SOBHA AUH'!D$4:D$21,'PR Report - SOBHA AUH'!$A$4:$A$21,$A34) -> 0 | E34: =SUMIFS('PR Report - SOBHA AUH'!E$4:E$21,'PR Report - SOBHA AUH'!$A$4:$A$21,$A34) -> 0 | F34: =SUMIFS('PR Report - SOBHA AUH'!F$4:F$21,'PR Report - SOBHA AUH'!$A$4:$A$21,$A34) -> 0 | G34: =IFERROR(E34/D34,0) -> 0 | H34: =SUMIFS('PR Report - SOBHA AUH'!H$4:H$21,'PR Report - SOBHA AUH'!$A$4:$A$21,$A34) -> 559683 | I34: =SUMIFS('PR Report - SOBHA AUH'!I$4:I$21,'PR Report - SOBHA AUH'!$A$4:$A$21,$A34) -> 0
A35: Vinod | B35: =SUMIFS('PR Report - SOBHA AUH'!B$4:B$21,'PR Report - SOBHA AUH'!$A$4:$A$21,$A35) -> 0 | C35: =SUMIFS('PR Report - SOBHA AUH'!C$4:C$21,'PR Report - SOBHA AUH'!$A$4:$A$21,$A35) -> 0 | D35: =SUMIFS('PR Report - SOBHA AUH'!D$4:D$21,'PR Report - SOBHA AUH'!$A$4:$A$21,$A35) -> 0 | E35: =SUMIFS('PR Report - SOBHA AUH'!E$4:E$21,'PR Report - SOBHA AUH'!$A$4:$A$21,$A35) -> 0 | F35: =SUMIFS('PR Report - SOBHA AUH'!F$4:F$21,'PR Report - SOBHA AUH'!$A$4:$A$21,$A35) -> 0 | G35: =IFERROR(E35/D35,0) -> 0 | H35: =SUMIFS('PR Report - SOBHA AUH'!H$4:H$21,'PR Report - SOBHA AUH'!$A$4:$A$21,$A35) -> 0 | I35: =SUMIFS('PR Report - SOBHA AUH'!I$4:I$21,'PR Report - SOBHA AUH'!$A$4:$A$21,$A35) -> 0
A36: SOBHA AUH Sub Total | B36: =SUM(B33:B35) -> 0 | C36: =SUM(C33:C35) -> 0 | D36: =SUM(D33:D35) -> 0 | E36: =SUM(E33:E35) -> 0 | F36: =SUM(F33:F35) -> 0 | G36: =SUM(G33:G35) -> 0 | H36: =SUM(H33:H35) -> 559683 | I36: =SUM(I33:I35) -> 0
A37: Total Dues | B37: =SUM(B32,B9,B36) -> 61723359 | C37: =SUM(C32,C9,C36) -> 41936917 | D37: =SUM(D32,D9,D36) -> 3.086168e+08 | E37: =SUM(E32,E9,E36) -> 2.1733379e+08 | F37: =SUM(F32,F9,F36) -> 1049297104 | G37: =IFERROR((E37)/(D37),0) -> 0.70421894 | H37: =SUM(H32,H9,H36) -> 1.5547312e+08 | I37: =SUM(I32,I9,I36) -> 1.2577859e+08
A38: Advances
A39: Abdulla | B39: =SUMIFS('PR Report - DOWNTOWN'!B$25:B$35,'PR Report - DOWNTOWN'!$A$25:$A$35,$A39)+SUMIFS('PR Report - SINIYA'!B$24:B$34,'PR Report - SINIYA'!$A$24:$A$34,$A39) -> 0 | C39: =SUMIFS('PR Report - DOWNTOWN'!C$25:C$35,'PR Report - DOWNTOWN'!$A$25:$A$35,$A39)+SUMIFS('PR Report - SINIYA'!C$24:C$34,'PR Report - SINIYA'!$A$24:$A$34,$A39) -> 0 | D39: =SUMIFS('PR Report - DOWNTOWN'!D$25:D$35,'PR Report - DOWNTOWN'!$A$25:$A$35,$A39)+SUMIFS('PR Report - SINIYA'!D$24:D$34,'PR Report - SINIYA'!$A$24:$A$34,$A39) -> 0 | E39: =SUMIFS('PR Report - DOWNTOWN'!E$25:E$35,'PR Report - DOWNTOWN'!$A$25:$A$35,$A39)+SUMIFS('PR Report - SINIYA'!E$24:E$34,'PR Report - SINIYA'!$A$24:$A$34,$A39) -> 216912 | F39: =SUMIFS('PR Report - DOWNTOWN'!F$25:F$35,'PR Report - DOWNTOWN'!$A$25:$A$35,$A39)+SUMIFS('PR Report - SINIYA'!F$24:F$34,'PR Report - SINIYA'!$A$24:$A$34,$A39) -> 0 | G39: =IFERROR(E39/D39,0) -> 0 | H39: =SUMIFS('PR Report - DOWNTOWN'!H$25:H$35,'PR Report - DOWNTOWN'!$A$25:$A$35,$A39)+SUMIFS('PR Report - SINIYA'!H$24:H$34,'PR Report - SINIYA'!$A$24:$A$34,$A39) -> 288016 | I39: =SUMIFS('PR Report - DOWNTOWN'!I$25:I$35,'PR Report - DOWNTOWN'!$A$25:$A$35,$A39)+SUMIFS('PR Report - SINIYA'!I$24:I$34,'PR Report - SINIYA'!$A$24:$A$34,$A39) -> 0
A40: Ateev | B40: =SUMIFS('PR Report - DOWNTOWN'!B$25:B$35,'PR Report - DOWNTOWN'!$A$25:$A$35,$A40)+SUMIFS('PR Report - SINIYA'!B$24:B$34,'PR Report - SINIYA'!$A$24:$A$34,$A40) -> 0 | C40: =SUMIFS('PR Report - DOWNTOWN'!C$25:C$35,'PR Report - DOWNTOWN'!$A$25:$A$35,$A40)+SUMIFS('PR Report - SINIYA'!C$24:C$34,'PR Report - SINIYA'!$A$24:$A$34,$A40) -> 0 | D40: =SUMIFS('PR Report - DOWNTOWN'!D$25:D$35,'PR Report - DOWNTOWN'!$A$25:$A$35,$A40)+SUMIFS('PR Report - SINIYA'!D$24:D$34,'PR Report - SINIYA'!$A$24:$A$34,$A40) -> 0 | E40: =SUMIFS('PR Report - DOWNTOWN'!E$25:E$35,'PR Report - DOWNTOWN'!$A$25:$A$35,$A40)+SUMIFS('PR Report - SINIYA'!E$24:E$34,'PR Report - SINIYA'!$A$24:$A$34,$A40) -> 0 | F40: =SUMIFS('PR Report - DOWNTOWN'!F$25:F$35,'PR Report - DOWNTOWN'!$A$25:$A$35,$A40)+SUMIFS('PR Report - SINIYA'!F$24:F$34,'PR Report - SINIYA'!$A$24:$A$34,$A40) -> 0 | G40: =IFERROR(E40/D40,0) -> 0 | H40: =SUMIFS('PR Report - DOWNTOWN'!H$25:H$35,'PR Report - DOWNTOWN'!$A$25:$A$35,$A40)+SUMIFS('PR Report - SINIYA'!H$24:H$34,'PR Report - SINIYA'!$A$24:$A$34,$A40) -> 0 | I40: =SUMIFS('PR Report - DOWNTOWN'!I$25:I$35,'PR Report - DOWNTOWN'!$A$25:$A$35,$A40)+SUMIFS('PR Report - SINIYA'!I$24:I$34,'PR Report - SINIYA'!$A$24:$A$34,$A40) -> 0
A41: Ayari | B41: =SUMIFS('PR Report - DOWNTOWN'!B$25:B$35,'PR Report - DOWNTOWN'!$A$25:$A$35,$A41)+SUMIFS('PR Report - SINIYA'!B$24:B$34,'PR Report - SINIYA'!$A$24:$A$34,$A41) -> 0 | C41: =SUMIFS('PR Report - DOWNTOWN'!C$25:C$35,'PR Report - DOWNTOWN'!$A$25:$A$35,$A41)+SUMIFS('PR Report - SINIYA'!C$24:C$34,'PR Report - SINIYA'!$A$24:$A$34,$A41) -> 0 | D41: =SUMIFS('PR Report - DOWNTOWN'!D$25:D$35,'PR Report - DOWNTOWN'!$A$25:$A$35,$A41)+SUMIFS('PR Report - SINIYA'!D$24:D$34,'PR Report - SINIYA'!$A$24:$A$34,$A41) -> 0 | E41: =SUMIFS('PR Report - DOWNTOWN'!E$25:E$35,'PR Report - DOWNTOWN'!$A$25:$A$35,$A41)+SUMIFS('PR Report - SINIYA'!E$24:E$34,'PR Report - SINIYA'!$A$24:$A$34,$A41) -> 0 | F41: =SUMIFS('PR Report - DOWNTOWN'!F$25:F$35,'PR Report - DOWNTOWN'!$A$25:$A$35,$A41)+SUMIFS('PR Report - SINIYA'!F$24:F$34,'PR Report - SINIYA'!$A$24:$A$34,$A41) -> 0 | G41: =IFERROR(E41/D41,0) -> 0 | H41: =SUMIFS('PR Report - DOWNTOWN'!H$25:H$35,'PR Report - DOWNTOWN'!$A$25:$A$35,$A41)+SUMIFS('PR Report - SINIYA'!H$24:H$34,'PR Report - SINIYA'!$A$24:$A$34,$A41) -> 0 | I41: =SUMIFS('PR Report - DOWNTOWN'!I$25:I$35,'PR Report - DOWNTOWN'!$A$25:$A$35,$A41)+SUMIFS('PR Report - SINIYA'!I$24:I$34,'PR Report - SINIYA'!$A$24:$A$34,$A41) -> 0
A42: Nischitha | B42: =SUMIFS('PR Report - DOWNTOWN'!B$25:B$35,'PR Report - DOWNTOWN'!$A$25:$A$35,$A42)+SUMIFS('PR Report - SINIYA'!B$24:B$34,'PR Report - SINIYA'!$A$24:$A$34,$A42) -> 0 | C42: =SUMIFS('PR Report - DOWNTOWN'!C$25:C$35,'PR Report - DOWNTOWN'!$A$25:$A$35,$A42)+SUMIFS('PR Report - SINIYA'!C$24:C$34,'PR Report - SINIYA'!$A$24:$A$34,$A42) -> 0 | D42: =SUMIFS('PR Report - DOWNTOWN'!D$25:D$35,'PR Report - DOWNTOWN'!$A$25:$A$35,$A42)+SUMIFS('PR Report - SINIYA'!D$24:D$34,'PR Report - SINIYA'!$A$24:$A$34,$A42) -> 0 | E42: =SUMIFS('PR Report - DOWNTOWN'!E$25:E$35,'PR Report - DOWNTOWN'!$A$25:$A$35,$A42)+SUMIFS('PR Report - SINIYA'!E$24:E$34,'PR Report - SINIYA'!$A$24:$A$34,$A42) -> 0 | F42: =SUMIFS('PR Report - DOWNTOWN'!F$25:F$35,'PR Report - DOWNTOWN'!$A$25:$A$35,$A42)+SUMIFS('PR Report - SINIYA'!F$24:F$34,'PR Report - SINIYA'!$A$24:$A$34,$A42) -> 0 | G42: =IFERROR(E42/D42,0) -> 0 | H42: =SUMIFS('PR Report - DOWNTOWN'!H$25:H$35,'PR Report - DOWNTOWN'!$A$25:$A$35,$A42)+SUMIFS('PR Report - SINIYA'!H$24:H$34,'PR Report - SINIYA'!$A$24:$A$34,$A42) -> 0 | I42: =SUMIFS('PR Report - DOWNTOWN'!I$25:I$35,'PR Report - DOWNTOWN'!$A$25:$A$35,$A42)+SUMIFS('PR Report - SINIYA'!I$24:I$34,'PR Report - SINIYA'!$A$24:$A$34,$A42) -> 0
A43: Noha | B43: =SUMIFS('PR Report - DOWNTOWN'!B$25:B$35,'PR Report - DOWNTOWN'!$A$25:$A$35,$A43)+SUMIFS('PR Report - SINIYA'!B$24:B$34,'PR Report - SINIYA'!$A$24:$A$34,$A43) -> 0 | C43: =SUMIFS('PR Report - DOWNTOWN'!C$25:C$35,'PR Report - DOWNTOWN'!$A$25:$A$35,$A43)+SUMIFS('PR Report - SINIYA'!C$24:C$34,'PR Report - SINIYA'!$A$24:$A$34,$A43) -> 65000 | D43: =SUMIFS('PR Report - DOWNTOWN'!D$25:D$35,'PR Report - DOWNTOWN'!$A$25:$A$35,$A43)+SUMIFS('PR Report - SINIYA'!D$24:D$34,'PR Report - SINIYA'!$A$24:$A$34,$A43) -> 0 | E43: =SUMIFS('PR Report - DOWNTOWN'!E$25:E$35,'PR Report - DOWNTOWN'!$A$25:$A$35,$A43)+SUMIFS('PR Report - SINIYA'!E$24:E$34,'PR Report - SINIYA'!$A$24:$A$34,$A43) -> 389512 | F43: =SUMIFS('PR Report - DOWNTOWN'!F$25:F$35,'PR Report - DOWNTOWN'!$A$25:$A$35,$A43)+SUMIFS('PR Report - SINIYA'!F$24:F$34,'PR Report - SINIYA'!$A$24:$A$34,$A43) -> 0 | G43: =IFERROR(E43/D43,0) -> 0 | H43: =SUMIFS('PR Report - DOWNTOWN'!H$25:H$35,'PR Report - DOWNTOWN'!$A$25:$A$35,$A43)+SUMIFS('PR Report - SINIYA'!H$24:H$34,'PR Report - SINIYA'!$A$24:$A$34,$A43) -> 246507.85 | I43: =SUMIFS('PR Report - DOWNTOWN'!I$25:I$35,'PR Report - DOWNTOWN'!$A$25:$A$35,$A43)+SUMIFS('PR Report - SINIYA'!I$24:I$34,'PR Report - SINIYA'!$A$24:$A$34,$A43) -> 388807.68
A44: Sherif | B44: =SUMIFS('PR Report - DOWNTOWN'!B$25:B$35,'PR Report - DOWNTOWN'!$A$25:$A$35,$A44)+SUMIFS('PR Report - SINIYA'!B$24:B$34,'PR Report - SINIYA'!$A$24:$A$34,$A44) -> 0 | C44: =SUMIFS('PR Report - DOWNTOWN'!C$25:C$35,'PR Report - DOWNTOWN'!$A$25:$A$35,$A44)+SUMIFS('PR Report - SINIYA'!C$24:C$34,'PR Report - SINIYA'!$A$24:$A$34,$A44) -> 728758 | D44: =SUMIFS('PR Report - DOWNTOWN'!D$25:D$35,'PR Report - DOWNTOWN'!$A$25:$A$35,$A44)+SUMIFS('PR Report - SINIYA'!D$24:D$34,'PR Report - SINIYA'!$A$24:$A$34,$A44) -> 0 | E44: =SUMIFS('PR Report - DOWNTOWN'!E$25:E$35,'PR Report - DOWNTOWN'!$A$25:$A$35,$A44)+SUMIFS('PR Report - SINIYA'!E$24:E$34,'PR Report - SINIYA'!$A$24:$A$34,$A44) -> 1360004 | F44: =SUMIFS('PR Report - DOWNTOWN'!F$25:F$35,'PR Report - DOWNTOWN'!$A$25:$A$35,$A44)+SUMIFS('PR Report - SINIYA'!F$24:F$34,'PR Report - SINIYA'!$A$24:$A$34,$A44) -> 0 | G44: =IFERROR(E44/D44,0) -> 0 | H44: =SUMIFS('PR Report - DOWNTOWN'!H$25:H$35,'PR Report - DOWNTOWN'!$A$25:$A$35,$A44)+SUMIFS('PR Report - SINIYA'!H$24:H$34,'PR Report - SINIYA'!$A$24:$A$34,$A44) -> 604342 | I44: =SUMIFS('PR Report - DOWNTOWN'!I$25:I$35,'PR Report - DOWNTOWN'!$A$25:$A$35,$A44)+SUMIFS('PR Report - SINIYA'!I$24:I$34,'PR Report - SINIYA'!$A$24:$A$34,$A44) -> 141386
A45: Wael | B45: =SUMIFS('PR Report - DOWNTOWN'!B$25:B$35,'PR Report - DOWNTOWN'!$A$25:$A$35,$A45)+SUMIFS('PR Report - SINIYA'!B$24:B$34,'PR Report - SINIYA'!$A$24:$A$34,$A45) -> 0 | C45: =SUMIFS('PR Report - DOWNTOWN'!C$25:C$35,'PR Report - DOWNTOWN'!$A$25:$A$35,$A45)+SUMIFS('PR Report - SINIYA'!C$24:C$34,'PR Report - SINIYA'!$A$24:$A$34,$A45) -> 0 | D45: =SUMIFS('PR Report - DOWNTOWN'!D$25:D$35,'PR Report - DOWNTOWN'!$A$25:$A$35,$A45)+SUMIFS('PR Report - SINIYA'!D$24:D$34,'PR Report - SINIYA'!$A$24:$A$34,$A45) -> 0 | E45: =SUMIFS('PR Report - DOWNTOWN'!E$25:E$35,'PR Report - DOWNTOWN'!$A$25:$A$35,$A45)+SUMIFS('PR Report - SINIYA'!E$24:E$34,'PR Report - SINIYA'!$A$24:$A$34,$A45) -> 0 | F45: =SUMIFS('PR Report - DOWNTOWN'!F$25:F$35,'PR Report - DOWNTOWN'!$A$25:$A$35,$A45)+SUMIFS('PR Report - SINIYA'!F$24:F$34,'PR Report - SINIYA'!$A$24:$A$34,$A45) -> 0 | G45: =IFERROR(E45/D45,0) -> 0 | H45: =SUMIFS('PR Report - DOWNTOWN'!H$25:H$35,'PR Report - DOWNTOWN'!$A$25:$A$35,$A45)+SUMIFS('PR Report - SINIYA'!H$24:H$34,'PR Report - SINIYA'!$A$24:$A$34,$A45) -> 35775 | I45: =SUMIFS('PR Report - DOWNTOWN'!I$25:I$35,'PR Report - DOWNTOWN'!$A$25:$A$35,$A45)+SUMIFS('PR Report - SINIYA'!I$24:I$34,'PR Report - SINIYA'!$A$24:$A$34,$A45) -> 138572
A46: Krizia | B46: =SUMIFS('PR Report - DOWNTOWN'!B$25:B$35,'PR Report - DOWNTOWN'!$A$25:$A$35,$A46)+SUMIFS('PR Report - SINIYA'!B$24:B$34,'PR Report - SINIYA'!$A$24:$A$34,$A46) -> 0 | C46: =SUMIFS('PR Report - DOWNTOWN'!C$25:C$35,'PR Report - DOWNTOWN'!$A$25:$A$35,$A46)+SUMIFS('PR Report - SINIYA'!C$24:C$34,'PR Report - SINIYA'!$A$24:$A$34,$A46) -> 1747417 | D46: =SUMIFS('PR Report - DOWNTOWN'!D$25:D$35,'PR Report - DOWNTOWN'!$A$25:$A$35,$A46)+SUMIFS('PR Report - SINIYA'!D$24:D$34,'PR Report - SINIYA'!$A$24:$A$34,$A46) -> 0 | E46: =SUMIFS('PR Report - DOWNTOWN'!E$25:E$35,'PR Report - DOWNTOWN'!$A$25:$A$35,$A46)+SUMIFS('PR Report - SINIYA'!E$24:E$34,'PR Report - SINIYA'!$A$24:$A$34,$A46) -> 3436611 | F46: =SUMIFS('PR Report - DOWNTOWN'!F$25:F$35,'PR Report - DOWNTOWN'!$A$25:$A$35,$A46)+SUMIFS('PR Report - SINIYA'!F$24:F$34,'PR Report - SINIYA'!$A$24:$A$34,$A46) -> 0 | G46: =IFERROR(E46/D46,0) -> 0 | H46: =SUMIFS('PR Report - DOWNTOWN'!H$25:H$35,'PR Report - DOWNTOWN'!$A$25:$A$35,$A46)+SUMIFS('PR Report - SINIYA'!H$24:H$34,'PR Report - SINIYA'!$A$24:$A$34,$A46) -> 2091049 | I46: =SUMIFS('PR Report - DOWNTOWN'!I$25:I$35,'PR Report - DOWNTOWN'!$A$25:$A$35,$A46)+SUMIFS('PR Report - SINIYA'!I$24:I$34,'PR Report - SINIYA'!$A$24:$A$34,$A46) -> 661137
A47: Vijay | B47: =SUMIFS('PR Report - DOWNTOWN'!B$25:B$35,'PR Report - DOWNTOWN'!$A$25:$A$35,$A47)+SUMIFS('PR Report - SINIYA'!B$24:B$34,'PR Report - SINIYA'!$A$24:$A$34,$A47) -> 0 | C47: =SUMIFS('PR Report - DOWNTOWN'!C$25:C$35,'PR Report - DOWNTOWN'!$A$25:$A$35,$A47)+SUMIFS('PR Report - SINIYA'!C$24:C$34,'PR Report - SINIYA'!$A$24:$A$34,$A47) -> 0 | D47: =SUMIFS('PR Report - DOWNTOWN'!D$25:D$35,'PR Report - DOWNTOWN'!$A$25:$A$35,$A47)+SUMIFS('PR Report - SINIYA'!D$24:D$34,'PR Report - SINIYA'!$A$24:$A$34,$A47) -> 0 | E47: =SUMIFS('PR Report - DOWNTOWN'!E$25:E$35,'PR Report - DOWNTOWN'!$A$25:$A$35,$A47)+SUMIFS('PR Report - SINIYA'!E$24:E$34,'PR Report - SINIYA'!$A$24:$A$34,$A47) -> 0 | F47: =SUMIFS('PR Report - DOWNTOWN'!F$25:F$35,'PR Report - DOWNTOWN'!$A$25:$A$35,$A47)+SUMIFS('PR Report - SINIYA'!F$24:F$34,'PR Report - SINIYA'!$A$24:$A$34,$A47) -> 0 | G47: =IFERROR(E47/D47,0) -> 0 | H47: =SUMIFS('PR Report - DOWNTOWN'!H$25:H$35,'PR Report - DOWNTOWN'!$A$25:$A$35,$A47)+SUMIFS('PR Report - SINIYA'!H$24:H$34,'PR Report - SINIYA'!$A$24:$A$34,$A47) -> 0 | I47: =SUMIFS('PR Report - DOWNTOWN'!I$25:I$35,'PR Report - DOWNTOWN'!$A$25:$A$35,$A47)+SUMIFS('PR Report - SINIYA'!I$24:I$34,'PR Report - SINIYA'!$A$24:$A$34,$A47) -> 0
A48: Basma | B48: =SUMIFS('PR Report - DOWNTOWN'!B$25:B$35,'PR Report - DOWNTOWN'!$A$25:$A$35,$A48)+SUMIFS('PR Report - SINIYA'!B$24:B$34,'PR Report - SINIYA'!$A$24:$A$34,$A48) -> 0 | C48: =SUMIFS('PR Report - DOWNTOWN'!C$25:C$35,'PR Report - DOWNTOWN'!$A$25:$A$35,$A48)+SUMIFS('PR Report - SINIYA'!C$24:C$34,'PR Report - SINIYA'!$A$24:$A$34,$A48) -> 522609 | D48: =SUMIFS('PR Report - DOWNTOWN'!D$25:D$35,'PR Report - DOWNTOWN'!$A$25:$A$35,$A48)+SUMIFS('PR Report - SINIYA'!D$24:D$34,'PR Report - SINIYA'!$A$24:$A$34,$A48) -> 0 | E48: =SUMIFS('PR Report - DOWNTOWN'!E$25:E$35,'PR Report - DOWNTOWN'!$A$25:$A$35,$A48)+SUMIFS('PR Report - SINIYA'!E$24:E$34,'PR Report - SINIYA'!$A$24:$A$34,$A48) -> 1228490 | F48: =SUMIFS('PR Report - DOWNTOWN'!F$25:F$35,'PR Report - DOWNTOWN'!$A$25:$A$35,$A48)+SUMIFS('PR Report - SINIYA'!F$24:F$34,'PR Report - SINIYA'!$A$24:$A$34,$A48) -> 0 | G48: =IFERROR(E48/D48,0) -> 0 | H48: =SUMIFS('PR Report - DOWNTOWN'!H$25:H$35,'PR Report - DOWNTOWN'!$A$25:$A$35,$A48)+SUMIFS('PR Report - SINIYA'!H$24:H$34,'PR Report - SINIYA'!$A$24:$A$34,$A48) -> 749881 | I48: =SUMIFS('PR Report - DOWNTOWN'!I$25:I$35,'PR Report - DOWNTOWN'!$A$25:$A$35,$A48)+SUMIFS('PR Report - SINIYA'!I$24:I$34,'PR Report - SINIYA'!$A$24:$A$34,$A48) -> 0
A49: Jaidev | B49: =SUMIFS('PR Report - DOWNTOWN'!B$25:B$35,'PR Report - DOWNTOWN'!$A$25:$A$35,$A49)+SUMIFS('PR Report - SINIYA'!B$24:B$34,'PR Report - SINIYA'!$A$24:$A$34,$A49) -> 0 | C49: =SUMIFS('PR Report - DOWNTOWN'!C$25:C$35,'PR Report - DOWNTOWN'!$A$25:$A$35,$A49)+SUMIFS('PR Report - SINIYA'!C$24:C$34,'PR Report - SINIYA'!$A$24:$A$34,$A49) -> 0 | D49: =SUMIFS('PR Report - DOWNTOWN'!D$25:D$35,'PR Report - DOWNTOWN'!$A$25:$A$35,$A49)+SUMIFS('PR Report - SINIYA'!D$24:D$34,'PR Report - SINIYA'!$A$24:$A$34,$A49) -> 0 | E49: =SUMIFS('PR Report - DOWNTOWN'!E$25:E$35,'PR Report - DOWNTOWN'!$A$25:$A$35,$A49)+SUMIFS('PR Report - SINIYA'!E$24:E$34,'PR Report - SINIYA'!$A$24:$A$34,$A49) -> 0 | F49: =SUMIFS('PR Report - DOWNTOWN'!F$25:F$35,'PR Report - DOWNTOWN'!$A$25:$A$35,$A49)+SUMIFS('PR Report - SINIYA'!F$24:F$34,'PR Report - SINIYA'!$A$24:$A$34,$A49) -> 0 | G49: =IFERROR(E49/D49,0) -> 0 | H49: =SUMIFS('PR Report - DOWNTOWN'!H$25:H$35,'PR Report - DOWNTOWN'!$A$25:$A$35,$A49)+SUMIFS('PR Report - SINIYA'!H$24:H$34,'PR Report - SINIYA'!$A$24:$A$34,$A49) -> 0 | I49: =SUMIFS('PR Report - DOWNTOWN'!I$25:I$35,'PR Report - DOWNTOWN'!$A$25:$A$35,$A49)+SUMIFS('PR Report - SINIYA'!I$24:I$34,'PR Report - SINIYA'!$A$24:$A$34,$A49) -> 0
A50: Yogesh | B50: =SUMIFS('PR Report - DOWNTOWN'!B$25:B$35,'PR Report - DOWNTOWN'!$A$25:$A$35,$A50)+SUMIFS('PR Report - SINIYA'!B$24:B$34,'PR Report - SINIYA'!$A$24:$A$34,$A50) -> 0 | C50: =SUMIFS('PR Report - DOWNTOWN'!C$25:C$35,'PR Report - DOWNTOWN'!$A$25:$A$35,$A50)+SUMIFS('PR Report - SINIYA'!C$24:C$34,'PR Report - SINIYA'!$A$24:$A$34,$A50) -> 0 | D50: =SUMIFS('PR Report - DOWNTOWN'!D$25:D$35,'PR Report - DOWNTOWN'!$A$25:$A$35,$A50)+SUMIFS('PR Report - SINIYA'!D$24:D$34,'PR Report - SINIYA'!$A$24:$A$34,$A50) -> 0 | E50: =SUMIFS('PR Report - DOWNTOWN'!E$25:E$35,'PR Report - DOWNTOWN'!$A$25:$A$35,$A50)+SUMIFS('PR Report - SINIYA'!E$24:E$34,'PR Report - SINIYA'!$A$24:$A$34,$A50) -> 1781697 | F50: =SUMIFS('PR Report - DOWNTOWN'!F$25:F$35,'PR Report - DOWNTOWN'!$A$25:$A$35,$A50)+SUMIFS('PR Report - SINIYA'!F$24:F$34,'PR Report - SINIYA'!$A$24:$A$34,$A50) -> 0 | G50: =IFERROR(E50/D50,0) -> 0 | H50: =SUMIFS('PR Report - DOWNTOWN'!H$25:H$35,'PR Report - DOWNTOWN'!$A$25:$A$35,$A50)+SUMIFS('PR Report - SINIYA'!H$24:H$34,'PR Report - SINIYA'!$A$24:$A$34,$A50) -> 40000 | I50: =SUMIFS('PR Report - DOWNTOWN'!I$25:I$35,'PR Report - DOWNTOWN'!$A$25:$A$35,$A50)+SUMIFS('PR Report - SINIYA'!I$24:I$34,'PR Report - SINIYA'!$A$24:$A$34,$A50) -> 674242
A51: UAQ Sub Total | B51: =SUM(B39:B50) -> 0 | C51: =SUM(C39:C50) -> 3063784 | D51: =SUM(D39:D50) -> 0 | E51: =SUM(E39:E50) -> 8413226 | F51: =SUM(F39:F50) -> 0 | G51: =IFERROR(E51/D51,0) -> 0 | H51: =SUM(H39:H50) -> 4055570.9 | I51: =SUM(I39:I50) -> 2004144.7
A52: Abdulla | B52: =SUMIFS('PR Report - SOBHA '!B$29:B$40,'PR Report - SOBHA '!$A$29:$A$40,$A52) -> 0 | C52: =SUMIFS('PR Report - SOBHA '!C$29:C$40,'PR Report - SOBHA '!$A$29:$A$40,$A52) -> 1000000 | D52: =SUMIFS('PR Report - SOBHA '!D$29:D$40,'PR Report - SOBHA '!$A$29:$A$40,$A52) -> 0 | E52: =SUMIFS('PR Report - SOBHA '!E$29:E$40,'PR Report - SOBHA '!$A$29:$A$40,$A52) -> 4310770 | F52: =SUMIFS('PR Report - SOBHA '!F$29:F$40,'PR Report - SOBHA '!$A$29:$A$40,$A52) -> 0 | G52: =IFERROR(E52/D52,0) -> 0 | H52: =SUMIFS('PR Report - SOBHA '!$H$29:$H$40,'PR Report - SOBHA '!$A$29:$A$40,$A52) -> 3073221 | I52: =SUMIFS('PR Report - SOBHA '!$I$29:$I$40,'PR Report - SOBHA '!$A$29:$A$40,$A52) -> 1563457
A53: Ateev | B53: =SUMIFS('PR Report - SOBHA '!B$29:B$40,'PR Report - SOBHA '!$A$29:$A$40,$A53) -> 0 | C53: =SUMIFS('PR Report - SOBHA '!C$29:C$40,'PR Report - SOBHA '!$A$29:$A$40,$A53) -> 2511878 | D53: =SUMIFS('PR Report - SOBHA '!D$29:D$40,'PR Report - SOBHA '!$A$29:$A$40,$A53) -> 0 | E53: =SUMIFS('PR Report - SOBHA '!E$29:E$40,'PR Report - SOBHA '!$A$29:$A$40,$A53) -> 11913055 | F53: =SUMIFS('PR Report - SOBHA '!F$29:F$40,'PR Report - SOBHA '!$A$29:$A$40,$A53) -> 0 | G53: =IFERROR(E53/D53,0) -> 0 | H53: =SUMIFS('PR Report - SOBHA '!$H$29:$H$40,'PR Report - SOBHA '!$A$29:$A$40,$A53) -> 9493591 | I53: =SUMIFS('PR Report - SOBHA '!$I$29:$I$40,'PR Report - SOBHA '!$A$29:$A$40,$A53) -> 3599020
A54: Ayari | B54: =SUMIFS('PR Report - SOBHA '!B$29:B$40,'PR Report - SOBHA '!$A$29:$A$40,$A54) -> 0 | C54: =SUMIFS('PR Report - SOBHA '!C$29:C$40,'PR Report - SOBHA '!$A$29:$A$40,$A54) -> 1000000 | D54: =SUMIFS('PR Report - SOBHA '!D$29:D$40,'PR Report - SOBHA '!$A$29:$A$40,$A54) -> 0 | E54: =SUMIFS('PR Report - SOBHA '!E$29:E$40,'PR Report - SOBHA '!$A$29:$A$40,$A54) -> 6358613 | F54: =SUMIFS('PR Report - SOBHA '!F$29:F$40,'PR Report - SOBHA '!$A$29:$A$40,$A54) -> 0 | G54: =IFERROR(E54/D54,0) -> 0 | H54: =SUMIFS('PR Report - SOBHA '!$H$29:$H$40,'PR Report - SOBHA '!$A$29:$A$40,$A54) -> 5456392.9 | I54: =SUMIFS('PR Report - SOBHA '!$I$29:$I$40,'PR Report - SOBHA '!$A$29:$A$40,$A54) -> 973340
A55: Nischitha | B55: =SUMIFS('PR Report - SOBHA '!B$29:B$40,'PR Report - SOBHA '!$A$29:$A$40,$A55) -> 0 | C55: =SUMIFS('PR Report - SOBHA '!C$29:C$40,'PR Report - SOBHA '!$A$29:$A$40,$A55) -> 0 | D55: =SUMIFS('PR Report - SOBHA '!D$29:D$40,'PR Report - SOBHA '!$A$29:$A$40,$A55) -> 0 | E55: =SUMIFS('PR Report - SOBHA '!E$29:E$40,'PR Report - SOBHA '!$A$29:$A$40,$A55) -> 0 | F55: =SUMIFS('PR Report - SOBHA '!F$29:F$40,'PR Report - SOBHA '!$A$29:$A$40,$A55) -> 0 | G55: =IFERROR(E55/D55,0) -> 0 | H55: =SUMIFS('PR Report - SOBHA '!$H$29:$H$40,'PR Report - SOBHA '!$A$29:$A$40,$A55) -> 0 | I55: =SUMIFS('PR Report - SOBHA '!$I$29:$I$40,'PR Report - SOBHA '!$A$29:$A$40,$A55) -> 0
A56: Sherif | B56: =SUMIFS('PR Report - SOBHA '!B$29:B$40,'PR Report - SOBHA '!$A$29:$A$40,$A56) -> 0 | C56: =SUMIFS('PR Report - SOBHA '!C$29:C$40,'PR Report - SOBHA '!$A$29:$A$40,$A56) -> 637266 | D56: =SUMIFS('PR Report - SOBHA '!D$29:D$40,'PR Report - SOBHA '!$A$29:$A$40,$A56) -> 0 | E56: =SUMIFS('PR Report - SOBHA '!E$29:E$40,'PR Report - SOBHA '!$A$29:$A$40,$A56) -> 2560947 | F56: =SUMIFS('PR Report - SOBHA '!F$29:F$40,'PR Report - SOBHA '!$A$29:$A$40,$A56) -> 0 | G56: =IFERROR(E56/D56,0) -> 0 | H56: =SUMIFS('PR Report - SOBHA '!$H$29:$H$40,'PR Report - SOBHA '!$A$29:$A$40,$A56) -> 4680292.4 | I56: =SUMIFS('PR Report - SOBHA '!$I$29:$I$40,'PR Report - SOBHA '!$A$29:$A$40,$A56) -> 840912
A57: Vijay | B57: =SUMIFS('PR Report - SOBHA '!B$29:B$40,'PR Report - SOBHA '!$A$29:$A$40,$A57) -> 0 | C57: =SUMIFS('PR Report - SOBHA '!C$29:C$40,'PR Report - SOBHA '!$A$29:$A$40,$A57) -> 1000129 | D57: =SUMIFS('PR Report - SOBHA '!D$29:D$40,'PR Report - SOBHA '!$A$29:$A$40,$A57) -> 0 | E57: =SUMIFS('PR Report - SOBHA '!E$29:E$40,'PR Report - SOBHA '!$A$29:$A$40,$A57) -> 4302140 | F57: =SUMIFS('PR Report - SOBHA '!F$29:F$40,'PR Report - SOBHA '!$A$29:$A$40,$A57) -> 0 | G57: =IFERROR(E57/D57,0) -> 0 | H57: =SUMIFS('PR Report - SOBHA '!$H$29:$H$40,'PR Report - SOBHA '!$A$29:$A$40,$A57) -> 1589332 | I57: =SUMIFS('PR Report - SOBHA '!$I$29:$I$40,'PR Report - SOBHA '!$A$29:$A$40,$A57) -> 900324
A58: Wael | B58: =SUMIFS('PR Report - SOBHA '!B$29:B$40,'PR Report - SOBHA '!$A$29:$A$40,$A58) -> 0 | C58: =SUMIFS('PR Report - SOBHA '!C$29:C$40,'PR Report - SOBHA '!$A$29:$A$40,$A58) -> 1000136.4 | D58: =SUMIFS('PR Report - SOBHA '!D$29:D$40,'PR Report - SOBHA '!$A$29:$A$40,$A58) -> 0 | E58: =SUMIFS('PR Report - SOBHA '!E$29:E$40,'PR Report - SOBHA '!$A$29:$A$40,$A58) -> 6750186 | F58: =SUMIFS('PR Report - SOBHA '!F$29:F$40,'PR Report - SOBHA '!$A$29:$A$40,$A58) -> 0 | G58: =IFERROR(E58/D58,0) -> 0 | H58: =SUMIFS('PR Report - SOBHA '!$H$29:$H$40,'PR Report - SOBHA '!$A$29:$A$40,$A58) -> 3920238 | I58: =SUMIFS('PR Report - SOBHA '!$I$29:$I$40,'PR Report - SOBHA '!$A$29:$A$40,$A58) -> 2292038.6
A59: Yogesh | B59: =SUMIFS('PR Report - SOBHA '!B$29:B$40,'PR Report - SOBHA '!$A$29:$A$40,$A59) -> 0 | C59: =SUMIFS('PR Report - SOBHA '!C$29:C$40,'PR Report - SOBHA '!$A$29:$A$40,$A59) -> 683324 | D59: =SUMIFS('PR Report - SOBHA '!D$29:D$40,'PR Report - SOBHA '!$A$29:$A$40,$A59) -> 0 | E59: =SUMIFS('PR Report - SOBHA '!E$29:E$40,'PR Report - SOBHA '!$A$29:$A$40,$A59) -> 1369006 | F59: =SUMIFS('PR Report - SOBHA '!F$29:F$40,'PR Report - SOBHA '!$A$29:$A$40,$A59) -> 0 | G59: =IFERROR(E59/D59,0) -> 0 | H59: =SUMIFS('PR Report - SOBHA '!$H$29:$H$40,'PR Report - SOBHA '!$A$29:$A$40,$A59) -> 1237047 | I59: =SUMIFS('PR Report - SOBHA '!$I$29:$I$40,'PR Report - SOBHA '!$A$29:$A$40,$A59) -> 0
A60: Noha | B60: =SUMIFS('PR Report - SOBHA '!B$29:B$40,'PR Report - SOBHA '!$A$29:$A$40,$A60) -> 0 | C60: =SUMIFS('PR Report - SOBHA '!C$29:C$40,'PR Report - SOBHA '!$A$29:$A$40,$A60) -> 586308 | D60: =SUMIFS('PR Report - SOBHA '!D$29:D$40,'PR Report - SOBHA '!$A$29:$A$40,$A60) -> 0 | E60: =SUMIFS('PR Report - SOBHA '!E$29:E$40,'PR Report - SOBHA '!$A$29:$A$40,$A60) -> 4823726.6 | F60: =SUMIFS('PR Report - SOBHA '!F$29:F$40,'PR Report - SOBHA '!$A$29:$A$40,$A60) -> 0 | G60: =IFERROR(E60/D60,0) -> 0 | H60: =SUMIFS('PR Report - SOBHA '!$H$29:$H$40,'PR Report - SOBHA '!$A$29:$A$40,$A60) -> 2924662.7 | I60: =SUMIFS('PR Report - SOBHA '!$I$29:$I$40,'PR Report - SOBHA '!$A$29:$A$40,$A60) -> 1032657.9
A61: Jaidev | B61: =SUMIFS('PR Report - SOBHA '!B$29:B$40,'PR Report - SOBHA '!$A$29:$A$40,$A61) -> 0 | C61: =SUMIFS('PR Report - SOBHA '!C$29:C$40,'PR Report - SOBHA '!$A$29:$A$40,$A61) -> 1844238 | D61: =SUMIFS('PR Report - SOBHA '!D$29:D$40,'PR Report - SOBHA '!$A$29:$A$40,$A61) -> 0 | E61: =SUMIFS('PR Report - SOBHA '!E$29:E$40,'PR Report - SOBHA '!$A$29:$A$40,$A61) -> 5408647.5 | F61: =SUMIFS('PR Report - SOBHA '!F$29:F$40,'PR Report - SOBHA '!$A$29:$A$40,$A61) -> 0 | G61: =IFERROR(E61/D61,0) -> 0 | H61: =SUMIFS('PR Report - SOBHA '!$H$29:$H$40,'PR Report - SOBHA '!$A$29:$A$40,$A61) -> 3730663.7 | I61: =SUMIFS('PR Report - SOBHA '!$I$29:$I$40,'PR Report - SOBHA '!$A$29:$A$40,$A61) -> 1672212
A62: Basma | B62: =SUMIFS('PR Report - SOBHA '!B$29:B$40,'PR Report - SOBHA '!$A$29:$A$40,$A62) -> 0 | C62: =SUMIFS('PR Report - SOBHA '!C$29:C$40,'PR Report - SOBHA '!$A$29:$A$40,$A62) -> 1477391 | D62: =SUMIFS('PR Report - SOBHA '!D$29:D$40,'PR Report - SOBHA '!$A$29:$A$40,$A62) -> 0 | E62: =SUMIFS('PR Report - SOBHA '!E$29:E$40,'PR Report - SOBHA '!$A$29:$A$40,$A62) -> 9515613 | F62: =SUMIFS('PR Report - SOBHA '!F$29:F$40,'PR Report - SOBHA '!$A$29:$A$40,$A62) -> 0 | G62: =IFERROR(E62/D62,0) -> 0 | H62: =SUMIFS('PR Report - SOBHA '!$H$29:$H$40,'PR Report - SOBHA '!$A$29:$A$40,$A62) -> 7291361 | I62: =SUMIFS('PR Report - SOBHA '!$I$29:$I$40,'PR Report - SOBHA '!$A$29:$A$40,$A62) -> 7149935.5
A63: Krizia | B63: =SUMIFS('PR Report - SOBHA '!B$29:B$40,'PR Report - SOBHA '!$A$29:$A$40,$A63) -> 0 | C63: =SUMIFS('PR Report - SOBHA '!C$29:C$40,'PR Report - SOBHA '!$A$29:$A$40,$A63) -> 0 | D63: =SUMIFS('PR Report - SOBHA '!D$29:D$40,'PR Report - SOBHA '!$A$29:$A$40,$A63) -> 0 | E63: =SUMIFS('PR Report - SOBHA '!E$29:E$40,'PR Report - SOBHA '!$A$29:$A$40,$A63) -> 1143453.6 | F63: =SUMIFS('PR Report - SOBHA '!F$29:F$40,'PR Report - SOBHA '!$A$29:$A$40,$A63) -> 0 | G63: =IFERROR(E63/D63,0) -> 0 | H63: =SUMIFS('PR Report - SOBHA '!$H$29:$H$40,'PR Report - SOBHA '!$A$29:$A$40,$A63) -> 561470 | I63: =SUMIFS('PR Report - SOBHA '!$I$29:$I$40,'PR Report - SOBHA '!$A$29:$A$40,$A63) -> 860483.56
A64: SOBHA Sub Total | B64: =SUM(B52:B63) -> 0 | C64: =SUM(C52:C63) -> 11740670 | D64: =SUM(D52:D63) -> 0 | E64: =SUM(E52:E63) -> 58456158 | F64: =SUM(F52:F63) -> 0 | G64: =IFERROR(E64/D64,0) -> 0 | H64: =SUM(H52:H63) -> 43958272 | I64: =SUM(I52:I63) -> 20884381
A65: Sherif | B65: =SUMIFS('PR Report - SOBHA AUH'!$B$24:$B$34,'PR Report - SOBHA AUH'!$A$24:$A$34,$A65) -> 0 | C65: =SUMIFS('PR Report - SOBHA AUH'!$C$24:$C$34,'PR Report - SOBHA AUH'!$A$24:$A$34,$A65) -> 30000 | D65: =SUMIFS('PR Report - SOBHA AUH'!$D$24:$D$34,'PR Report - SOBHA AUH'!$A$24:$A$34,$A65) -> 0 | E65: =SUMIFS('PR Report - SOBHA AUH'!$E$24:$E$34,'PR Report - SOBHA AUH'!$A$24:$A$34,$A65) -> 1253891 | F65: =SUMIFS('PR Report - SOBHA AUH'!$F$24:$F$34,'PR Report - SOBHA AUH'!$A$24:$A$34,$A65) -> 0 | G65: =IFERROR(E65/D65,0) -> 0 | H65: =SUMIFS('PR Report - SOBHA AUH'!$H$24:$H$34,'PR Report - SOBHA AUH'!$A$24:$A$34,$A65) -> 782197.82 | I65: =SUMIFS('PR Report - SOBHA AUH'!$I$24:$I$34,'PR Report - SOBHA AUH'!$A$24:$A$34,$A65) -> 55000
A66: Noha | B66: =SUMIFS('PR Report - SOBHA AUH'!$B$24:$B$34,'PR Report - SOBHA AUH'!$A$24:$A$34,$A66) -> 0 | C66: =SUMIFS('PR Report - SOBHA AUH'!$C$24:$C$34,'PR Report - SOBHA AUH'!$A$24:$A$34,$A66) -> 0 | D66: =SUMIFS('PR Report - SOBHA AUH'!$D$24:$D$34,'PR Report - SOBHA AUH'!$A$24:$A$34,$A66) -> 0 | E66: =SUMIFS('PR Report - SOBHA AUH'!$E$24:$E$34,'PR Report - SOBHA AUH'!$A$24:$A$34,$A66) -> 0 | F66: =SUMIFS('PR Report - SOBHA AUH'!$F$24:$F$34,'PR Report - SOBHA AUH'!$A$24:$A$34,$A66) -> 0 | G66: =IFERROR(E66/D66,0) -> 0 | H66: =SUMIFS('PR Report - SOBHA AUH'!$H$24:$H$34,'PR Report - SOBHA AUH'!$A$24:$A$34,$A66) -> 0 | I66: =SUMIFS('PR Report - SOBHA AUH'!$I$24:$I$34,'PR Report - SOBHA AUH'!$A$24:$A$34,$A66) -> 0
A67: SOBHA AUH Sub Total | B67: =SUM(B65:B66) -> 0 | C67: =SUM(C65:C66) -> 30000 | D67: =SUM(D65:D66) -> 0 | E67: =SUM(E65:E66) -> 1253891 | F67: =SUM(F65:F66) -> 0 | G67: =SUM(G65:G66) -> 0 | H67: =SUM(H65:H66) -> 782197.82 | I67: =SUM(I65:I66) -> 55000
A68: Total Advances | B68: =SUM(B64,B51,B67) -> 0 | C68: =SUM(C64,C51,C67) -> 14834454 | D68: =SUM(D64,D51,D67) -> 0 | E68: =SUM(E64,E51,E67) -> 68123275 | F68: =SUM(F64,F51,F67) -> 0 | G68: =SUM(G64,G51,G67) -> 0 | H68: =SUM(H64,H51,H67) -> 48796040 | I68: =SUM(I64,I51,I67) -> 22943525
A69: Grand Total | B69: =SUM(B37,B68) -> 61723359 | C69: =SUM(C37,C68) -> 56771371 | D69: =SUM(D37,D68) -> 3.086168e+08 | E69: =SUM(E37,E68) -> 2.8545707e+08 | F69: =SUM(F37,F68) -> 1049297104 | G69: =IFERROR(E69/D69,0) -> 0.92495636 | H69: =SUM(H37,H68) -> 2.0426916e+08 | I69: =SUM(I37,I68) -> 1.4872212e+08
A71: Total
A72: Collection Executive | B72: Not Approved | C72: In Process | D72: Resubmitted | E72: Rejected
A73: Dues
A74: Ali | B74: =SUMIFS('PR Report - SOBHA '!$B$48:$B$70,'PR Report - SOBHA '!$A$48:$A$70,A74) -> 5003503.6 | C74: =SUMIFS('PR Report - SOBHA '!$C$48:$C$70,'PR Report - SOBHA '!$A$48:$A$70,$A74) -> 1911450.8 | D74: =SUMIFS('PR Report - SOBHA '!$D$48:$D$70,'PR Report - SOBHA '!$A$48:$A$70,$A74) -> 1035336 | E74: =SUMIFS('PR Report - SOBHA '!$E$48:$E$70,'PR Report - SOBHA '!$A$48:$A$70,$A74) -> 2056716.9
A75: Anirudh | B75: =SUMIFS('PR Report - SOBHA '!$B$48:$B$70,'PR Report - SOBHA '!$A$48:$A$70,A75) -> 4572457 | C75: =SUMIFS('PR Report - SOBHA '!$C$48:$C$70,'PR Report - SOBHA '!$A$48:$A$70,$A75) -> 1415573 | D75: =SUMIFS('PR Report - SOBHA '!$D$48:$D$70,'PR Report - SOBHA '!$A$48:$A$70,$A75) -> 388254 | E75: =SUMIFS('PR Report - SOBHA '!$E$48:$E$70,'PR Report - SOBHA '!$A$48:$A$70,$A75) -> 2768630
A76: Ruhul | B76: =SUMIFS('PR Report - SOBHA '!$B$48:$B$70,'PR Report - SOBHA '!$A$48:$A$70,A76) -> 4238208.5 | C76: =SUMIFS('PR Report - SOBHA '!$C$48:$C$70,'PR Report - SOBHA '!$A$48:$A$70,$A76) -> 1282474.4 | D76: =SUMIFS('PR Report - SOBHA '!$D$48:$D$70,'PR Report - SOBHA '!$A$48:$A$70,$A76) -> 2552809.1 | E76: =SUMIFS('PR Report - SOBHA '!$E$48:$E$70,'PR Report - SOBHA '!$A$48:$A$70,$A76) -> 402925
A77: Karan | B77: =SUMIFS('PR Report - SOBHA '!$B$48:$B$70,'PR Report - SOBHA '!$A$48:$A$70,A77) -> 2640605.4 | C77: =SUMIFS('PR Report - SOBHA '!$C$48:$C$70,'PR Report - SOBHA '!$A$48:$A$70,$A77) -> 819291.03 | D77: =SUMIFS('PR Report - SOBHA '!$D$48:$D$70,'PR Report - SOBHA '!$A$48:$A$70,$A77) -> 331587 | E77: =SUMIFS('PR Report - SOBHA '!$E$48:$E$70,'PR Report - SOBHA '!$A$48:$A$70,$A77) -> 1489727.4
A78: Aqsa | B78: =SUMIFS('PR Report - SOBHA '!$B$48:$B$70,'PR Report - SOBHA '!$A$48:$A$70,A78) -> 4216231.3 | C78: =SUMIFS('PR Report - SOBHA '!$C$48:$C$70,'PR Report - SOBHA '!$A$48:$A$70,$A78) -> 527326 | D78: =SUMIFS('PR Report - SOBHA '!$D$48:$D$70,'PR Report - SOBHA '!$A$48:$A$70,$A78) -> 481716 | E78: =SUMIFS('PR Report - SOBHA '!$E$48:$E$70,'PR Report - SOBHA '!$A$48:$A$70,$A78) -> 3207189.3
A79: Sabah | B79: =SUMIFS('PR Report - SOBHA '!$B$48:$B$70,'PR Report - SOBHA '!$A$48:$A$70,A79) -> 3034882.1 | C79: =SUMIFS('PR Report - SOBHA '!$C$48:$C$70,'PR Report - SOBHA '!$A$48:$A$70,$A79) -> 630995 | D79: =SUMIFS('PR Report - SOBHA '!$D$48:$D$70,'PR Report - SOBHA '!$A$48:$A$70,$A79) -> 919602.54 | E79: =SUMIFS('PR Report - SOBHA '!$E$48:$E$70,'PR Report - SOBHA '!$A$48:$A$70,$A79) -> 1484284.6
A80: Daria | B80: =SUMIFS('PR Report - SOBHA '!$B$48:$B$70,'PR Report - SOBHA '!$A$48:$A$70,A80) -> 1980461.2 | C80: =SUMIFS('PR Report - SOBHA '!$C$48:$C$70,'PR Report - SOBHA '!$A$48:$A$70,$A80) -> 251525 | D80: =SUMIFS('PR Report - SOBHA '!$D$48:$D$70,'PR Report - SOBHA '!$A$48:$A$70,$A80) -> 621644 | E80: =SUMIFS('PR Report - SOBHA '!$E$48:$E$70,'PR Report - SOBHA '!$A$48:$A$70,$A80) -> 1107292.2
A81: Rajiv | B81: =SUMIFS('PR Report - SOBHA '!$B$48:$B$70,'PR Report - SOBHA '!$A$48:$A$70,A81) -> 7215187.2 | C81: =SUMIFS('PR Report - SOBHA '!$C$48:$C$70,'PR Report - SOBHA '!$A$48:$A$70,$A81) -> 6003574 | D81: =SUMIFS('PR Report - SOBHA '!$D$48:$D$70,'PR Report - SOBHA '!$A$48:$A$70,$A81) -> 682599 | E81: =SUMIFS('PR Report - SOBHA '!$E$48:$E$70,'PR Report - SOBHA '!$A$48:$A$70,$A81) -> 529014.21
A82: Abdellatif | B82: =SUMIFS('PR Report - SOBHA '!$B$48:$B$70,'PR Report - SOBHA '!$A$48:$A$70,A82) -> 3159710.7 | C82: =SUMIFS('PR Report - SOBHA '!$C$48:$C$70,'PR Report - SOBHA '!$A$48:$A$70,$A82) -> 724329.96 | D82: =SUMIFS('PR Report - SOBHA '!$D$48:$D$70,'PR Report - SOBHA '!$A$48:$A$70,$A82) -> 968272.38 | E82: =SUMIFS('PR Report - SOBHA '!$E$48:$E$70,'PR Report - SOBHA '!$A$48:$A$70,$A82) -> 1467108.4
A83: Omar | B83: =SUMIFS('PR Report - SOBHA '!$B$48:$B$70,'PR Report - SOBHA '!$A$48:$A$70,A83) -> 4744590 | C83: =SUMIFS('PR Report - SOBHA '!$C$48:$C$70,'PR Report - SOBHA '!$A$48:$A$70,$A83) -> 2706753.3 | D83: =SUMIFS('PR Report - SOBHA '!$D$48:$D$70,'PR Report - SOBHA '!$A$48:$A$70,$A83) -> 1035244 | E83: =SUMIFS('PR Report - SOBHA '!$E$48:$E$70,'PR Report - SOBHA '!$A$48:$A$70,$A83) -> 1002592.7
A84: Oksana | B84: =SUMIFS('PR Report - SOBHA '!$B$48:$B$70,'PR Report - SOBHA '!$A$48:$A$70,A84) -> 5422934.5 | C84: =SUMIFS('PR Report - SOBHA '!$C$48:$C$70,'PR Report - SOBHA '!$A$48:$A$70,$A84) -> 1362943 | D84: =SUMIFS('PR Report - SOBHA '!$D$48:$D$70,'PR Report - SOBHA '!$A$48:$A$70,$A84) -> 1145514 | E84: =SUMIFS('PR Report - SOBHA '!$E$48:$E$70,'PR Report - SOBHA '!$A$48:$A$70,$A84) -> 2914477.5
A85: Ainur | B85: =SUMIFS('PR Report - SOBHA '!$B$48:$B$70,'PR Report - SOBHA '!$A$48:$A$70,A85) -> 7925559.1 | C85: =SUMIFS('PR Report - SOBHA '!$C$48:$C$70,'PR Report - SOBHA '!$A$48:$A$70,$A85) -> 2713378 | D85: =SUMIFS('PR Report - SOBHA '!$D$48:$D$70,'PR Report - SOBHA '!$A$48:$A$70,$A85) -> 670556 | E85: =SUMIFS('PR Report - SOBHA '!$E$48:$E$70,'PR Report - SOBHA '!$A$48:$A$70,$A85) -> 4541625.1
... A91: Sid | B91: =SUMIFS('PR Report - SOBHA '!$B$48:$B$70,'PR Report - SOBHA '!$A$48:$A$70,A91) -> 2767324 | C91: =SUMIFS('PR Report - SOBHA '!$C$48:$C$70,'PR Report - SOBHA '!$A$48:$A$70,$A91) -> 140000 | D91: =SUMIFS('PR Report - SOBHA '!$D$48:$D$70,'PR Report - SOBHA '!$A$48:$A$70,$A91) -> 1535800 | E91: =SUMIFS('PR Report - SOBHA '!$E$48:$E$70,'PR Report - SOBHA '!$A$48:$A$70,$A91) -> 1091524
A92: Hussein | B92: =_xlfn.XLOOKUP(A92,'PR Report - SOBHA '!$A$48:$A$70,'PR Report - SOBHA '!$B$48:$B$70) -> 3657233.3 | C92: =SUMIFS('PR Report - SOBHA '!$C$48:$C$70,'PR Report - SOBHA '!$A$48:$A$70,$A92) -> 5574242 | D92: =SUMIFS('PR Report - SOBHA '!$D$48:$D$70,'PR Report - SOBHA '!$A$48:$A$70,$A92) -> 1090624 | E92: =SUMIFS('PR Report - SOBHA '!$E$48:$E$70,'PR Report - SOBHA '!$A$48:$A$70,$A92) -> 649600.6
A93: Moustafa | B93: =SUMIFS('PR Report - SOBHA '!$B$48:$B$70,'PR Report - SOBHA '!$A$48:$A$70,A93) -> 4581377.6 | C93: =SUMIFS('PR Report - SOBHA '!$C$48:$C$70,'PR Report - SOBHA '!$A$48:$A$70,$A93) -> 426604 | D93: =SUMIFS('PR Report - SOBHA '!$D$48:$D$70,'PR Report - SOBHA '!$A$48:$A$70,$A93) -> 1473080.8 | E93: =SUMIFS('PR Report - SOBHA '!$E$48:$E$70,'PR Report - SOBHA '!$A$48:$A$70,$A93) -> 2681692.8
A94: Nijish | B94: =SUMIFS('PR Report - SOBHA '!$B$48:$B$70,'PR Report - SOBHA '!$A$48:$A$70,A94) -> 2499807.9 | C94: =SUMIFS('PR Report - SOBHA '!$C$48:$C$70,'PR Report - SOBHA '!$A$48:$A$70,$A94) -> 405851.42 | D94: =SUMIFS('PR Report - SOBHA '!$D$48:$D$70,'PR Report - SOBHA '!$A$48:$A$70,$A94) -> 37486.79 | E94: =SUMIFS('PR Report - SOBHA '!$E$48:$E$70,'PR Report - SOBHA '!$A$48:$A$70,$A94) -> 2056469.7
A95: Lamis | B95: =SUMIFS('PR Report - SOBHA '!$B$48:$B$70,'PR Report - SOBHA '!$A$48:$A$70,A95) -> 8319487.2 | C95: =SUMIFS('PR Report - SOBHA '!$C$48:$C$70,'PR Report - SOBHA '!$A$48:$A$70,$A95) -> 7143566 | D95: =SUMIFS('PR Report - SOBHA '!$D$48:$D$70,'PR Report - SOBHA '!$A$48:$A$70,$A95) -> 177795 | E95: =SUMIFS('PR Report - SOBHA '!$E$48:$E$70,'PR Report - SOBHA '!$A$48:$A$70,$A95) -> 998126.19
A96: SOBHA Sub Total | B96: =SUM(B74:B95) -> 1.0721567e+08 | C96: =SUM(C74:C95) -> 43996655 | D96: =SUM(D74:D95) -> 21673520 | E96: =SUM(E74:E95) -> 45202726
A97: Anna | B97: =SUMIFS('PR Report - SINIYA'!$B$41:$B$59,'PR Report - SINIYA'!$A$41:$A$59,A97)+SUMIFS('PR Report - DOWNTOWN'!$B$42:$B$59,'PR Report - DOWNTOWN'!$A$42:$A$59,A97) -> 506236.11 | C97: =SUMIFS('PR Report - SINIYA'!$C$41:$C$59,'PR Report - SINIYA'!$A$41:$A$59,$A97)+SUMIFS('PR Report - DOWNTOWN'!$C$42:$C$59,'PR Report - DOWNTOWN'!$A$42:$A$59,$A97) -> 356236.11 | D97: =SUMIFS('PR Report - SINIYA'!$D$41:$D$59,'PR Report - SINIYA'!$A$41:$A$59,$A97)+SUMIFS('PR Report - DOWNTOWN'!$D$42:$D$59,'PR Report - DOWNTOWN'!$A$42:$A$59,$A97) -> 0 | E97: =SUMIFS('PR Report - SINIYA'!$E$41:$E$59,'PR Report - SINIYA'!$A$41:$A$59,$A97)+SUMIFS('PR Report - DOWNTOWN'!$E$42:$E$59,'PR Report - DOWNTOWN'!$A$42:$A$59,$A97) -> 150000
A98: Monish | B98: =SUMIFS('PR Report - SINIYA'!$B$41:$B$59,'PR Report - SINIYA'!$A$41:$A$59,A98)+SUMIFS('PR Report - DOWNTOWN'!$B$42:$B$59,'PR Report - DOWNTOWN'!$A$42:$A$59,A98) -> 5676444.3 | C98: =SUMIFS('PR Report - SINIYA'!$C$41:$C$59,'PR Report - SINIYA'!$A$41:$A$59,$A98)+SUMIFS('PR Report - DOWNTOWN'!$C$42:$C$59,'PR Report - DOWNTOWN'!$A$42:$A$59,$A98) -> 1479114 | D98: =SUMIFS('PR Report - SINIYA'!$D$41:$D$59,'PR Report - SINIYA'!$A$41:$A$59,$A98)+SUMIFS('PR Report - DOWNTOWN'!$D$42:$D$59,'PR Report - DOWNTOWN'!$A$42:$A$59,$A98) -> 2199816.2 | E98: =SUMIFS('PR Report - SINIYA'!$E$41:$E$59,'PR Report - SINIYA'!$A$41:$A$59,$A98)+SUMIFS('PR Report - DOWNTOWN'!$E$42:$E$59,'PR Report - DOWNTOWN'!$A$42:$A$59,$A98) -> 1997514.2
A99: Walid | B99: =SUMIFS('PR Report - SINIYA'!$B$41:$B$59,'PR Report - SINIYA'!$A$41:$A$59,A99)+SUMIFS('PR Report - DOWNTOWN'!$B$42:$B$59,'PR Report - DOWNTOWN'!$A$42:$A$59,A99) -> 8114728.6 | C99: =SUMIFS('PR Report - SINIYA'!$C$41:$C$59,'PR Report - SINIYA'!$A$41:$A$59,$A99)+SUMIFS('PR Report - DOWNTOWN'!$C$42:$C$59,'PR Report - DOWNTOWN'!$A$42:$A$59,$A99) -> 1757706.4 | D99: =SUMIFS('PR Report - SINIYA'!$D$41:$D$59,'PR Report - SINIYA'!$A$41:$A$59,$A99)+SUMIFS('PR Report - DOWNTOWN'!$D$42:$D$59,'PR Report - DOWNTOWN'!$A$42:$A$59,$A99) -> 772083.3 | E99: =SUMIFS('PR Report - SINIYA'!$E$41:$E$59,'PR Report - SINIYA'!$A$41:$A$59,$A99)+SUMIFS('PR Report - DOWNTOWN'!$E$42:$E$59,'PR Report - DOWNTOWN'!$A$42:$A$59,$A99) -> 5584938.9
A100: Melvyn | B100: =SUMIFS('PR Report - SINIYA'!$B$41:$B$59,'PR Report - SINIYA'!$A$41:$A$59,A100)+SUMIFS('PR Report - DOWNTOWN'!$B$42:$B$59,'PR Report - DOWNTOWN'!$A$42:$A$59,A100) -> 4265516.2 | C100: =SUMIFS('PR Report - SINIYA'!$C$41:$C$59,'PR Report - SINIYA'!$A$41:$A$59,$A100)+SUMIFS('PR Report - DOWNTOWN'!$C$42:$C$59,'PR Report - DOWNTOWN'!$A$42:$A$59,$A100) -> 2545735.6 | D100: =SUMIFS('PR Report - SINIYA'!$D$41:$D$59,'PR Report - SINIYA'!$A$41:$A$59,$A100)+SUMIFS('PR Report - DOWNTOWN'!$D$42:$D$59,'PR Report - DOWNTOWN'!$A$42:$A$59,$A100) -> 416549 | E100: =SUMIFS('PR Report - SINIYA'!$E$41:$E$59,'PR Report - SINIYA'!$A$41:$A$59,$A100)+SUMIFS('PR Report - DOWNTOWN'!$E$42:$E$59,'PR Report - DOWNTOWN'!$A$42:$A$59,$A100) -> 1303231.6
A101: UAQ Sub Total | B101: =SUM(B97:B100) -> 18562925 | C101: =SUM(C97:C100) -> 6138792.1 | D101: =SUM(D97:D100) -> 3388448.5 | E101: =SUM(E97:E100) -> 9035684.7
A102: Omar | B102: =SUMIFS('PR Report - SOBHA AUH'!B$41:B$58,'PR Report - SOBHA AUH'!$A$41:$A$58,$A102) -> 0 | C102: =SUMIFS('PR Report - SOBHA AUH'!C$41:C$58,'PR Report - SOBHA AUH'!$A$41:$A$58,$A$102) -> 0 | D102: =SUMIFS('PR Report - SOBHA AUH'!D$41:D$58,'PR Report - SOBHA AUH'!$A$41:$A$58,$A$102) -> 0 | E102: =SUMIFS('PR Report - SOBHA AUH'!E$41:E$58,'PR Report - SOBHA AUH'!$A$41:$A$58,$A$102) -> 0
A103: Ruhul | B103: =SUMIFS('PR Report - SOBHA AUH'!B$41:B$58,'PR Report - SOBHA AUH'!$A$41:$A$58,$A103) -> 0 | C103: =SUMIFS('PR Report - SOBHA AUH'!C$41:C$58,'PR Report - SOBHA AUH'!$A$41:$A$58,$A103) -> 0 | D103: =SUMIFS('PR Report - SOBHA AUH'!D$41:D$58,'PR Report - SOBHA AUH'!$A$41:$A$58,$A103) -> 0 | E103: =SUMIFS('PR Report - SOBHA AUH'!E$41:E$58,'PR Report - SOBHA AUH'!$A$41:$A$58,$A103) -> 0
A104: Vinod | B104: =SUMIFS('PR Report - SOBHA AUH'!B$41:B$58,'PR Report - SOBHA AUH'!$A$41:$A$58,$A104) -> 0 | C104: =SUMIFS('PR Report - SOBHA AUH'!C$41:C$58,'PR Report - SOBHA AUH'!$A$41:$A$58,$A104) -> 0 | D104: =SUMIFS('PR Report - SOBHA AUH'!D$41:D$58,'PR Report - SOBHA AUH'!$A$41:$A$58,$A104) -> 0 | E104: =SUMIFS('PR Report - SOBHA AUH'!E$41:E$58,'PR Report - SOBHA AUH'!$A$41:$A$58,$A104) -> 0
A105: SOBHA AUH Sub Total | B105: =SUM(B102:B104) -> 0 | C105: =SUM(C102:C104) -> 0 | D105: =SUM(D102:D104) -> 0 | E105: =SUM(E102:E104) -> 0
A106: Total Dues | B106: =SUM(B101,B96,B105) -> 1.2577859e+08 | C106: =SUM(C101,C96,C105) -> 50135447 | D106: =SUM(D101,D96,D105) -> 25061968 | E106: =SUM(E101,E96,E105) -> 54238411
A107: Advances
A108: Ayari | B108: =SUMIFS('PR Report - SOBHA '!B$73:B$84,'PR Report - SOBHA '!$A$73:$A$84,$A108) -> 973340 | C108: =SUMIFS('PR Report - SOBHA '!C$74:C$84,'PR Report - SOBHA '!$A$74:$A$84,$A108) -> 0 | D108: =SUMIFS('PR Report - SOBHA '!D$74:D$84,'PR Report - SOBHA '!$A$74:$A$84,$A108) -> 0 | E108: =SUMIFS('PR Report - SOBHA '!E$74:E$84,'PR Report - SOBHA '!$A$74:$A$84,$A108) -> 0
A109: Ateev | B109: =SUMIFS('PR Report - SOBHA '!B$73:B$84,'PR Report - SOBHA '!$A$73:$A$84,$A109) -> 3599020 | C109: =SUMIFS('PR Report - SOBHA '!C$74:C$84,'PR Report - SOBHA '!$A$74:$A$84,$A109) -> 1652682 | D109: =SUMIFS('PR Report - SOBHA '!D$74:D$84,'PR Report - SOBHA '!$A$74:$A$84,$A109) -> 0 | E109: =SUMIFS('PR Report - SOBHA '!E$74:E$84,'PR Report - SOBHA '!$A$74:$A$84,$A109) -> 1946338
A110: Abdulla | B110: =SUMIFS('PR Report - SOBHA '!B$73:B$84,'PR Report - SOBHA '!$A$73:$A$84,$A110) -> 1563457 | C110: =SUMIFS('PR Report - SOBHA '!C$74:C$84,'PR Report - SOBHA '!$A$74:$A$84,$A110) -> 1563457 | D110: =SUMIFS('PR Report - SOBHA '!D$74:D$84,'PR Report - SOBHA '!$A$74:$A$84,$A110) -> 0 | E110: =SUMIFS('PR Report - SOBHA '!E$74:E$84,'PR Report - SOBHA '!$A$74:$A$84,$A110) -> 0
A111: Wael | B111: =SUMIFS('PR Report - SOBHA '!B$73:B$84,'PR Report - SOBHA '!$A$73:$A$84,$A111) -> 2292038.6 | C111: =SUMIFS('PR Report - SOBHA '!C$74:C$84,'PR Report - SOBHA '!$A$74:$A$84,$A111) -> 718079.82 | D111: =SUMIFS('PR Report - SOBHA '!D$74:D$84,'PR Report - SOBHA '!$A$74:$A$84,$A111) -> 490451.78 | E111: =SUMIFS('PR Report - SOBHA '!E$74:E$84,'PR Report - SOBHA '!$A$74:$A$84,$A111) -> 1083507
A112: Nischitha | B112: =SUMIFS('PR Report - SOBHA '!B$73:B$84,'PR Report - SOBHA '!$A$73:$A$84,$A112) -> 0 | C112: =SUMIFS('PR Report - SOBHA '!C$74:C$84,'PR Report - SOBHA '!$A$74:$A$84,$A112) -> 0 | D112: =SUMIFS('PR Report - SOBHA '!D$74:D$84,'PR Report - SOBHA '!$A$74:$A$84,$A112) -> 0 | E112: =SUMIFS('PR Report - SOBHA '!E$74:E$84,'PR Report - SOBHA '!$A$74:$A$84,$A112) -> 0
A113: Sherif | B113: =SUMIFS('PR Report - SOBHA '!B$73:B$84,'PR Report - SOBHA '!$A$73:$A$84,$A113) -> 840912 | C113: =SUMIFS('PR Report - SOBHA '!C$74:C$84,'PR Report - SOBHA '!$A$74:$A$84,$A113) -> 840912 | D113: =SUMIFS('PR Report - SOBHA '!D$74:D$84,'PR Report - SOBHA '!$A$74:$A$84,$A113) -> 0 | E113: =SUMIFS('PR Report - SOBHA '!E$74:E$84,'PR Report - SOBHA '!$A$74:$A$84,$A113) -> 0
A114: Noha | B114: =SUMIFS('PR Report - SOBHA '!B$73:B$84,'PR Report - SOBHA '!$A$73:$A$84,$A114) -> 1032657.9 | C114: =SUMIFS('PR Report - SOBHA '!C$74:C$84,'PR Report - SOBHA '!$A$74:$A$84,$A114) -> 150073.87 | D114: =SUMIFS('PR Report - SOBHA '!D$74:D$84,'PR Report - SOBHA '!$A$74:$A$84,$A114) -> 0 | E114: =SUMIFS('PR Report - SOBHA '!E$74:E$84,'PR Report - SOBHA '!$A$74:$A$84,$A114) -> 882584
A115: Krizia | B115: =SUMIFS('PR Report - SOBHA '!B$73:B$84,'PR Report - SOBHA '!$A$73:$A$84,$A115) -> 860483.56 | C115: =SUMIFS('PR Report - SOBHA '!C$74:C$84,'PR Report - SOBHA '!$A$74:$A$84,$A115) -> 133983.56 | D115: =SUMIFS('PR Report - SOBHA '!D$74:D$84,'PR Report - SOBHA '!$A$74:$A$84,$A115) -> 726500 | E115: =SUMIFS('PR Report - SOBHA '!E$74:E$84,'PR Report - SOBHA '!$A$74:$A$84,$A115) -> 0
A116: Ahmed | B116: =SUMIFS('PR Report - SOBHA '!B$73:B$84,'PR Report - SOBHA '!$A$73:$A$84,$A116) -> 0 | C116: =SUMIFS('PR Report - SOBHA '!C$74:C$84,'PR Report - SOBHA '!$A$74:$A$84,$A116) -> 0 | D116: =SUMIFS('PR Report - SOBHA '!D$74:D$84,'PR Report - SOBHA '!$A$74:$A$84,$A116) -> 0 | E116: =SUMIFS('PR Report - SOBHA '!E$74:E$84,'PR Report - SOBHA '!$A$74:$A$84,$A116) -> 0
...

Sheet PR Data
A1: Payment Request: Payment Request Name | B1: Mode | C1: Amount | D1: Booking: Unit | E1: Payment Request: Created By | F1: Status | G1: Payment Request: Created Date | H1: Booking: Booking Name | I1: Unit Purchase Amount | J1: Instrument Date | K1: Cheque Date | L1: Date of Initiation | M1: Towards Other Charges Amount | N1: Towards Pre-Registration Amount | O1: Amount Towards | P1: Net Unit Amount | Q1: Collector name | R1: Remarks | S1: paid percentage | T1: Filtering Data | U1: Project | V1: Receipt Number | W1: Receipt Status | Z1: 0.095 | AA1: 46143 | AB1: 46173 | AC1: All PR this Month Updated | Salesforce | AE1: Receipt Name | AF1: Booking: Booking Name | AG1: Project Unit: Unit Name | AH1: Opportunity: Opportunity Name | AI1: Total Amount | AJ1: Cheque Date | AK1: Receipt Status | AL1: Sub Project | AM1: Collector Name | AN1: Project | AO1: PDC - all time | AQ1: Executive | AR1: Standard Name | AS1: Executive Catgeory | AT1: Executive Post
A2: PR-0505928 | B2: Website | C2: 11302 | D2: RA-2113 | E2: Ahmed Abdellatif Mahmoud Elhanafy Shokil | F2: Rejected by System | G2: 46149 | H2: B-1368 | I2: 865048.61 | J2: 0 | K2: 0 | L2: 0 | M2: 11302 | N2: 0 | O2: 0 | P2: 0 | Q2: Abdellatif | R2: Rejected | S2: 1.0115346 | T2: Yes | U2: Sobha | V2: 0 | W2: 0 | AE2: R-920972 | AF2: B-48687 | AG2: SCY-RC-B402 | AH2: Ali Thallab Mohamed Fahad Alhajeri | AI2: 249456 | AJ2: 46144 | AK2: UnProcessed | AL2: River Cove Residences-River Cove Residences - Tower B | AM2: Ruhul | AN2: Sobha AUH | AQ2: Ahmed Abdellatif Mahmoud Elhanafy Shokil | AR2: Abdellatif | AS2: Dues | AT2: Collector
A3: PR-0502814 | B3: Website | C3: 150000 | D3: SR-V 607 | E3: Sobha One App | F3: Approved | G3: 46143 | H3: B-18187 | I3: 7797288.2 | J3: 46143 | K3: 0 | L3: 46143 | M3: 0 | N3: 0 | O3: Unit Price | P3: 150000 | Q3: Ateev | R3: Approved | S3: 0.83847494 | T3: Yes | U3: Sobha | V3: R-921120 | W3: Cleared | AE3: R-920973 | AF3: B-48687 | AG3: SCY-RC-B402 | AH3: Ali Thallab Mohamed Fahad Alhajeri | AI3: 28896 | AJ3: 46144 | AK3: UnProcessed | AL3: River Cove Residences-River Cove Residences - Tower B | AM3: Ruhul | AN3: Sobha AUH | AQ3: Ahmed Atia | AR3: Atia | AS3: Dues | AT3: Collector
A4: PR-0505402 | B4: Website | C4: 100000 | D4: SR-V 619 | E4: Hussein Moawad | F4: Approved | G4: 46148 | H4: B-21472 | I4: 9716668.8 | J4: 0 | K4: 0 | L4: 0 | M4: 0 | N4: 0 | O4: 0 | P4: 100000 | Q4: Hussein | R4: Approved | S4: 0.72060376 | T4: Yes | U4: Sobha | V4: R-923485 | W4: Cleared | AE4: R-139362 | AF4: B-17852 | AG4: 6P12 | AH4: Gayathri Potti Rajan | AI4: 41858 | AJ4: 46167 | AK4: PDC | AL4: Greens-Phase III - Building 6 | AM4: Anirudh | AN4: Sobha | AQ4: Ainur Mukanova | AR4: Ainur | AS4: Dues | AT4: Collector
A5: PR-0505390 | B5: Website | C5: 100000 | D5: SR-V 619 | E5: Hussein Moawad | F5: Rejected by System | G5: 46148 | H5: B-21472 | I5: 9716668.8 | J5: 0 | K5: 0 | L5: 0 | M5: 0 | N5: 0 | O5: 0 | P5: 100000 | Q5: Hussein | R5: Rejected | S5: 0.72060376 | T5: Yes | U5: Sobha | V5: 0 | W5: 0 | AE5: R-447320 | AF5: B-10204 | AG5: VE 138 | AH5: Azenda Real Estate LLC | AI5: 4589609 | AJ5: 46150 | AK5: PDC | AL5: Villas-Phase III | AM5: Rajiv | AN5: Sobha | AQ5: Ali Babu Shaikh | AR5: Ali | AS5: Dues | AT5: Collector
A6: PR-0506020 | B6: Website | C6: 99500 | D6: SR-V 619 | E6: Hussein Moawad | F6: Approved | G6: 46149 | H6: B-21472 | I6: 9716668.8 | J6: 0 | K6: 0 | L6: 0 | M6: 0 | N6: 0 | O6: 0 | P6: 99500 | Q6: Hussein | R6: Approved | S6: 0.72060376 | T6: Yes | U6: Sobha | V6: R-931091 | W6: Cleared | AE6: R-451660 | AF6: B-9304 | AG6: CVG-2508 | AH6: AZAT SHAIMUKHAMETOV | AI6: 227969.88 | AJ6: 46148 | AK6: PDC | AL6: Creek Vistas Grande-Creek Vistas Grande | AM6: Omar | AN6: Sobha | AQ6: Anirudh Sharma | AR6: Anirudh | AS6: Dues | AT6: Collector
A7: PR-0506019 | B7: Website | C7: 99500 | D7: SR-V 619 | E7: Hussein Moawad | F7: Rejected by System | G7: 46149 | H7: B-21472 | I7: 9716668.8 | J7: 0 | K7: 0 | L7: 0 | M7: 0 | N7: 0 | O7: 0 | P7: 99500 | Q7: Hussein | R7: Rejected | S7: 0.72060376 | T7: Yes | U7: Sobha | V7: 0 | W7: 0 | AE7: R-451715 | AF7: B-10585 | AG7: CVG-1805 | AH7: AZAT SHAIMUKHAMETOV- CVG1805 | AI7: 197346.28 | AJ7: 46148 | AK7: PDC | AL7: Creek Vistas Grande-Creek Vistas Grande | AM7: Omar | AN7: Sobha | AQ7: Aqsa Rahman | AR7: Aqsa | AS7: Dues | AT7: Collector
A8: PR-0502901 | B8: Website | C8: 19700 | D8: SO-A814 | E8: Abdulabid Chiralakandy | F8: Rejected by System | G8: 46143 | H8: B-28335 | I8: 1594890 | J8: 0 | K8: 0 | L8: 0 | M8: 0 | N8: 0 | O8: 0 | P8: 19700 | Q8: Wael | R8: Rejected | S8: 0.67757024 | T8: Yes | U8: Sobha | V8: 0 | W8: 0 | AE8: R-459338 | AF8: B-8965 | AG8: CVG-2401 | AH8: SUBHI KANAWATI | AI8: 299906 | AJ8: 46148 | AK8: PDC | AL8: Creek Vistas Grande-Creek Vistas Grande | AM8: Omar | AN8: Sobha | AQ8: Daria Lisovets | AR8: Daria | AS8: Dues | AT8: Collector
A9: PR-0502900 | B9: Website | C9: 19700 | D9: SO-A814 | E9: Abdulabid Chiralakandy | F9: Rejected by System | G9: 46143 | H9: B-28335 | I9: 1594890 | J9: 0 | K9: 0 | L9: 0 | M9: 0 | N9: 0 | O9: 0 | P9: 19700 | Q9: Wael | R9: Rejected | S9: 0.67757024 | T9: Yes | U9: Sobha | V9: 0 | W9: 0 | AE9: R-463887 | AF9: B-9033 | AG9: CVG-2404 | AH9: Itsaiva Pacome CVG-2404 | AI9: 139519 | AJ9: 46148 | AK9: PDC | AL9: Creek Vistas Grande-Creek Vistas Grande | AM9: Omar | AN9: Sobha | AQ9: Farheen Parveen | AR9: Farheen | AS9: Dues | AT9: Collector
A10: PR-0502954 | B10: Website | C10: 19700 | D10: SO-A814 | E10: Abdulabid Chiralakandy | F10: Approved | G10: 46143 | H10: B-28335 | I10: 1594890 | J10: 0 | K10: 0 | L10: 0 | M10: 0 | N10: 0 | O10: 0 | P10: 19700 | Q10: Wael | R10: Approved | S10: 0.67757024 | T10: Yes | U10: Sobha | V10: R-921258 | W10: Cleared | AE10: R-463898 | AF10: B-9023 | AG10: CVG-2003 | AH10: Itsaiva Pacome | AI10: 134753.41 | AJ10: 46148 | AK10: PDC | AL10: Creek Vistas Grande-Creek Vistas Grande | AM10: Omar | AN10: Sobha | AQ10: Hussein Moawad | AR10: Hussein | AS10: Dues | AT10: Collector
A11: PR-0502952 | B11: Website | C11: 19700 | D11: SO-A814 | E11: Abdulabid Chiralakandy | F11: Rejected by System | G11: 46143 | H11: B-28335 | I11: 1594890 | J11: 0 | K11: 0 | L11: 0 | M11: 0 | N11: 0 | O11: 0 | P11: 19700 | Q11: Wael | R11: Rejected | S11: 0.67757024 | T11: Yes | U11: Sobha | V11: 0 | W11: 0 | AE11: R-466985 | AF11: B-9987 | AG11: CVG-3007 | AH11: Andrey Luntovskiy | AI11: 228393 | AJ11: 46148 | AK11: PDC | AL11: Creek Vistas Grande-Creek Vistas Grande | AM11: Omar | AN11: Sobha | AQ11: Karan Bhatia | AR11: Karan | AS11: Dues | AT11: Collector
A12: PR-0503500 | B12: Website | C12: 79750 | D12: SO-A815 | E12: Abdulabid Chiralakandy | F12: Approved | G12: 46145 | H12: B-33555 | I12: 1594890 | J12: 0 | K12: 0 | L12: 0 | M12: 0 | N12: 0 | O12: 0 | P12: 79750 | Q12: Omar | R12: Approved | S12: 0.5 | T12: Yes | U12: Sobha | V12: R-921501 | W12: Cleared | AE12: R-470117 | AF12: B-8690 | AG12: CVG-1910 | AH12: Samy Talaat Barakat | AI12: 148006 | AJ12: 46148 | AK12: PDC | AL12: Creek Vistas Grande-Creek Vistas Grande | AM12: Omar | AN12: Sobha | AQ12: Lamis Amamra | AR12: Lamis | AS12: Dues | AT12: Collector
A13: PR-0504284 | B13: Website | C13: 79739 | D13: SO-A815 | E13: Abdulabid Chiralakandy | F13: Approved | G13: 46146 | H13: B-33555 | I13: 1594890 | J13: 0 | K13: 0 | L13: 0 | M13: 0 | N13: 0 | O13: 0 | P13: 79739 | Q13: Omar | R13: Approved | S13: 0.5 | T13: Yes | U13: Sobha | V13: R-922284 | W13: Cleared | AE13: R-470590 | AF13: B-10970 | AG13: CVG-805 | AH13: Ms. Tanya Jain Sanjiv Kumar Jain | AI13: 197346.28 | AJ13: 46148 | AK13: PDC | AL13: Creek Vistas Grande-Creek Vistas Grande | AM13: Omar | AN13: Sobha | AQ13: Moustafa Ahmed Zaky Mohamed Attallah | AR13: Moustafa | AS13: Dues | AT13: Collector
A14: PR-0502756 | B14: DWT(Domestic) | C14: 161663 | D14: SO-A2213 | E14: Omar Elsayed Mohamed Rezk Shanab | F14: Approved | G14: 46143 | H14: B-32807 | I14: 1616638.5 | J14: 0 | K14: 0 | L14: 46142 | M14: 0 | N14: 0 | O14: 0 | P14: 161663 | Q14: Omar | R14: Approved | S14: 0.39999975 | T14: Yes | U14: Sobha | V14: R-922225 | W14: Cleared | AE14: R-470529 | AF14: B-9176 | AG14: CVG-3301 | AH14: VLADIMIR VOLKOV - CVG-3301 | AI14: 304015 | AJ14: 46148 | AK14: PDC | AL14: Creek Vistas Grande-Creek Vistas Grande | AM14: Omar | AN14: Sobha | AQ14: Oksana Stepanenko | AR14: Oksana | AS14: Dues | AT14: Collector
A15: PR-0505941 | B15: DWT(Domestic) | C15: 100000 | D15: SO-B1516 | E15: Sobha One App | F15: Pending for Accounts Approval | G15: 46149 | H15: B-33407 | I15: 1667638 | J15: 46149 | K15: 0 | L15: 46149 | M15: 0 | N15: 0 | O15: Unit Price | P15: 100000 | Q15: Oksana | R15: In process | S15: 0.3 | T15: Yes | U15: Sobha | V15: 0 | W15: 0 | AE15: R-470553 | AF15: B-12085 | AG15: CVG-906 | AH15: Mr. Mahad Dayib Khalif | AI15: 151911 | AJ15: 46148 | AK15: PDC | AL15: Creek Vistas Grande-Creek Vistas Grande | AM15: Omar | AN15: Sobha | AQ15: Omar Elsayed Mohamed Rezk Shanab | AR15: Omar | AS15: Dues | AT15: Collector
A16: PR-0504186 | B16: DWT(Domestic) | C16: 172969 | D16: SO-B3917 | E16: Oksana Stepanenko | F16: Resubmitted to SM/SD | G16: 46146 | H16: B-34010 | I16: 1729688.8 | J16: 0 | K16: 0 | L16: 46136 | M16: 0 | N16: 0 | O16: 0 | P16: 172969 | Q16: Oksana | R16: Resubmitted | S16: 0.40000017 | T16: Yes | U16: Sobha | V16: 0 | W16: 0 | AE16: R-470666 | AF16: B-10008 | AG16: CVG-3001 | AH16: Modern Living-CVG3001 | AI16: 299906 | AJ16: 46148 | AK16: PDC | AL16: Creek Vistas Grande-Creek Vistas Grande | AM16: Omar | AN16: Sobha | AQ16: Rajiv Singh | AR16: Rajiv | AS16: Dues | AT16: Collector
A17: PR-0503017 | B17: DWT(Domestic) | C17: 174062.07 | D17: SO-B4117 | E17: Sobha One App | F17: Approved | G17: 46143 | H17: B-33456 | I17: 1740613.1 | J17: 46143 | K17: 0 | L17: 46143 | M17: 0 | N17: 0 | O17: Unit Price | P17: 174062.07 | Q17: Oksana | R17: Approved | S17: 0.40000044 | T17: Yes | U17: Sobha | V17: R-922472 | W17: Cleared | AE17: R-470667 | AF17: B-10004 | AG17: CVG-3605 | AH17: Modern Living-CVG3605 | AI17: 202906 | AJ17: 46148 | AK17: PDC | AL17: Creek Vistas Grande-Creek Vistas Grande | AM17: Omar | AN17: Sobha | AQ17: Ruhul Amin | AR17: Ruhul | AS17: Dues | AT17: Collector
A18: PR-0503253 | B18: DWT(Domestic) | C18: 175702 | D18: SO-B1016 | E18: Sobha One App | F18: Resubmitted to SM/SD | G18: 46144 | H18: B-40377 | I18: 1757016 | J18: 46144 | K18: 0 | L18: 46144 | M18: 0 | N18: 0 | O18: Unit Price | P18: 175702 | Q18: Oksana | R18: Resubmitted | S18: 0.40000034 | T18: Yes | U18: Sobha | V18: 0 | W18: 0 | AE18: R-470668 | AF18: B-10006 | AG18: CVG-3607 | AH18: Modern Living-CVG3607 | AI18: 231565 | AJ18: 46148 | AK18: PDC | AL18: Creek Vistas Grande-Creek Vistas Grande | AM18: Omar | AN18: Sobha | AQ18: Sabah Anis | AR18: Sabah | AS18: Dues | AT18: Collector
A19: PR-0504587 | B19: DWT(Domestic) | C19: 175702 | D19: SO-B1016 | E19: Oksana Stepanenko | F19: Resubmitted to SM/SD | G19: 46147 | H19: B-40377 | I19: 1757016 | J19: 0 | K19: 0 | L19: 46144 | M19: 0 | N19: 0 | O19: 0 | P19: 175702 | Q19: Oksana | R19: Resubmitted | S19: 0.40000034 | T19: Yes | U19: Sobha | V19: 0 | W19: 0 | AE19: R-471019 | AF19: B-8652 | AG19: CVG-2409 | AH19: SHILPA SHETTY | AI19: 142243 | AJ19: 46148 | AK19: PDC | AL19: Creek Vistas Grande-Creek Vistas Grande | AM19: Omar | AN19: Sobha | AQ19: Sarmad Zia | AR19: Sarmad | AS19: Dues | AT19: Collector
A20: PR-0504439 | B20: IWT(International) | C20: 21000 | D20: SO-B2120 | E20: Oksana Stepanenko | F20: Approved | G20: 46147 | H20: B-21686 | I20: 2678347.2 | J20: 0 | K20: 0 | L20: 46146 | M20: 0 | N20: 0 | O20: 0 | P20: 21000 | Q20: Oksana | R20: Approved | S20: 0.5181003 | T20: Yes | U20: Sobha | V20: R-923439 | W20: Cleared | AE20: R-471420 | AF20: B-8691 | AG20: CVG-2010 | AH20: Samy Talaat Barakat- CVG 2010 | AI20: 298069 | AJ20: 46148 | AK20: PDC | AL20: Creek Vistas Grande-Creek Vistas Grande | AM20: Omar | AN20: Sobha | AQ20: Sid Ahmed Kriket | AR20: Sid | AS20: Dues | AT20: Collector
A21: PR-0505363 | B21: IWT(International) | C21: 23000 | D21: SO-B2120 | E21: Oksana Stepanenko | F21: Approved | G21: 46148 | H21: B-21686 | I21: 2678347.2 | J21: 0 | K21: 0 | L21: 46147 | M21: 0 | N21: 0 | O21: 0 | P21: 23000 | Q21: Oksana | R21: Approved | S21: 0.5181003 | T21: Yes | U21: Sobha | V21: R-931352 | W21: Cleared | AE21: R-471955 | AF21: B-9458 | AG21: CVG-2801 | AH21: Jiahui Chuang CVG-2801 | AI21: 299905 | AJ21: 46148 | AK21: PDC | AL21: Creek Vistas Grande-Creek Vistas Grande | AM21: Omar | AN21: Sobha | AQ21: Vinod Kumar Karunakaran Pankajam | AR21: Vinod | AS21: Dues | AT21: Collector
A22: PR-0506024 | B22: DWT(Domestic) | C22: 100000 | D22: SO-B2120 | E22: Oksana Stepanenko | F22: Pending for Accounts Approval | G22: 46149 | H22: B-21686 | I22: 2678347.2 | J22: 0 | K22: 0 | L22: 46146 | M22: 0 | N22: 0 | O22: 0 | P22: 100000 | Q22: Oksana | R22: In process | S22: 0.5181003 | T22: Yes | U22: Sobha | V22: 0 | W22: 0 | AE22: R-471977 | AF22: B-10635 | AG22: CVG-1601 | AH22: Mr. Rajan Ashok Uttamchandani | AI22: 295797.6 | AJ22: 46148 | AK22: PDC | AL22: Creek Vistas Grande-Creek Vistas Grande | AM22: Omar | AN22: Sobha | AQ22: Zeba Begum | AR22: Zeba | AS22: Dues | AT22: Collector
A23: PR-0506017 | B23: DWT(Domestic) | C23: 100000 | D23: SO-B2120 | E23: Oksana Stepanenko | F23: Pending for Accounts Approval | G23: 46149 | H23: B-21686 | I23: 2678347.2 | J23: 0 | K23: 0 | L23: 46146 | M23: 0 | N23: 0 | O23: 0 | P23: 100000 | Q23: Oksana | R23: In process | S23: 0.5181003 | T23: Yes | U23: Sobha | V23: 0 | W23: 0 | AE23: R-472538 | AF23: B-9113 | AG23: CVG-3702 | AH23: Ms. Tam Malin Maria Holmstrom | AI23: 223287 | AJ23: 46148 | AK23: PDC | AL23: Creek Vistas Grande-Creek Vistas Grande | AM23: Omar | AN23: Sobha | AQ23: Nijish Achuthan | AR23: Nijish | AS23: Dues | AT23: Collector
A24: PR-0506008 | B24: DWT(Domestic) | C24: 15000 | D24: SO-B2120 | E24: Oksana Stepanenko | F24: Pending for Accounts Approval | G24: 46149 | H24: B-21686 | I24: 2678347.2 | J24: 0 | K24: 0 | L24: 46147 | M24: 0 | N24: 0 | O24: 0 | P24: 15000 | Q24: Oksana | R24: In process | S24: 0.5181003 | T24: Yes | U24: Sobha | V24: 0 | W24: 0 | AE24: R-472553 | AF24: B-10171 | AG24: CVG-2501 | AH24: Mr. Ruodi Hu | AI24: 299906 | AJ24: 46148 | AK24: PDC | AL24: Creek Vistas Grande-Creek Vistas Grande | AM24: Omar | AN24: Sobha | AQ24: Anna Serova | AR24: Anna | AS24: Dues | AT24: Collector
A25: PR-0504234 | B25: OTC Deposit(Cash counter) | C25: 784857 | D25: SO-D918 | E25: Julius Santoline Noronha | F25: Approved | G25: 46146 | H25: B-17486 | I25: 2049978 | J25: 46146 | K25: 0 | L25: 0 | M25: 0 | N25: 0 | O25: 0 | P25: 784857 | Q25: Ateev | R25: Approved | S25: 0.98286122 | T25: Yes | U25: Sobha | V25: R-922475 | W25: Cleared | AE25: R-474622 | AF25: B-10877 | AG25: CVG-3205 | AH25: Bilal Ahmed Jamel Ahmed | AI25: 202905 | AJ25: 46148 | AK25: PDC | AL25: Creek Vistas Grande-Creek Vistas Grande | AM25: Omar | AN25: Sobha | AQ25: Melvyn Martin Joseph Fernandes | AR25: Melvyn | AS25: Dues | AT25: Collector
A26: PR-0504914 | B26: DWT(Domestic) | C26: 226130 | D26: SO-E1412 | E26: Vinod Kumar Karunakaran Pankajam | F26: Resubmitted to SM/SD | G26: 46147 | H26: B-22286 | I26: 2639721 | J26: 0 | K26: 0 | L26: 46125 | M26: 0 | N26: 0 | O26: 0 | P26: 226130 | Q26: Vinod | R26: Resubmitted | S26: 0.37345831 | T26: Yes | U26: Sobha | V26: 0 | W26: 0 | AE26: R-476031 | AF26: B-8683 | AG26: CVG-1609 | AH26: Nadin Essam Loutfy Elsaid Elnaggar CVG-1609 | AI26: 140293.81 | AJ26: 46148 | AK26: PDC | AL26: Creek Vistas Grande-Creek Vistas Grande | AM26: Omar | AN26: Sobha | AQ26: Monish Mangalore | AR26: Monish | AS26: Dues | AT26: Collector
A27: PR-0504906 | B27: DWT(Domestic) | C27: 107801 | D27: SO-E1412 | E27: Vinod Kumar Karunakaran Pankajam | F27: Resubmitted to SM/SD | G27: 46147 | H27: B-22286 | I27: 2639721 | J27: 0 | K27: 0 | L27: 46119 | M27: 0 | N27: 0 | O27: 0 | P27: 107801 | Q27: Vinod | R27: Resubmitted | S27: 0.37345831 | T27: Yes | U27: Sobha | V27: 0 | W27: 0 | AE27: R-476048 | AF27: B-8669 | AG27: CVG-1204 | AH27: JHUMA | AI27: 137583 | AJ27: 46148 | AK27: PDC | AL27: Creek Vistas Grande-Creek Vistas Grande | AM27: Omar | AN27: Sobha | AQ27: WALID YASSIN | AR27: Walid | AS27: Dues | AT27: Collector
A28: PR-0505543 | B28: DWT(Domestic) | C28: 100000 | D28: VER-3406 | E28: Mukhammad Yusuf Mirjalil | F28: Approved | G28: 46148 | H28: B-19930 | I28: 2156713.4 | J28: 0 | K28: 0 | L28: 46148 | M28: 0 | N28: 0 | O28: 0 | P28: 100000 | Q28: Yusuf | R28: Approved | S28: 0.64636715 | T28: Yes | U28: Sobha | V28: R-931107 | W28: Cleared | AE28: R-476049 | AF28: B-8615 | AG28: CVG-2502 | AH28: Ms. Huihui Ding | AI28: 220270 | AJ28: 46148 | AK28: PDC | AL28: Creek Vistas Grande-Creek Vistas Grande | AM28: Omar | AN28: Sobha | AQ28: Mohammed Abdulla | AR28: Abdulla | AS28: Advance | AT28: Collector
A29: PR-0505539 | B29: DWT(Domestic) | C29: 115671 | D29: VER-3406 | E29: Mukhammad Yusuf Mirjalil | F29: Pending for Accounts Approval | G29: 46148 | H29: B-19930 | I29: 2156713.4 | J29: 0 | K29: 0 | L29: 46148 | M29: 0 | N29: 0 | O29: 0 | P29: 115671 | Q29: Yusuf | R29: In process | S29: 0.64636715 | T29: Yes | U29: Sobha | V29: 0 | W29: 0 | AE29: R-476074 | AF29: B-10014 | AG29: CVG-1306 | AH29: Mr. Teimuraz Grigolava | AI29: 151911 | AJ29: 46148 | AK29: PDC | AL29: Creek Vistas Grande-Creek Vistas Grande | AM29: Omar | AN29: Sobha | AQ29: Ateev Mehra | AR29: Ateev | AS29: Advance | AT29: Collector
A30: PR-0504709 | B30: OTC Deposit(Cash counter) | C30: 220000 | D30: VER-6006 | E30: Julius Santoline Noronha | F30: Approved | G30: 46147 | H30: B-18729 | I30: 2119684.9 | J30: 46147 | K30: 0 | L30: 0 | M30: 0 | N30: 0 | O30: 0 | P30: 220000 | Q30: Yusuf | R30: Approved | S30: 0.70676986 | T30: Yes | U30: Sobha | V30: R-922752 | W30: Cleared | AE30: R-477524 | AF30: B-9911 | AG30: CVG-3309 | AH30: Jurgen Riesel | AI30: 144191 | AJ30: 46148 | AK30: PDC | AL30: Creek Vistas Grande-Creek Vistas Grande | AM30: Omar | AN30: Sobha | AQ30: Mohamed Ayari | AR30: Ayari | AS30: Advance | AT30: Collector
A31: PR-0505321 | B31: Website | C31: 200 | D31: VER-6006 | E31: Sobha One App | F31: Rejected by System | G31: 46148 | H31: B-18729 | I31: 2119684.9 | J31: 46148 | K31: 0 | L31: 46148 | M31: 0 | N31: 0 | O31: Unit Price | P31: 200 | Q31: Yusuf | R31: Rejected | S31: 0.70676986 | T31: Yes | U31: Sobha | V31: 0 | W31: 0 | AE31: R-478617 | AF31: B-8991 | AG31: CVG-3701 | AH31: Kcendzov Semen | AI31: 304014 | AJ31: 46148 | AK31: PDC | AL31: Creek Vistas Grande-Creek Vistas Grande | AM31: Omar | AN31: Sobha | AQ31: Basma Metwally | AR31: Basma | AS31: Advance | AT31: Collector
A32: PR-0505329 | B32: Website | C32: 200 | D32: VER-6006 | E32: Sobha One App | F32: Rejected by System | G32: 46148 | H32: B-18729 | I32: 2119684.9 | J32: 46148 | K32: 0 | L32: 46148 | M32: 0 | N32: 0 | O32: Unit Price | P32: 200 | Q32: Yusuf | R32: Rejected | S32: 0.70676986 | T32: Yes | U32: Sobha | V32: 0 | W32: 0 | AE32: R-480630 | AF32: B-10349 | AG32: CVG-203 | AH32: Ms. Sumana Devi Vijay Kumar | AI32: 206557 | AJ32: 46148 | AK32: PDC | AL32: Creek Vistas Grande-Creek Vistas Grande | AM32: Omar | AN32: Sobha | AQ32: Jaidev Rajesh Shah | AR32: Jaidev | AS32: Advance | AT32: Collector
A33: PR-0505858 | B33: IWT(International) | C33: 10000 | D33: CVH-A909 | E33: Ateev Mehra | F33: Pending for Accounts Approval | G33: 46149 | H33: B-16768 | I33: 2084802.8 | J33: 0 | K33: 0 | L33: 46148 | M33: 0 | N33: 0 | O33: 0 | P33: 10000 | Q33: Ateev | R33: In process | S33: 0.76543556 | T33: Yes | U33: Sobha | V33: 0 | W33: 0 | AE33: R-481220 | AF33: B-8660 | AG33: CVG-2109 | AH33: Mr. Yahia Abdel Moneim Kabil | AI33: 142242 | AJ33: 46148 | AK33: PDC | AL33: Creek Vistas Grande-Creek Vistas Grande | AM33: Omar | AN33: Sobha | AQ33: Krizia Leah Nikita Collin | AR33: Krizia | AS33: Advance | AT33: Collector
A34: PR-0504521 | B34: IWT(International) | C34: 210757 | D34: SO-B4808 | E34: Oksana Stepanenko | F34: Approved | G34: 46147 | H34: B-26887 | I34: 4215181.3 | J34: 0 | K34: 0 | L34: 46147 | M34: 0 | N34: 0 | O34: 0 | P34: 210757 | Q34: Oksana | R34: Approved | S34: 0.39999989 | T34: Yes | U34: Sobha | V34: R-931362 | W34: Cleared | AE34: R-481589 | AF34: B-11016 | AG34: CVG-3707 | AH34: prashant Dixit | AI34: 231565 | AJ34: 46148 | AK34: PDC | AL34: Creek Vistas Grande-Creek Vistas Grande | AM34: Omar | AN34: Sobha | AQ34: Nischitha | AR34: Nischitha | AS34: Advance | AT34: Collector
A35: PR-0505501 | B35: DWT(Domestic) | C35: 36466 | D35: SO-C1516 | E35: Oksana Stepanenko | F35: Approved | G35: 46148 | H35: B-33018 | I35: 3364664 | J35: 0 | K35: 0 | L35: 46144 | M35: 0 | N35: 0 | O35: 0 | P35: 36466 | Q35: Oksana | R35: Approved | S35: 0.39999982 | T35: Yes | U35: Sobha | V35: R-930989 | W35: Cleared | AE35: R-481597 | AF35: B-8666 | AG35: CVG-2510 | AH35: Mr.Mehdi Hassan Issa Rammal | AI35: 150062 | AJ35: 46148 | AK35: PDC | AL35: Creek Vistas Grande-Creek Vistas Grande | AM35: Omar | AN35: Sobha | AQ35: Noha Elhattab | AR35: Noha | AS35: Advance | AT35: Collector
A36: PR-0503673 | B36: IWT(International) | C36: 450000 | D36: SO-C3409 | E36: Ateev Mehra | F36: Approved | G36: 46146 | H36: B-48375 | I36: 1830528 | J36: 0 | K36: 0 | L36: 46145 | M36: 0 | N36: 0 | O36: 0 | P36: 450000 | Q36: Ateev | R36: Approved | S36: 0.93686412 | T36: Yes | U36: Sobha | V36: R-922114 | W36: Cleared | AE36: R-481606 | AF36: B-8665 | AG36: CVG-2209 | AH36: Mr.Mehdi Hassan Issa Rammal | AI36: 142242 | AJ36: 46148 | AK36: PDC | AL36: Creek Vistas Grande-Creek Vistas Grande | AM36: Omar | AN36: Sobha | AQ36: Sherif Zaki | AR36: Sherif | AS36: Advance | AT36: Collector
A37: PR-0504096 | B37: IWT(International) | C37: 450000 | D37: SO-C3409 | E37: Ateev Mehra | F37: Approved | G37: 46146 | H37: B-48375 | I37: 1830528 | J37: 0 | K37: 0 | L37: 46146 | M37: 0 | N37: 0 | O37: 0 | P37: 450000 | Q37: Ateev | R37: Approved | S37: 0.93686412 | T37: Yes | U37: Sobha | V37: R-923250 | W37: Cleared | AE37: R-482580 | AF37: B-8858 | AG37: CVG-910 | AH37: Mary Ann Beltran Lapuz CVG-910 | AI37: 148006.8 | AJ37: 46148 | AK37: PDC | AL37: Creek Vistas Grande-Creek Vistas Grande | AM37: Omar | AN37: Sobha | AQ37: Vijay Narayanan Pillai | AR37: Vijay | AS37: Advance | AT37: Collector
A38: PR-0504722 | B38: IWT(International) | C38: 450000 | D38: SO-C3409 | E38: Ateev Mehra | F38: Approved | G38: 46147 | H38: B-48375 | I38: 1830528 | J38: 0 | K38: 0 | L38: 46147 | M38: 0 | N38: 0 | O38: 0 | P38: 450000 | Q38: Ateev | R38: Approved | S38: 0.93686412 | T38: Yes | U38: Sobha | V38: R-931036 | W38: Cleared | AE38: R-483247 | AF38: B-8607 | AG38: CVG-3109 | AH38: DANIL ANISIMOV - CVG 3109 - (New) | AI38: 144191 | AJ38: 46148 | AK38: PDC | AL38: Creek Vistas Grande-Creek Vistas Grande | AM38: Omar | AN38: Sobha | AQ38: Wael Mohamed Abdelmonem Ramadan | AR38: Wael | AS38: Advance | AT38: Collector
A39: PR-0506228 | B39: IWT(International) | C39: 77622 | D39: SO-C3409 | E39: Ateev Mehra | F39: Pending for Accounts Approval | G39: 46149 | H39: B-48375 | I39: 1830528 | J39: 0 | K39: 0 | L39: 46149 | M39: 0 | N39: 0 | O39: 0 | P39: 77622 | Q39: Ateev | R39: In process | S39: 0.93686412 | T39: Yes | U39: Sobha | V39: 0 | W39: 0 | AE39: R-483798 | AF39: B-8869 | AG39: CVG-3809 | AH39: JOHN VIYANI GREGORY - CVG-3809 | AI39: 144191 | AJ39: 46148 | AK39: PDC | AL39: Creek Vistas Grande-Creek Vistas Grande | AM39: Omar | AN39: Sobha | AQ39: Yogesh Karande | AR39: Yogesh | AS39: Advance | AT39: Collector
A40: PR-0504649 | B40: DWT(Domestic) | C40: 210020 | D40: SO-C2409 | E40: Ateev Mehra | F40: Approved | G40: 46147 | H40: B-23542 | I40: 2208232 | J40: 0 | K40: 0 | L40: 46147 | M40: 0 | N40: 0 | O40: 0 | P40: 210020 | Q40: Ateev | R40: Approved | S40: 0.59927399 | T40: Yes | U40: Sobha | V40: R-930982 | W40: Cleared | AE40: R-484084 | AF40: B-10685 | AG40: CVG-2907 | AH40: Minnie Bodhanwala | AI40: 228393 | AJ40: 46148 | AK40: PDC | AL40: Creek Vistas Grande-Creek Vistas Grande | AM40: Omar | AN40: Sobha | AQ40: Rohan Nair | AR40: Rohan | AS40: Dues | AT40: Manager
A41: PR-0505232 | B41: DWT(Domestic) | C41: 300000 | D41: SO-E4201 | E41: Mohammed Abdulla | F41: Approved | G41: 46148 | H41: B-22790 | I41: 3045952 | J41: 0 | K41: 0 | L41: 46148 | M41: 0 | N41: 0 | O41: 0 | P41: 300000 | Q41: Abdulla | R41: Approved | S41: 0.90164593 | T41: Yes | U41: Sobha | V41: R-931052 | W41: Cleared | AE41: R-484620 | AF41: B-9138 | AG41: CVG-2802 | AH41: LIHUA FAN | AI41: 220270 | AJ41: 46148 | AK41: PDC | AL41: Creek Vistas Grande-Creek Vistas Grande | AM41: Omar | AN41: Sobha | AQ41: Karan Kohli | AR41: Karan Kohli | AS41: Dues | AT41: Manager
A42: PR-0505226 | B42: DWT(Domestic) | C42: 300000 | D42: SO-E4201 | E42: Mohammed Abdulla | F42: Approved | G42: 46148 | H42: B-22790 | I42: 3045952 | J42: 0 | K42: 0 | L42: 46146 | M42: 0 | N42: 0 | O42: 0 | P42: 300000 | Q42: Abdulla | R42: Approved | S42: 0.90164593 | T42: Yes | U42: Sobha | V42: R-931329 | W42: Cleared | AE42: R-485114 | AF42: B-9758 | AG42: CVG-1909 | AH42: GULNAWAZ AAMIR | AI42: 140294 | AJ42: 46148 | AK42: PDC | AL42: Creek Vistas Grande-Creek Vistas Grande | AM42: Omar | AN42: Sobha | AQ42: Manuraj Chouhan | AR42: Manuraj | AS42: Advance | AT42: Manager
A43: PR-0505220 | B43: DWT(Domestic) | C43: 300000 | D43: SO-E4201 | E43: Mohammed Abdulla | F43: Approved | G43: 46148 | H43: B-22790 | I43: 3045952 | J43: 0 | K43: 0 | L43: 46147 | M43: 0 | N43: 0 | O43: 0 | P43: 300000 | Q43: Abdulla | R43: Approved | S43: 0.90164593 | T43: Yes | U43: Sobha | V43: R-931222 | W43: Cleared | AE43: R-487042 | AF43: B-10165 | AG43: CVG-404 | AH43: Mohammed Youssef Mohammed Abouelmagd Khashaba CVG-404 | AI43: 160522 | AJ43: 46148 | AK43: PDC | AL43: Creek Vistas Grande-Creek Vistas Grande | AM43: Omar | AN43: Sobha
A44: PR-0504642 | B44: DWT(Domestic) | C44: 150000 | D44: SO-D2415 | E44: Ahmed Abdellatif Mahmoud Elhanafy Shokil | F44: Approved | G44: 46147 | H44: B-26547 | I44: 2589724.8 | J44: 0 | K44: 0 | L44: 46147 | M44: 0 | N44: 0 | O44: 0 | P44: 150000 | Q44: Abdellatif | R44: Approved | S44: 0.5000207 | T44: Yes | U44: Sobha | V44: R-923182 | W44: Cleared | AE44: R-487589 | AF44: B-8552 | AG44: CVG-3409 | AH44: ANAND SADASIVA IYER | AI44: 144191 | AJ44: 46148 | AK44: PDC | AL44: Creek Vistas Grande-Creek Vistas Grande | AM44: Omar | AN44: Sobha
A45: PR-0505432 | B45: DWT(Domestic) | C45: 109000 | D45: SO-D2415 | E45: Ahmed Abdellatif Mahmoud Elhanafy Shokil | F45: Approved | G45: 46148 | H45: B-26547 | I45: 2589724.8 | J45: 0 | K45: 0 | L45: 46148 | M45: 0 | N45: 0 | O45: 0 | P45: 109000 | Q45: Abdellatif | R45: Approved | S45: 0.5000207 | T45: Yes | U45: Sobha | V45: R-931297 | W45: Cleared | AE45: R-487604 | AF45: B-9718 | AG45: CVG-1108 | AH45: Mr. Yiping Zhang | AI45: 224847 | AJ45: 46148 | AK45: PDC | AL45: Creek Vistas Grande-Creek Vistas Grande | AM45: Omar | AN45: Sobha
A46: PR-0505791 | B46: DWT(Domestic) | C46: 109000 | D46: SO-D2415 | E46: Ahmed Abdellatif Mahmoud Elhanafy Shokil | F46: Pending for Accounts Approval | G46: 46149 | H46: B-26547 | I46: 2589724.8 | J46: 0 | K46: 0 | L46: 46148 | M46: 0 | N46: 0 | O46: 0 | P46: 109000 | Q46: Abdellatif | R46: In process | S46: 0.5000207 | T46: Yes | U46: Sobha | V46: 0 | W46: 0 | AE46: R-488149 | AF46: B-8799 | AG46: CVG-1503 | AH46: ELNUR NURITDNOV | AI46: 132882 | AJ46: 46148 | AK46: PDC | AL46: Creek Vistas Grande-Creek Vistas Grande | AM46: Omar | AN46: Sobha
A47: PR-0504869 | B47: Credit Card | C47: 40871 | D47: SO-D2815 | E47: Farheen Parveen | F47: Resubmitted to SM/SD | G47: 46147 | H47: B-24966 | I47: 2608861.6 | J47: 0 | K47: 0 | L47: 0 | M47: 0 | N47: 0 | O47: 0 | P47: 40871 | Q47: Farheen | R47: Resubmitted | S47: 0.40000589 | T47: Yes | U47: Sobha | V47: 0 | W47: 0 | AE47: R-488872 | AF47: B-9786 | AG47: CVG-3308 | AH47: PRIYANKA VYAS | AI47: 231093 | AJ47: 46148 | AK47: PDC | AL47: Creek Vistas Grande-Creek Vistas Grande | AM47: Omar | AN47: Sobha
A48: PR-0504862 | B48: Credit Card | C48: 80000 | D48: SO-D2815 | E48: Farheen Parveen | F48: Resubmitted to SM/SD | G48: 46147 | H48: B-24966 | I48: 2608861.6 | J48: 0 | K48: 0 | L48: 0 | M48: 0 | N48: 0 | O48: 0 | P48: 80000 | Q48: Farheen | R48: Resubmitted | S48: 0.40000589 | T48: Yes | U48: Sobha | V48: 0 | W48: 0 | AE48: R-488878 | AF48: B-9186 | AG48: CVG-1009 | AH48: Rehaaan Nensey | AI48: 140294 | AJ48: 46148 | AK48: PDC | AL48: Creek Vistas Grande-Creek Vistas Grande | AM48: Omar | AN48: Sobha
A49: PR-0504855 | B49: Credit Card | C49: 140000 | D49: SO-D2815 | E49: Farheen Parveen | F49: Resubmitted to SM/SD | G49: 46147 | H49: B-24966 | I49: 2608861.6 | J49: 0 | K49: 0 | L49: 0 | M49: 0 | N49: 0 | O49: 0 | P49: 140000 | Q49: Farheen | R49: Resubmitted | S49: 0.40000589 | T49: Yes | U49: Sobha | V49: 0 | W49: 0 | AE49: R-488881 | AF49: B-9262 | AG49: CVG-2608 | AH49: Alsafan textile trading . | AI49: 227970 | AJ49: 46148 | AK49: PDC | AL49: Creek Vistas Grande-Creek Vistas Grande | AM49: Omar | AN49: Sobha
A50: PR-0506038 | B50: IWT(International) | C50: 30000 | D50: 330 RSC-814 | E50: Hussein Moawad | F50: Pending for Accounts Approval | G50: 46149 | H50: B-18058 | I50: 1501815 | J50: 0 | K50: 0 | L50: 46147 | M50: 0 | N50: 0 | O50: 0 | P50: 30000 | Q50: Hussein | R50: In process | S50: 0.65671937 | T50: Yes | U50: Sobha | V50: 0 | W50: 0 | AE50: R-493861 | AF50: B-9224 | AG50: CVG-904 | AH50: Valeriy Khegay | AI50: 139520 | AJ50: 46148 | AK50: PDC | AL50: Creek Vistas Grande-Creek Vistas Grande | AM50: Omar | AN50: Sobha
A51: PR-0506011 | B51: IWT(International) | C51: 7647 | D51: 330 RSC-814 | E51: Hussein Moawad | F51: Pending for Accounts Approval | G51: 46149 | H51: B-18058 | I51: 1501815 | J51: 0 | K51: 0 | L51: 46142 | M51: 0 | N51: 0 | O51: 0 | P51: 7647 | Q51: Hussein | R51: In process | S51: 0.65671937 | T51: Yes | U51: Sobha | V51: 0 | W51: 0 | AE51: R-493826 | AF51: B-23829 | AG51: CVG-3310 | AH51: Francesco Grillo | AI51: 152118 | AJ51: 46148 | AK51: PDC | AL51: Creek Vistas Grande-Creek Vistas Grande | AM51: Omar | AN51: Sobha
A52: PR-0503990 | B52: IWT(International) | C52: 174212 | D52: 330 RSC-1001 | E52: Sobha One App | F52: Resubmitted to SM/SD | G52: 46146 | H52: B-33910 | I52: 1742118 | J52: 46146 | K52: 0 | L52: 46146 | M52: 0 | N52: 0 | O52: Unit Price | P52: 174212 | Q52: Hussein | R52: Resubmitted | S52: 0.28583214 | T52: Yes | U52: Sobha | V52: 0 | W52: 0 | AE52: R-493851 | AF52: B-8721 | AG52: CVG-3910 | AH52: Mr. Jihad Mohamad Hassan | AI52: 152118.1 | AJ52: 46148 | AK52: PDC | AL52: Creek Vistas Grande-Creek Vistas Grande | AM52: Omar | AN52: Sobha
A53: PR-0502885 | B53: DWT(Domestic) | C53: 19500 | D53: 330 RSC-1008 | E53: Lamis Amamra | F53: Resubmitted to SM/SD | G53: 46143 | H53: B-17394 | I53: 1870528 | J53: 0 | K53: 0 | L53: 46079 | M53: 0 | N53: 0 | O53: 0 | P53: 19500 | Q53: Lamis | R53: Resubmitted | S53: 0.66017182 | T53: Yes | U53: Sobha | V53: 0 | W53: 0 | AE53: R-507555 | AF53: B-8762 | AG53: CVG-3403 | AH53: GULNARA ZUFEROVNA BERG | AI53: 136625 | AJ53: 46148 | AK53: PDC | AL53: Creek Vistas Grande-Creek Vistas Grande | AM53: Omar | AN53: Sobha
A54: PR-0503077 | B54: DWT(Domestic) | C54: 30000 | D54: 330 RSC-1008 | E54: Lamis Amamra | F54: Resubmitted to SM/SD | G54: 46144 | H54: B-17394 | I54: 1870528 | J54: 0 | K54: 0 | L54: 46065 | M54: 0 | N54: 0 | O54: 0 | P54: 30000 | Q54: Lamis | R54: Resubmitted | S54: 0.66017182 | T54: Yes | U54: Sobha | V54: 0 | W54: 0 | AE54: R-515655 | AF54: B-9466 | AG54: CVG-1308 | AH54: ELENA CARMEN POPESCU | AI54: 224847 | AJ54: 46153 | AK54: PDC | AL54: Creek Vistas Grande-Creek Vistas Grande | AM54: Omar | AN54: Sobha
A55: PR-0503076 | B55: DWT(Domestic) | C55: 25000 | D55: 330 RSC-1008 | E55: Lamis Amamra | F55: Resubmitted to SM/SD | G55: 46144 | H55: B-17394 | I55: 1870528 | J55: 0 | K55: 0 | L55: 46075 | M55: 0 | N55: 0 | O55: 0 | P55: 25000 | Q55: Lamis | R55: Resubmitted | S55: 0.66017182 | T55: Yes | U55: Sobha | V55: 0 | W55: 0 | AE55: R-518725 | AF55: B-8963 | AG55: CVG-3703 | AH55: OLGA BARKHUDAROVA- CVG3703 | AI55: 136625 | AJ55: 46148 | AK55: PDC | AL55: Creek Vistas Grande-Creek Vistas Grande | AM55: Omar | AN55: Sobha
A56: PR-0503834 | B56: CDM Cash (Cash Deposit in Machine) | C56: 3000 | D56: 330 RSC-1209 | E56: Hussein Moawad | F56: Approved | G56: 46146 | H56: B-24105 | I56: 1856812.4 | J56: 46097 | K56: 0 | L56: 46097 | M56: 0 | N56: 0 | O56: 0 | P56: 3000 | Q56: Hussein | R56: Approved | S56: 0.50002576 | T56: Yes | U56: Sobha | V56: R-922402 | W56: Cleared | AE56: R-521744 | AF56: B-8698 | AG56: CVG-3903 | AH56: Montrose Properties Limited | AI56: 136625 | AJ56: 46148 | AK56: PDC | AL56: Creek Vistas Grande-Creek Vistas Grande | AM56: Omar | AN56: Sobha
A57: PR-0504037 | B57: OTC Deposit(Cash counter) | C57: 110000 | D57: 330 RSC-1310 | E57: Julius Santoline Noronha | F57: Approved | G57: 46146 | H57: B-16698 | I57: 1630550.1 | J57: 46146 | K57: 0 | L57: 0 | M57: 0 | N57: 0 | O57: 0 | P57: 110000 | Q57: Basma | R57: Approved | S57: 0.76746884 | T57: Yes | U57: Sobha | V57: R-922163 | W57: Cleared | AE57: R-523808 | AF57: B-11078 | AG57: CVG-2507 | AH57: Montrose Properties Limited | AI57: 228394 | AJ57: 46148 | AK57: PDC | AL57: Creek Vistas Grande-Creek Vistas Grande | AM57: Omar | AN57: Sobha
